Workbook

Sheet Checklist
A1: # | B1: Task | C1: Responsible | D1: When? | E1: Status
A2: 1 | B2: Paid Community Data | C2: Himanshu | D2: Pre launch | E2: Completed
A3: 2 | B3: Static code deployment | C3: Mahir | D3: Pre launch | E3: WIP
A4: 3 | B4: Cron jobs | C4: Mahir | D4: Pre launch | E4: WIP
A5: 4 | B5: International Payments | C5: Mahir | D5: Pre launch | E5: Completed
A6: 5 | B6: Old data from Excel | C6: Himanshu | D6: Pre launch | E6: Completed
A7: 6 | B7: Old data from Airtable | C7: Himanshu | D7: Pre launch | E7: Completed
A8: 7 | B8: Well being data from airtable | C8: Himanshu | D8: Pre launch | E8: Completed
A9: 8 | B9: Remove testing data | C9: Himanshu | D9: Pre launch | E9: Completed
A10: 9 | B10: Data migration script for old data | C10: Mahir | D10: Pre launch | E10: Pending
A11: 10 | B11: Offset handling script for current members + CM + Owner (create subscription models) | C11: Mahir | D11: Launch | E11: Pending
A12: 11 | B12: Exempted user list | C12: Himanshu | D12: Pre launch | E12: WIP
A13: 12 | B13: Active plan List from webflow CMS | C13: Himanshu | D13: Pre launch | E13: Completed
... A24: 23 | B24: Accepting event payments in transaction table | C24: Mahir | D24: Post Launch | E24: Pending
A25: 24 | B25: Dont remove python geek yet | C25: Himanshu | E25: Pending
A26: 25 | B26: Community Migration cases - Unchai + Garv | C26: Himanshu | D26: Post Launch | E26: Pending
A27: 26 | B27: Manage Refunds | C27: Himanshu | D27: Pre launch | E27: Pending
A28: 27 | B28: Email CM about the release plan + free till 30th (Android only) | C28: Himanshu | D28: Pre launch | E28: Pending
A29: 28 | B29: Create excel for sql plan data | C29: Himanshu | D29: Pre launch | E29: Completed
A30: 29 | B30: Email CM about the release plan + free till 7th July (iOS only) | C30: Himanshu | D30: Post Launch | E30: Pending
A31: 30 | B31: Events for subscriptions segment | C31: Mahir | E31: Pending
A32: 31 | B32: is removbed case for cron job | C32: Himanshu | D32: Pre launch | E32: Completed

Sheet User data - excel
A1: payment_id | B1: plan_id | C1: Community Name | D1: Community_id | E1: plan_name | F1: plan_duration | G1: plan_cost | H1: renew | I1: amount | J1: email | K1: contact | L1: currency | M1: is_international | N1: method | O1: status | P1: created_at | Q1: Users | R1: payment_page_url
A2: pay_GMMPqMJQVOgxYx | C2: Defence tribe | D2: 49831 | F2: Quarterly Plan Plan | G2: 299 | I2: 299 | J2: vedanshved25dec@gmail.com | K2: 917270913144 | L2: INR | M2: FALSE | N2: upi | O2: captured | P2: 44203.607 | Q2: 3372
A3: pay_GMMajKdG9UC7y0 | C3: Defence tribe | D3: 49831 | F3: Quarterly Plan Plan | G3: 299 | I3: 299 | J3: deepakkumar3624@gmail.com | K3: 919717802505 | L3: INR | M3: FALSE | N3: upi | O3: captured | P3: 44203.614 | Q3: 2827
A4: pay_GMRtiGOOiByLTp | C4: Defence tribe | D4: 49831 | F4: Quarterly Plan Plan | G4: 299 | I4: 299 | J4: dalalnishant2@gmail.com | K4: 918168803701 | L4: INR | M4: FALSE | N4: card | O4: captured | P4: 44203.83 | Q4: 3186
A5: pay_GNCHuNu1kJ0zaa | C5: Deutsch In Tandem | D5: 49834 | F5: Half Yearly Plan | G5: 499 | I5: 499 | J5: yogitash22@gmail.com | K5: 918800718020 | L5: INR | M5: FALSE | N5: upi | O5: captured | P5: 44205.721 | Q5: 3250
A6: pay_GNd6dnCUooNQKs | C6: Defence tribe | D6: 49831 | F6: Quarterly Plan Plan | G6: 299 | I6: 299 | J6: hdsinghima@gmail.com | K6: 916005739437 | L6: INR | M6: FALSE | N6: card | O6: captured | P6: 44206.814 | Q6: 1966
A7: pay_GOQEpIS7XcKoir | C7: Defence tribe | D7: 49831 | F7: Quarterly Plan Plan | G7: 299 | I7: 299 | J7: lkmdbani@gmail.com | K7: 918427297182 | L7: INR | M7: FALSE | N7: card | O7: captured | P7: 44208.817 | Q7: NF V2
A8: pay_GPTXtXi4wSTtNa | C8: Deutsch In Tandem | D8: 49834 | F8: Quarterly Plan | G8: 299 | I8: 299 | J8: khanolkardivya@gmail.com | K8: 916263018296 | L8: INR | M8: FALSE | N8: upi | O8: captured | P8: 44211.478 | Q8: 3762
A9: pay_GPy0NlVHv4QR0L | C9: Defence tribe | D9: 49831 | F9: Quarterly Plan Plan | G9: 299 | I9: 299 | J9: padmeshsavaratkar3256@gmail.com | K9: 917218040940 | L9: INR | M9: FALSE | N9: upi | O9: captured | P9: 44212.72 | Q9: 3781
A10: pay_GR4mKgIV1C5RN5 | C10: Defence tribe | D10: 49831 | F10: Quarterly Plan Plan | G10: 299 | I10: 299 | J10: prathampatel7700@gmail.com | K10: 919009992720 | L10: INR | M10: FALSE | N10: upi | O10: captured | P10: 44215.523 | Q10: 4197
A11: pay_GRqz0J18NyaIQD | C11: Defence tribe | D11: 49831 | F11: Quarterly Plan Plan | G11: 299 | I11: 299 | J11: ashishbisht336@gmail.com | K11: 918171705580 | L11: INR | M11: FALSE | N11: upi | O11: captured | P11: 44217.488 | Q11: 4697
A12: pay_GRvBKZGHwgPRjm | C12: Defence tribe | D12: 49831 | F12: Quarterly Plan Plan | G12: 299 | I12: 299 | J12: mauryanitesh484@gmail.com | K12: 917268085630 | L12: INR | M12: FALSE | N12: upi | O12: captured | P12: 44217.659 | Q12: 4786
A13: pay_GSPU6pt7WJaZ5w | C13: Defence tribe | D13: 49831 | F13: Quarterly Plan Plan | G13: 299 | I13: 299 | J13: aniket.kulkarni2912@gmail.com | K13: 917383086100 | L13: INR | M13: FALSE | N13: netbanking | O13: captured | P13: 44218.894 | Q13: 5187
A14: pay_GTAIl8R5CKBaBV | C14: Defence tribe | D14: 49831 | F14: Quarterly Plan Plan | G14: 299 | I14: 299 | J14: maheshdond1998@gmail.com | K14: 918668235424 | L14: INR | M14: FALSE | N14: upi | O14: captured | P14: 44220.802 | Q14: 5857
A15: pay_GUNy0tcPxVDLj1 | C15: Deutsch In Tandem | D15: 49834 | F15: Quarterly Plan | G15: 299 | I15: 299 | J15: akharbanda1@hotmail.com | K15: 918468909258 | L15: INR | M15: FALSE | N15: upi | O15: captured | P15: 44223.887 | Q15: 1954
A16: pay_GUZbjXvudoeP9s | C16: Defence tribe | D16: 49831 | F16: Quarterly Plan Plan | G16: 299 | I16: 299 | J16: sahilshaikh19702@gmail.com | K16: 919370569303 | L16: INR | M16: FALSE | N16: card | O16: captured | P16: 44224.361 | Q16: 6724
A17: pay_GV4jzgzMpB8TC4 | C17: Defence tribe | D17: 49831 | F17: Quarterly Plan Plan | G17: 299 | I17: 299 | J17: 56modinaren56@gmail.com | K17: 916396846910 | L17: INR | M17: FALSE | N17: netbanking | O17: captured | P17: 44225.63 | Q17: 7923
A18: pay_GVODTfpfo5aMnJ | C18: Deutsch In Tandem | D18: 49834 | F18: Quarterly Plan | G18: 299 | I18: 299 | J18: riyay4892@gmail.com | K18: 919959986457 | L18: INR | M18: FALSE | N18: upi | O18: captured | P18: 44226.424 | Q18: 6280
A19: pay_GVRCPtovigqIVp | C19: Deutsch In Tandem | D19: 49834 | F19: Quarterly Plan | G19: 299 | I19: 299 | J19: ku.rkrishna86@gmail.com | K19: 919074974588 | L19: INR | M19: FALSE | N19: upi | O19: captured | P19: 44226.545 | Q19: NF V2
A20: pay_GVVFZ0WR0ZCrEw | C20: Deutsch In Tandem | D20: 49834 | F20: Quarterly Plan | G20: 299 | I20: 299 | J20: sakshisharad01@gmail.com | K20: 917070989596 | L20: INR | M20: FALSE | N20: card | O20: captured | P20: 44226.71 | Q20: 9318
A21: pay_GVxsYaKlbtgSSk | C21: Defence tribe | D21: 49831 | F21: Quarterly Plan Plan | G21: 299 | I21: 299 | J21: msrathore245@gmail.com | K21: 918619552616 | L21: INR | M21: FALSE | N21: upi | O21: captured | P21: 44227.877 | Q21: 9249
A22: pay_GW6xiEDpehVAgv | C22: Deutsch In Tandem | D22: 49834 | F22: Half Yearly Plan | G22: 499 | I22: 499 | J22: vjagadeeshsurya9@gmail.com | K22: 918801416002 | L22: INR | M22: FALSE | N22: upi | O22: captured | P22: 44228.248 | Q22: 2204
A23: pay_GZ8ESWCuUQreEd | C23: Deutsch In Tandem | D23: 49834 | F23: Half Yearly Plan | G23: 499 | I23: 499 | J23: sushamavarghese2002@gmail.com | K23: 917592993781 | L23: INR | M23: FALSE | N23: upi | O23: captured | P23: 44235.881 | Q23: 11776
A24: pay_GZNVgRMMeT8onU | C24: Defence tribe | D24: 49831 | F24: Quarterly Plan Plan | G24: 299 | I24: 299 | J24: abhishektiwarippndc@gmail.com | K24: 919140600963 | L24: INR | M24: FALSE | N24: upi | O24: captured | P24: 44236.503 | Q24: 11830
A25: pay_GaGH4uY9r0ki7N | C25: Defence tribe | D25: 49831 | F25: Quarterly Plan Plan | G25: 299 | I25: 299 | J25: deepanshujhariya2@gmail.com | K25: 917879337462 | L25: INR | M25: FALSE | N25: upi | O25: captured | P25: 44238.735 | Q25: 12725
A26: pay_GaGL6h52VdxV33 | C26: Defence tribe | D26: 49831 | F26: Quarterly Plan Plan | G26: 299 | I26: 299 | J26: akashprajapati959819@gmail.com | K26: 918303205070 | L26: INR | M26: FALSE | N26: upi | O26: captured | P26: 44238.738 | Q26: 12741
A27: pay_GaJdX5gcvc0hza | C27: Deutsch In Tandem | D27: 49834 | F27: Quarterly Plan | G27: 299 | I27: 299 | J27: rheaa131@gmail.com | K27: 917990724041 | L27: INR | M27: FALSE | N27: upi | O27: captured | P27: 44238.873 | Q27: 4827
A28: pay_GaZLrT73PaUIbc | C28: Defence tribe | D28: 49831 | F28: Quarterly Plan Plan | G28: 299 | I28: 299 | J28: sksharma26121999@gmail.com | K28: 918273506739 | L28: INR | M28: FALSE | N28: upi | O28: captured | P28: 44239.513 | Q28: 12920
A29: pay_GaaJY8e9MsBTbQ | C29: Deutsch In Tandem | D29: 49834 | F29: Half Yearly Plan | G29: 499 | I29: 499 | J29: shivanibkdas@gmail.com | K29: 971505493883 | L29: INR | M29: FALSE | N29: card | O29: captured | P29: 44239.552 | Q29: 2133
A30: pay_GbucskLB1arRI6 | C30: Defence tribe | D30: 49831 | F30: Quarterly Plan Plan | G30: 299 | I30: 299 | J30: singhshashank199947@gmail.com | K30: 919354096048 | L30: INR | M30: FALSE | N30: upi | O30: captured | P30: 44242.907 | Q30: 14022
A31: pay_Gc8SndGFUF1kwZ | C31: Defence tribe | D31: 49831 | F31: Quarterly Plan Plan | G31: 299 | I31: 299 | J31: sonitsharma44@gmail.com | K31: 918868001977 | L31: INR | M31: FALSE | N31: upi | O31: captured | P31: 44243.471 | Q31: 14012
... A44: pay_Gho6SlmcgJ8pBD | C44: Defence tribe | D44: 49831 | F44: Quarterly Plan | G44: 499 | I44: 499 | J44: shvineet123@gmail.com | K44: 919310446765 | L44: INR | M44: FALSE | N44: upi | O44: captured | P44: 44257.804 | Q44: 15580
A45: pay_GiEluXNGNJIuZy | C45: Defence tribe | D45: 49831 | F45: Quarterly Plan | G45: 499 | I45: 499 | J45: girja.textiles@gmail.com | K45: 919322695468 | L45: INR | M45: FALSE | N45: card | O45: captured | P45: 44258.891 | Q45: NF V2
A46: pay_GiKGQvIEjyo6f4 | C46: Deutsch In Tandem | D46: 49834 | F46: Quarterly Plan | G46: 299 | I46: 299 | J46: mdatifalam4@gmail.com | K46: 917903350694 | L46: INR | M46: FALSE | N46: upi | O46: captured | P46: 44259.115 | Q46: 11297
A47: pay_GiZESjfLV3JEGB | C47: Deutsch In Tandem | D47: 49834 | F47: Quarterly Plan | G47: 299 | I47: 299 | J47: chirag34upqdhyay@gmail.com | K47: 917226918962 | L47: INR | M47: FALSE | N47: card | O47: captured | P47: 44259.725 | Q47: 16068
A48: pay_GiZR0CKP2WwoBa | C48: Defence Tribe | D48: 49831 | F48: Half Yearly Plan | G48: 799 | I48: 799 | J48: itzcuteansari@gmail.com | K48: 918318980567 | L48: INR | M48: FALSE | N48: upi | O48: captured | P48: 44259.733 | Q48: 16807
A49: pay_Gj3xrba3DwfjRb | C49: Deutsch In Tandem | D49: 49834 | F49: Quarterly Plan | G49: 299 | I49: 299 | J49: gr.venkateshyadav@gmail.com | K49: 919900049665 | L49: INR | M49: FALSE | N49: upi | O49: captured | P49: 44260.977 | Q49: 15838
A50: pay_Gk6gPvgP3OjcV3 | C50: Defence Tribe | D50: 49831 | F50: Half Yearly Plan | G50: 799 | I50: 799 | J50: morenilesh732@gmail.com | K50: 918766847954 | L50: INR | M50: FALSE | N50: upi | O50: captured | P50: 44263.615 | Q50: 15945
A51: pay_GyglY0KRtoIQ2s | C51: De battlers | D51: 49991 | F51: Monthly Plan | G51: 99 | I51: 99 | J51: araithatha3@gmail.com | K51: 919426320716 | L51: INR | M51: FALSE | N51: card | O51: captured | P51: 44300.465 | Q51: 16851
A52: pay_Gz8R6cdZRM5Uh1 | C52: De battlers | D52: 49991 | F52: Monthly Plan | G52: 99 | I52: 99 | J52: raniponmathip@yahoo.com | K52: 919710303309 | L52: INR | M52: FALSE | N52: upi | O52: captured | P52: 44301.593 | Q52: 16881
A53: pay_GpBsM14H3em3gQ | C53: Artists Commercialization | D53: 49864 | F53: Monthly Plan | G53: 99 | I53: 99 | J53: aishwarya.kulkarni23@gmail.com | K53: 919640252443 | L53: INR | M53: FALSE | N53: upi | O53: captured | P53: 44276.462 | Q53: 16389
A54: pay_GnGZpniHLVgRyc | C54: HanHangul | D54: 49833 | F54: Quarterly Plan | G54: 99 | I54: 99 | J54: tanmayee.maiya@gmail.com | K54: 919611611019 | L54: INR | M54: FALSE | N54: upi | O54: captured | P54: 44271.6 | Q54: 16307
A55: pay_GpGzmW4hRqSAdd | C55: Artists Commercialization | D55: 49864 | F55: Monthly Plan | G55: 99 | I55: 99 | J55: official.kpsingh@gmail.com | K55: 919501700310 | L55: INR | M55: FALSE | N55: card | O55: captured | P55: 44276.671 | Q55: 16473
A56: pay_GnJB9nKLOKPlks | C56: HanHangul | D56: 49833 | F56: Quarterly Plan | G56: 99 | I56: 99 | J56: rinhamuneer24@gmail.com | K56: 919108229430 | L56: INR | M56: FALSE | N56: upi | O56: captured | P56: 44271.706 | Q56: 16263
A57: pay_GpNHUIDGBDqvHZ | C57: Artists Commercialization | D57: 49864 | F57: Monthly Plan | G57: 99 | I57: 99 | J57: das.sagar15@gmail.com | K57: 919975696909 | L57: INR | M57: FALSE | N57: card | O57: captured | P57: 44276.927 | Q57: NF V2
A58: pay_GnKAEATxPDBpwq | C58: HanHangul | D58: 49833 | F58: Quarterly Plan | G58: 99 | I58: 99 | J58: debbie.roy9@gmail.com | K58: 919900800662 | L58: INR | M58: FALSE | N58: card | O58: captured | P58: 44271.746 | Q58: 16246
A59: pay_GnKEXYGHIeUjsw | C59: HanHangul | D59: 49833 | F59: Quarterly Plan | G59: 99 | I59: 99 | J59: subhashree.4991@gmail.com | K59: 919734664931 | L59: INR | M59: FALSE | N59: card | O59: captured | P59: 44271.749 | Q59: 8312
A60: pay_GnKN6sv0wMH790 | C60: Defence tribe | D60: 49831 | F60: Quarterly Plan | G60: 599 | I60: 599 | J60: er.shaktiprasadpatra@gmail.com | K60: 919348206965 | L60: INR | M60: FALSE | N60: netbanking | O60: captured | P60: 44271.755 | Q60: 16235
A61: pay_Gpw8g5EVBQQzdK | C61: Artists Commercialization | D61: 49864 | F61: Monthly Plan | G61: 99 | I61: 99 | J61: arttherapyformind@gmail.com | K61: 917829902114 | L61: INR | M61: FALSE | N61: netbanking | O61: captured | P61: 44278.348 | Q61: NF V2
A62: pay_GnO3mrfqXRmoQY | C62: HanHangul | D62: 49833 | F62: Quarterly Plan | G62: 99 | I62: 99 | J62: sprajahamsa@gmail.com | K62: 919591825002 | L62: INR | M62: FALSE | N62: upi | O62: captured | P62: 44271.905 | Q62: 16265
A63: pay_GnOFFJ981DHiX5 | C63: HanHangul | D63: 49833 | F63: Quarterly Plan | G63: 99 | I63: 99 | J63: amansawala14@gmail.com | K63: 919558836301 | L63: INR | M63: FALSE | N63: upi | O63: captured | P63: 44271.912 | Q63: 16248
A64: pay_GnOOlgdOPhYb2p | C64: HanHangul | D64: 49833 | F64: Quarterly Plan | G64: 99 | I64: 99 | J64: jschetanareddy@gmail.com | K64: 919148287261 | L64: INR | M64: FALSE | N64: upi | O64: captured | P64: 44271.919 | Q64: 16249
A65: pay_GnPGMt1CkBiInj | C65: HanHangul | D65: 49833 | F65: Quarterly Plan | G65: 99 | I65: 99 | J65: harshinineralla@gmail.com | K65: 918152013967 | L65: INR | M65: FALSE | N65: upi | O65: captured | P65: 44271.954 | Q65: 16266
A66: pay_GpxXJvzcNJBWqS | C66: Artists Commercialization | D66: 49864 | F66: Monthly Plan | G66: 99 | I66: 99 | J66: mroysingh@gmail.com | K66: 919550621321 | L66: INR | M66: FALSE | N66: upi | O66: captured | P66: 44278.405 | Q66: NF V2
A67: pay_GnPs7zaIzbFJTT | C67: HanHangul | D67: 49833 | F67: Quarterly Plan | G67: 99 | I67: 99 | J67: priyagsk98@gmail.com | K67: 917034476756 | L67: INR | M67: FALSE | N67: upi | O67: captured | P67: 44271.979 | Q67: 4363
A68: pay_GzTtfzux886Ijy | C68: De battlers | D68: 49991 | F68: Quarterly Plan | G68: 199 | I68: 199 | J68: bharti.jhurani@gmail.com | K68: 917276016442 | L68: INR | M68: FALSE | N68: netbanking | O68: captured | P68: 44302.468 | Q68: 16929
A69: pay_Gnd7wibNOBDlxQ | C69: HanHangul | D69: 49833 | F69: Quarterly Plan | G69: 99 | I69: 99 | J69: mansi14051999@gmail.com | K69: 971588137128 | L69: INR | M69: FALSE | N69: upi | O69: captured | P69: 44272.519 | Q69: 16275
A70: pay_GnfGs7LV9W4gdP | C70: HanHangul | D70: 49833 | F70: Quarterly Plan | G70: 99 | I70: 99 | J70: nehavenugopal91@gmail.com | K70: 919686818319 | L70: INR | M70: FALSE | N70: netbanking | O70: captured | P70: 44272.606 | Q70: 13724
A71: pay_Gpz84Hz6gnwhYy | C71: Artists Commercialization | D71: 49864 | F71: Monthly Plan | G71: 99 | I71: 99 | J71: priyajuhi98@gmail.com | K71: 917985805437 | L71: INR | M71: FALSE | N71: upi | O71: captured | P71: 44278.47 | Q71: 16789
A72: pay_GnfbmTY9jaKteA | C72: HanHangul | D72: 49833 | F72: Quarterly Plan | G72: 99 | I72: 99 | J72: kavyah830@gmail.com | K72: 917510953072 | L72: INR | M72: FALSE | N72: upi | O72: captured | P72: 44272.62 | Q72: 16268
A73: pay_GngGY6FpZgCM69 | C73: HanHangul | D73: 49833 | F73: Quarterly Plan | G73: 99 | I73: 99 | J73: marinafndes654@gmail.com | K73: 918605603525 | L73: INR | M73: FALSE | N73: upi | O73: captured | P73: 44272.647 | Q73: 16272
A74: pay_GnhjhgvHf14C3X | C74: HanHangul | D74: 49833 | F74: Quarterly Plan | G74: 99 | I74: 99 | J74: fnoman37@gmail.com | K74: 919884884951 | L74: INR | M74: FALSE | N74: upi | O74: captured | P74: 44272.707 | Q74: NF V2
A75: pay_Gnif9nnHfkbNBR | C75: HanHangul | D75: 49833 | F75: Quarterly Plan | G75: 99 | I75: 99 | J75: vaanipandit574@gmail.com | K75: 918920043318 | L75: INR | M75: FALSE | N75: upi | O75: captured | P75: 44272.745 | Q75: 16271
A76: pay_GqDriOATdUGUOJ | C76: Artists Commercialization | D76: 49864 | F76: Monthly Plan | G76: 99 | I76: 99 | J76: dilipabnave@gmail.com | K76: 919881434502 | L76: INR | M76: FALSE | N76: card | O76: captured | P76: 44279.071 | Q76: NF V2
A77: pay_Go0JnsSxAZHIJ3 | C77: HanHangul | D77: 49833 | F77: Quarterly Plan | G77: 99 | I77: 99 | J77: ananyad326@gmail.com | K77: 918638182668 | L77: INR | M77: FALSE | N77: upi | O77: captured | P77: 44273.464 | Q77: 16285
A78: pay_Go1MC7koCPnzgI | C78: HanHangul | D78: 49833 | F78: Quarterly Plan | G78: 99 | I78: 99 | J78: maluchulliparambil@gmail.com | K78: 917026475982 | L78: INR | M78: FALSE | N78: upi | O78: captured | P78: 44273.507 | Q78: 16288
A79: pay_Go1kTEFM234nDZ | C79: HanHangul | D79: 49833 | F79: Quarterly Plan | G79: 99 | I79: 99 | J79: mdasmail12@gmail.com | K79: 919051973402 | L79: INR | M79: FALSE | N79: upi | O79: captured | P79: 44273.523 | Q79: 16298
A80: pay_GqkjSNvUsPIcKr | C80: Artists Commercialization | D80: 49864 | F80: Monthly Plan | G80: 99 | I80: 99 | J80: artist.cilffordpeacock@gmail.com | K80: 918454884214 | L80: INR | M80: FALSE | N80: netbanking | O80: captured | P80: 44280.41 | Q80: NF V2
A81: pay_Go7AvHTvZgXaCU | C81: HanHangul | D81: 49833 | F81: Quarterly Plan | G81: 99 | I81: 99 | J81: gayu9121991@gmail.com | K81: 919324470993 | L81: INR | M81: FALSE | N81: upi | O81: captured | P81: 44273.744 | Q81: 6427
A82: pay_GqnHbKaEwoCkZK | C82: Artists Commercialization | D82: 49864 | F82: Monthly Plan | G82: 99 | I82: 99 | J82: popartisto@gmail.com | K82: 919819558656 | L82: INR | M82: FALSE | N82: upi | O82: captured | P82: 44280.514 | Q82: 16482
A83: pay_GzVUH9uO6P7Yjq | C83: De battlers | D83: 49991 | F83: Monthly Plan | G83: 99 | I83: 99 | J83: rajeshreebotre@hotmail.com | K83: 919890168744 | L83: INR | M83: FALSE | N83: upi | O83: captured | P83: 44302.533 | Q83: NF V2
A84: pay_GoCGaAze1hqt41 | C84: HAWC | D84: 49962 | F84: Quarterly Plan | G84: 99 | I84: 99 | J84: ankitrai2227@gmail.com | K84: 919936058885 | L84: INR | M84: FALSE | N84: upi | O84: captured | P84: 44273.951 | Q84: 16303
A85: pay_GoCKzU8WrWPE1h | C85: HanHangul | D85: 49833 | F85: Quarterly Plan | G85: 99 | I85: 99 | J85: ssurbhi1229@gmail.com | K85: 919100149855 | L85: INR | M85: FALSE | N85: upi | O85: captured | P85: 44273.954 | Q85: NF V2
A86: pay_GqtMtBEqw54E9A | C86: Artists Commercialization | D86: 49864 | F86: Monthly Plan | G86: 99 | I86: 99 | J86: payalsthalekar33@gmail.com | K86: 919819825204 | L86: INR | M86: FALSE | N86: upi | O86: captured | P86: 44280.762 | Q86: NF V2
A87: pay_GoNn3rLuZJkaAn | C87: HanHangul | D87: 49833 | F87: Quarterly Plan | G87: 99 | I87: 99 | J87: hudamajeed500@gmail.com | K87: 918113908682 | L87: INR | M87: FALSE | N87: upi | O87: captured | P87: 44274.421 | Q87: NF V2
A88: pay_GoNou2j4bP6Rd0 | C88: HanHangul | D88: 49833 | F88: Quarterly Plan | G88: 99 | I88: 99 | J88: manishaparven111@gmail.com | K88: 918637578701 | L88: INR | M88: FALSE | N88: upi | O88: captured | P88: 44274.422 | Q88: 16316
A89: pay_Gr791e3trG4x2p | C89: Artists Commercialization | D89: 49864 | F89: Monthly Plan | G89: 99 | I89: 99 | J89: ramneet1980@gmail.com | K89: 919268000639 | L89: INR | M89: FALSE | N89: card | O89: captured | P89: 44281.324 | Q89: 16484
A90: pay_Gr7g6PPgMDRZ7t | C90: Artists Commercialization | D90: 49864 | F90: Monthly Plan | G90: 99 | I90: 99 | J90: niveditasahu0007@gmail.com | K90: 918419802594 | L90: INR | M90: FALSE | N90: upi | O90: captured | P90: 44281.346 | Q90: NF V2
A91: pay_GrH0UeYh8iM7Y5 | C91: Artists Commercialization | D91: 49864 | F91: Monthly Plan | G91: 99 | I91: 99 | J91: shreyamusings@gmail.com | K91: 918505879696 | L91: INR | M91: FALSE | N91: paylater | O91: captured | P91: 44281.726 | Q91: NF V2
A92: pay_GoOU2LhWcvBaO9 | C92: HanHangul | D92: 49833 | F92: Quarterly Plan | G92: 99 | I92: 99 | J92: ishuu8295@gmail.com | K92: 919380559770 | L92: INR | M92: FALSE | N92: upi | O92: captured | P92: 44274.449 | Q92: 16311
A93: pay_GoPS20wNXdgkTV | C93: HanHangul | D93: 49833 | F93: Quarterly Plan | G93: 99 | I93: 99 | J93: ektapande96@gmail.com | K93: 918855857448 | L93: INR | M93: FALSE | N93: upi | O93: captured | P93: 44274.489 | Q93: 16351
A94: pay_GoPcLpC5k6jdph | C94: HanHangul | D94: 49833 | F94: Quarterly Plan | G94: 99 | I94: 99 | J94: swetagusain609@gmail.com | K94: 917088956095 | L94: INR | M94: FALSE | N94: upi | O94: captured | P94: 44274.495 | Q94: 16378
A95: pay_GoPorMHlYEApNB | C95: HanHangul | D95: 49833 | F95: Quarterly Plan | G95: 99 | I95: 99 | J95: chippimuthu96@gmail.com | K95: 918281831033 | L95: INR | M95: FALSE | N95: upi | O95: captured | P95: 44274.504 | Q95: 10242*
A96: pay_Grjo9mX1PvCi57 | C96: Artists Commercialization | D96: 49864 | F96: Monthly Plan | G96: 99 | I96: 99 | J96: datta2209@gmail.com | K96: 919619651802 | L96: INR | M96: FALSE | N96: upi | O96: captured | P96: 44282.9 | Q96: 16791
A97: pay_Grz6TblrVUlJUv | C97: Artists Commercialization | D97: 49864 | F97: Monthly Plan | G97: 99 | I97: 99 | J97: mehbabujb@gmail.com | K97: 919480750504 | L97: INR | M97: FALSE | N97: card | O97: captured | P97: 44283.523 | Q97: NF V2
A98: pay_Gs1TqUT15ZigCE | C98: Artists Commercialization | D98: 49864 | F98: Monthly Plan | G98: 99 | I98: 99 | J98: bunti.singh222@gmail.com | K98: 919422560164 | L98: INR | M98: FALSE | N98: card | O98: captured | P98: 44283.62 | Q98: NF V2
A99: pay_GoSjb0TG71Fle2 | C99: HAWC | D99: 49962 | F99: Quarterly Plan | G99: 99 | I99: 99 | J99: suruchi.jain19@ibsindia.org | K99: 919741982632 | L99: INR | M99: FALSE | N99: card | O99: captured | P99: 44274.623 | Q99: 12906
A100: pay_GoUpY0LDJy1S2L | C100: Hiraeth | D100: 49877 | F100: Quarterly Plan | G100: 99 | I100: 99 | J100: shweta.bagaddeo@gmail.com | K100: 917720002421 | L100: INR | M100: FALSE | N100: upi | O100: captured | P100: 44274.708 | Q100: 16319
A101: pay_GoWJqNDRSC0ze2 | C101: HanHangul | D101: 49833 | F101: Quarterly Plan | G101: 99 | I101: 99 | J101: manishaaa10@gmail.com | K101: 919795401525 | L101: INR | M101: FALSE | N101: upi | O101: captured | P101: 44274.769 | Q101: NF V2
A102: pay_GoXTiOHBT0dlJK | C102: HanHangul | D102: 49833 | F102: Quarterly Plan | G102: 99 | I102: 99 | J102: saraperry44444444@gmail.com | K102: 918979531948 | L102: INR | M102: FALSE | N102: card | O102: captured | P102: 44274.816 | Q102: 6585
A103: pay_GoYfdYYyaAwZK7 | C103: Hiraeth | D103: 49877 | F103: Quarterly Plan | G103: 99 | I103: 99 | J103: asim.mathur1002@gmail.com | K103: 919752391479 | L103: INR | M103: FALSE | N103: card | O103: captured | P103: 44274.864 | Q103: 16472
A104: pay_GoaQ5tespfRHzj | C104: Hiraeth | D104: 49877 | F104: Quarterly Plan | G104: 99 | I104: 99 | J104: shampaliroy80@gmail.com | K104: 918777845335 | L104: INR | M104: FALSE | N104: card | O104: captured | P104: 44274.936 | Q104: NF V2
A105: pay_Gob8032MzacEFV | C105: HanHangul | D105: 49833 | F105: Quarterly Plan | G105: 99 | I105: 99 | J105: snehaestam123@gmail.com | K105: 919552788069 | L105: INR | M105: FALSE | N105: upi | O105: captured | P105: 44274.965 | Q105: 16314
A106: pay_GodCw1NSxRTZv5 | C106: HAWC | D106: 49962 | F106: Quarterly Plan | G106: 99 | I106: 99 | J106: zahabiaakhan@gmail.com | K106: 918697175323 | L106: INR | M106: FALSE | N106: upi | O106: captured | P106: 44275.049 | Q106: 16334
A107: pay_GogUZb6uONI6la | C107: Hiraeth | D107: 49877 | F107: Quarterly Plan | G107: 99 | I107: 99 | J107: jyothidirector@gmail.com | K107: 919902701162 | L107: INR | M107: FALSE | N107: upi | O107: captured | P107: 44275.183 | Q107: 16462
A108: pay_GzXuetNk5uc45m | C108: De battlers | D108: 49991 | F108: Monthly Plan | G108: 99 | I108: 99 | J108: nkrishnakishore@gmail.com | K108: 919866723714 | L108: INR | M108: FALSE | N108: upi | O108: captured | P108: 44302.632 | Q108: 17028
A109: pay_H0TJJs83UBuAwB | C109: De battlers | D109: 49991 | F109: Half Yearly Plan | G109: 349 | I109: 349 | J109: niikhiilverma@gmail.com | K109: 919118031434 | L109: INR | M109: FALSE | N109: upi | O109: captured | P109: 44304.971 | Q109: 16958
A110: pay_GoqJ3Vckrhc4QY | C110: HanHangul | D110: 49833 | F110: Quarterly Plan | G110: 99 | I110: 99 | J110: taameenshabir@gmail.com | K110: 916006067114 | L110: INR | M110: FALSE | N110: card | O110: captured | P110: 44275.583 | Q110: 16322
A111: pay_GoqQJG7civxkwo | C111: HanHangul | D111: 49833 | F111: Quarterly Plan | G111: 99 | I111: 99 | J111: aanchal.sawhney18@gmail.com | K111: 919630053022 | L111: INR | M111: FALSE | N111: upi | O111: captured | P111: 44275.588 | Q111: 16383
A112: pay_H0o9oVmmpCfexd | C112: De battlers | D112: 49991 | F112: Monthly Plan | G112: 99 | I112: 99 | J112: bhu.abhishek111@gmail.com | K112: 918825193669 | L112: INR | M112: FALSE | N112: upi | O112: captured | P112: 44305.821 | Q112: 17027
...

Sheet User data - airtable
A1: payment_id | B1: plan_id | C1: Community Name | D1: Community_id | E1: plan_name | F1: plan_duration | G1: plan_cost | H1: renew | I1: amount | J1: email | K1: phone | L1: =CONCAT(J1,K1) -> emailphone | M1: currency | N1: is_international | O1: method | P1: status | Q1: created_at | R1: user_id | S1: payment_page_url | T1: payment_type
A2: =VLOOKUP(L2,payment_ids!C:D,2,FALSE) -> pay_HLNuFmG6aNQ5Zz | C2: A Blue Lotus Life | D2: 50143 | F2: 6 | G2: 999 | I2: 999 | J2: thehappypankaj@yahoo.com | K2: =+918283088675 -> 918283088675 | L2: =CONCAT(J2,K2) -> thehappypankaj@yahoo.com918283088675 | M2: INR | N2: FALSE | O2: =VLOOKUP(A2,payment_ids!D:E,2,FALSE) -> upi | P2: captured | Q2: 44475.819 | S2: https://hi.likeminds.community/d/a-blue-lotus-life | T2: Subscription
A3: =VLOOKUP(L3,payment_ids!C:D,2,FALSE) -> pay_HNDFyxw24p8Ojm | C3: A Blue Lotus Life | D3: 50143 | F3: 1 | G3: 199 | I3: 199 | J3: pakhi.garg95@gmail.com | K3: =+919808881888 -> 919808881888 | L3: =CONCAT(J3,K3) -> pakhi.garg95@gmail.com919808881888 | M3: INR | N3: FALSE | O3: =VLOOKUP(A3,payment_ids!D:E,2,FALSE) -> upi | P3: captured | Q3: 6/15/2021 10:33 AM | S3: https://hi.likeminds.community/d/a-blue-lotus-life | T3: Subscription
A4: =VLOOKUP(L4,payment_ids!C:D,2,FALSE) -> pay_HNTFkn45M6JhsN | C4: A Blue Lotus Life | D4: 50143 | F4: 1 | G4: 199 | I4: 199 | J4: bhawna.sandeep1130@gmail.com | K4: =+918950904883 -> 918950904883 | L4: =CONCAT(J4,K4) -> bhawna.sandeep1130@gmail.com918950904883 | M4: INR | N4: FALSE | O4: =VLOOKUP(A4,payment_ids!D:E,2,FALSE) -> upi | P4: captured | Q4: 6/16/2021 2:12 AM | S4: https://hi.likeminds.community/d/a-blue-lotus-life | T4: Subscription
A5: =VLOOKUP(L5,payment_ids!C:D,2,FALSE) -> pay_HNjqcFTYoWX0yu | C5: A Blue Lotus Life | D5: 50143 | F5: 6 | G5: 999 | I5: 999 | J5: saumyajoshi89@gmail.com | K5: =+918469114428 -> 918469114428 | L5: =CONCAT(J5,K5) -> saumyajoshi89@gmail.com918469114428 | M5: INR | N5: FALSE | O5: =VLOOKUP(A5,payment_ids!D:E,2,FALSE) -> card | P5: captured | Q5: 6/16/2021 6:44 PM | S5: https://hi.likeminds.community/d/a-blue-lotus-life | T5: Subscription
A6: =VLOOKUP(L6,payment_ids!C:D,2,FALSE) -> pay_HMRMlrYlyFK0Rf | C6: A Blue Lotus Life | D6: 50143 | F6: 1 | G6: 199 | I6: 199 | J6: krishnaraj.bhatns@gmail.com | K6: =+919731761212 -> 919731761212 | L6: =CONCAT(J6,K6) -> krishnaraj.bhatns@gmail.com919731761212 | M6: INR | N6: FALSE | O6: =VLOOKUP(A6,payment_ids!D:E,2,FALSE) -> upi | P6: captured | Q6: 6/20/2021 12:11 PM | S6: https://hi.likeminds.community/d/a-blue-lotus-life#Pricing | T6: Subscription
A7: =VLOOKUP(L7,payment_ids!C:D,2,FALSE) -> pay_HMRMlrYlyFK0Rf | C7: A Blue Lotus Life | D7: 50143 | F7: 1 | G7: 199 | I7: 199 | J7: krishnaraj.bhatns@gmail.com | K7: =+919731761212 -> 919731761212 | L7: =CONCAT(J7,K7) -> krishnaraj.bhatns@gmail.com919731761212 | M7: INR | N7: FALSE | O7: =VLOOKUP(A7,payment_ids!D:E,2,FALSE) -> upi | P7: captured | Q7: 6/20/2021 12:28 PM | S7: https://hi.likeminds.community/d/a-blue-lotus-life#Pricing | T7: Subscription
A8: =VLOOKUP(L8,payment_ids!C:D,2,FALSE) -> pay_H6IvfhXVSJtsVU | C8: Ahoj: Let's Blog | D8: 49997 | F8: 1 | G8: 99 | I8: 99 | J8: tara.lanba1999@gmail.com | K8: =+919582439852 -> 919582439852 | L8: =CONCAT(J8,K8) -> tara.lanba1999@gmail.com919582439852 | M8: INR | N8: FALSE | O8: =VLOOKUP(A8,payment_ids!D:E,2,FALSE) -> upi | P8: captured | Q8: 44260.71 | S8: https://community.likeminds.community/ahoj-lets-blog
A9: =VLOOKUP(L9,payment_ids!C:D,2,FALSE) -> pay_H6M18PniZZxhuH | C9: Ahoj: Let's Blog | D9: 49997 | F9: 1 | G9: 99 | I9: 99 | J9: mahirgupta98@gmail.com | K9: =+919416173796 -> 919416173796 | L9: =CONCAT(J9,K9) -> mahirgupta98@gmail.com919416173796 | M9: INR | N9: FALSE | O9: =VLOOKUP(A9,payment_ids!D:E,2,FALSE) -> upi | P9: captured | Q9: 44260.836 | S9: https://community.likeminds.community/ahoj-lets-blog
A10: =VLOOKUP(L10,payment_ids!C:D,2,FALSE) -> pay_H6OZHMGGwhtkMg | C10: Ahoj: Let's Blog | D10: 49997 | F10: 6 | G10: 349 | I10: 349 | J10: tanvimhatre001@gmail.com | K10: =+919969893269 -> 919969893269 | L10: =CONCAT(J10,K10) -> tanvimhatre001@gmail.com919969893269 | M10: INR | N10: FALSE | O10: =VLOOKUP(A10,payment_ids!D:E,2,FALSE) -> card | P10: captured | Q10: 44260.94 | S10: https://community.likeminds.community/ahoj-lets-blog
A11: =VLOOKUP(L11,payment_ids!C:D,2,FALSE) -> pay_H6ejsTenhxPtgT | C11: Ahoj: Let's Blog | D11: 49997 | F11: 6 | G11: 349 | I11: 349 | J11: nawatheygaurav@gmail.com | K11: =+919819252511 -> 919819252511 | L11: =CONCAT(J11,K11) -> nawatheygaurav@gmail.com919819252511 | M11: INR | N11: FALSE | O11: =VLOOKUP(A11,payment_ids!D:E,2,FALSE) -> upi | P11: captured | Q11: 44291.6 | S11: https://community.likeminds.community/ahoj-lets-blog
A12: =VLOOKUP(L12,payment_ids!C:D,2,FALSE) -> pay_H6gODrRvIOBR2G | C12: Ahoj: Let's Blog | D12: 49997 | F12: 1 | G12: 99 | I12: 99 | J12: leshanimehra1998@gmail.com | K12: =+918600964699 -> 918600964699 | L12: =CONCAT(J12,K12) -> leshanimehra1998@gmail.com918600964699 | M12: INR | N12: FALSE | O12: =VLOOKUP(A12,payment_ids!D:E,2,FALSE) -> upi | P12: captured | Q12: 44291.667 | S12: https://community.likeminds.community/ahoj-lets-blog
A13: =VLOOKUP(L13,payment_ids!C:D,2,FALSE) -> pay_H6gmIveChQnJtL | C13: Ahoj: Let's Blog | D13: 49997 | F13: 1 | G13: 99 | I13: 99 | J13: dezikakol@gmail.com | K13: =+919561542950 -> 919561542950 | L13: =CONCAT(J13,K13) -> dezikakol@gmail.com919561542950 | M13: INR | N13: FALSE | O13: =VLOOKUP(A13,payment_ids!D:E,2,FALSE) -> netbanking | P13: captured | Q13: 44291.683 | S13: https://community.likeminds.community/ahoj-lets-blog
A14: =VLOOKUP(L14,payment_ids!C:D,2,FALSE) -> pay_H6hFPdEWIAM1A2 | C14: Ahoj: Let's Blog | D14: 49997 | F14: 1 | G14: 99 | I14: 99 | J14: iamagsusfreak@gmail.com | K14: =+918129282453 -> 918129282453 | L14: =CONCAT(J14,K14) -> iamagsusfreak@gmail.com918129282453 | M14: INR | N14: FALSE | O14: =VLOOKUP(A14,payment_ids!D:E,2,FALSE) -> upi | P14: captured | Q14: 44291.702 | S14: https://community.likeminds.community/ahoj-lets-blog
A15: =VLOOKUP(L15,payment_ids!C:D,2,FALSE) -> pay_H6cZodbxWfXymQ | C15: Ahoj: Let's Blog | D15: 49997 | F15: 1 | G15: 99 | I15: 99 | J15: abhijit.jha33@gmail.com | K15: =+919711341773 -> 919711341773 | L15: =CONCAT(J15,K15) -> abhijit.jha33@gmail.com919711341773 | M15: INR | N15: FALSE | O15: =VLOOKUP(A15,payment_ids!D:E,2,FALSE) -> upi | P15: captured | Q15: 44291.511 | S15: https://community.likeminds.community/ahoj-lets-blog
A16: =VLOOKUP(L16,payment_ids!C:D,2,FALSE) -> pay_H6qjW9ICOOLM7A | C16: Ahoj: Let's Blog | D16: 49997 | F16: 1 | G16: 99 | I16: 99 | J16: crupam714@gmail.com | K16: =+919330771104 -> 919330771104 | L16: =CONCAT(J16,K16) -> crupam714@gmail.com919330771104 | M16: INR | N16: FALSE | O16: =VLOOKUP(A16,payment_ids!D:E,2,FALSE) -> upi | P16: captured | Q16: 44321.088 | S16: https://community.likeminds.community/ahoj-lets-blog
A17: =VLOOKUP(L17,payment_ids!C:D,2,FALSE) -> pay_H6xvuIL5Vvmaww | C17: Ahoj: Let's Blog | D17: 49997 | F17: 1 | G17: 99 | I17: 99 | J17: benadikam@gmail.com | K17: =+919860729292 -> 919860729292 | L17: =CONCAT(J17,K17) -> benadikam@gmail.com919860729292 | M17: INR | N17: FALSE | O17: =VLOOKUP(A17,payment_ids!D:E,2,FALSE) -> upi | P17: captured | Q17: 44321.382 | S17: https://community.likeminds.community/ahoj-lets-blog
A18: =VLOOKUP(L18,payment_ids!C:D,2,FALSE) -> pay_H70f2pvlDc6itm | C18: Ahoj: Let's Blog | D18: 49997 | F18: 6 | G18: 349 | I18: 349 | J18: travelwithfreddie@gmail.com | K18: =+919998728170 -> 919998728170 | L18: =CONCAT(J18,K18) -> travelwithfreddie@gmail.com919998728170 | M18: INR | N18: FALSE | O18: =VLOOKUP(A18,payment_ids!D:E,2,FALSE) -> upi | P18: captured | Q18: 44321.493 | S18: https://community.likeminds.community/ahoj-lets-blog
A19: =VLOOKUP(L19,payment_ids!C:D,2,FALSE) -> pay_H7Ye3cHPJezSiS | C19: Ahoj: Let's Blog | D19: 49997 | F19: 1 | G19: 99 | I19: 99 | J19: pallspallavi56789@gmail.com | K19: =+917838604128 -> 917838604128 | L19: =CONCAT(J19,K19) -> pallspallavi56789@gmail.com917838604128 | M19: INR | N19: FALSE | O19: =VLOOKUP(A19,payment_ids!D:E,2,FALSE) -> upi | P19: captured | Q19: 44352.878 | S19: https://community.likeminds.community/ahoj-lets-blog
A20: =VLOOKUP(L20,payment_ids!C:D,2,FALSE) -> pay_H7ZH7dwQA7xAMu | C20: Ahoj: Let's Blog | D20: 49997 | F20: 1 | G20: 99 | I20: 99 | J20: debajyoti_wr@hotmail.com | K20: =+919804294752 -> 919804294752 | L20: =CONCAT(J20,K20) -> debajyoti_wr@hotmail.com919804294752 | M20: INR | N20: FALSE | O20: =VLOOKUP(A20,payment_ids!D:E,2,FALSE) -> upi | P20: captured | Q20: 44352.903 | S20: https://community.likeminds.community/ahoj-lets-blog
A21: =VLOOKUP(L21,payment_ids!C:D,2,FALSE) -> pay_H7Nbm5Dv9pLMtM | C21: Ahoj: Let's Blog | D21: 49997 | F21: 1 | G21: 99 | I21: 99 | J21: contact.nandini01@gmail.com | K21: =+917980675481 -> 917980675481 | L21: =CONCAT(J21,K21) -> contact.nandini01@gmail.com917980675481 | M21: INR | N21: FALSE | O21: =VLOOKUP(A21,payment_ids!D:E,2,FALSE) -> upi | P21: captured | Q21: 44352.429 | S21: https://community.likeminds.community/ahoj-lets-blog
A22: =VLOOKUP(L22,payment_ids!C:D,2,FALSE) -> pay_H7akglvqfqvM7T | C22: Ahoj: Let's Blog | D22: 49997 | F22: 3 | G22: 199 | I22: 199 | J22: kartikbalwan@gmail.com | K22: =+919261615151 -> 919261615151 | L22: =CONCAT(J22,K22) -> kartikbalwan@gmail.com919261615151 | M22: INR | N22: FALSE | O22: =VLOOKUP(A22,payment_ids!D:E,2,FALSE) -> upi | P22: captured | Q22: 44352.964 | S22: https://community.likeminds.community/ahoj-lets-blog
A23: =VLOOKUP(L23,payment_ids!C:D,2,FALSE) -> pay_H7pricVWbFOcsz | C23: Ahoj: Let's Blog | D23: 49997 | F23: 1 | G23: 99 | I23: 99 | J23: ajaypanampet@gmail.com | K23: =+918547452646 -> 918547452646 | L23: =CONCAT(J23,K23) -> ajaypanampet@gmail.com918547452646 | M23: INR | N23: FALSE | O23: =VLOOKUP(A23,payment_ids!D:E,2,FALSE) -> upi | P23: captured | Q23: 44382.58 | S23: https://community.likeminds.community/ahoj-lets-blog
A24: =VLOOKUP(L24,payment_ids!C:D,2,FALSE) -> pay_H7rIuIYitrB1K9 | C24: Ahoj: Let's Blog | D24: 49997 | F24: 1 | G24: 99 | I24: 99 | J24: ritusmita01@gmail.com | K24: =+919071865890 -> 919071865890 | L24: =CONCAT(J24,K24) -> ritusmita01@gmail.com919071865890 | M24: INR | N24: FALSE | O24: =VLOOKUP(A24,payment_ids!D:E,2,FALSE) -> upi | P24: captured | Q24: 44382.642 | S24: https://community.likeminds.community/ahoj-lets-blog
A25: =VLOOKUP(L25,payment_ids!C:D,2,FALSE) -> pay_H7l84g4WgUv7ea | C25: Ahoj: Let's Blog | D25: 49997 | F25: 6 | G25: 349 | I25: 349 | J25: raimap994@gmail.com | K25: =+916290860709 -> 916290860709 | L25: =CONCAT(J25,K25) -> raimap994@gmail.com916290860709 | M25: INR | N25: FALSE | O25: =VLOOKUP(A25,payment_ids!D:E,2,FALSE) -> upi | P25: captured | Q25: 44382.388 | S25: https://community.likeminds.community/ahoj-lets-blog
A26: =VLOOKUP(L26,payment_ids!C:D,2,FALSE) -> pay_H8X46YbTfVcxHd | C26: Ahoj: Let's Blog | D26: 49997 | F26: 3 | G26: 199 | I26: 199 | J26: devrahulsingh2104@gmail.com | K26: =+919012341187 -> 919012341187 | L26: =CONCAT(J26,K26) -> devrahulsingh2104@gmail.com919012341187 | M26: INR | N26: FALSE | O26: =VLOOKUP(A26,payment_ids!D:E,2,FALSE) -> upi | P26: captured | Q26: 44444.341 | S26: https://community.likeminds.community/ahoj-lets-blog
A27: =VLOOKUP(L27,payment_ids!C:D,2,FALSE) -> pay_H8lQ5UTVui9dTO | C27: Ahoj: Let's Blog | D27: 49997 | F27: 3 | G27: 199 | I27: 199 | J27: sachin225sandy@gmail.com | K27: =+919030736603 -> 919030736603 | L27: =CONCAT(J27,K27) -> sachin225sandy@gmail.com919030736603 | M27: INR | N27: FALSE | O27: =VLOOKUP(A27,payment_ids!D:E,2,FALSE) -> card | P27: captured | Q27: 44444.926 | S27: https://community.likeminds.community/ahoj-lets-blog
A28: =VLOOKUP(L28,payment_ids!C:D,2,FALSE) -> pay_H8aIV3aCzWiI7l | C28: Ahoj: Let's Blog | D28: 49997 | F28: 3 | G28: 199 | I28: 199 | J28: anuradhashukla143@gmail.com | K28: =+918601624514 -> 918601624514 | L28: =CONCAT(J28,K28) -> anuradhashukla143@gmail.com918601624514 | M28: INR | N28: FALSE | O28: =VLOOKUP(A28,payment_ids!D:E,2,FALSE) -> upi | P28: captured | Q28: 44444.473 | S28: https://community.likeminds.community/ahoj-lets-blog
A29: =VLOOKUP(L29,payment_ids!C:D,2,FALSE) -> pay_H95jxoDSI7LEUB | C29: Ahoj: Let's Blog | D29: 49997 | F29: 3 | G29: 199 | I29: 199 | J29: sandhya.rajan03@gmail.com | K29: =+916380865060 -> 916380865060 | L29: =CONCAT(J29,K29) -> sandhya.rajan03@gmail.com916380865060 | M29: INR | N29: FALSE | O29: =VLOOKUP(A29,payment_ids!D:E,2,FALSE) -> upi | P29: captured | Q29: 44474.754 | S29: https://community.likeminds.community/ahoj-lets-blog
A30: =VLOOKUP(L30,payment_ids!C:D,2,FALSE) -> pay_H97U2lo9toAHVq | C30: Ahoj: Let's Blog | D30: 49997 | F30: 3 | G30: 199 | I30: 199 | J30: opgodara93@gmail.com | K30: =+919587884155 -> 919587884155 | L30: =CONCAT(J30,K30) -> opgodara93@gmail.com919587884155 | M30: INR | N30: FALSE | O30: =VLOOKUP(A30,payment_ids!D:E,2,FALSE) -> upi | P30: captured | Q30: 44474.825 | S30: https://community.likeminds.community/ahoj-lets-blog
A31: =VLOOKUP(L31,payment_ids!C:D,2,FALSE) -> pay_HBWG2W5fG6koig | C31: Ahoj: Let's Blog | D31: 49997 | F31: 3 | G31: 199 | I31: 199 | J31: guru_3@yahoo.com | K31: =+919916242098 -> 919916242098 | L31: =CONCAT(J31,K31) -> guru_3@yahoo.com919916242098 | M31: INR | N31: FALSE | O31: =VLOOKUP(A31,payment_ids!D:E,2,FALSE) -> upi | P31: captured | Q31: 5/16/2021 9:20 PM | S31: https://community.likeminds.community/ahoj-lets-blog
A32: =VLOOKUP(L32,payment_ids!C:D,2,FALSE) -> pay_HBifDwU9dgPVQZ | C32: Ahoj: Let's Blog | D32: 49997 | F32: 3 | G32: 199 | I32: 199 | J32: khyatimehta0@gmail.com | K32: =+919739438900 -> 919739438900 | L32: =CONCAT(J32,K32) -> khyatimehta0@gmail.com919739438900 | M32: INR | N32: FALSE | O32: =VLOOKUP(A32,payment_ids!D:E,2,FALSE) -> upi | P32: captured | Q32: 5/17/2021 9:29 AM | S32: https://community.likeminds.community/ahoj-lets-blog
A33: =VLOOKUP(L33,payment_ids!C:D,2,FALSE) -> pay_HBl9GiClfs6oRm | C33: Ahoj: Let's Blog | D33: 49997 | F33: 3 | G33: 199 | I33: 199 | J33: krishan.bora1990@gmail.com | K33: =+919818529598 -> 919818529598 | L33: =CONCAT(J33,K33) -> krishan.bora1990@gmail.com919818529598 | M33: INR | N33: FALSE | O33: =VLOOKUP(A33,payment_ids!D:E,2,FALSE) -> card | P33: captured | Q33: 5/17/2021 11:54 AM | S33: https://community.likeminds.community/ahoj-lets-blog
A34: =VLOOKUP(L34,payment_ids!C:D,2,FALSE) -> pay_HCDVQQ1ACO1UQ9 | C34: Ahoj: Let's Blog | D34: 49997 | F34: 3 | G34: 199 | I34: 199 | J34: princeparmar6@gmail.com | K34: =+918425046969 -> 918425046969 | L34: =CONCAT(J34,K34) -> princeparmar6@gmail.com918425046969 | M34: INR | N34: FALSE | O34: =VLOOKUP(A34,payment_ids!D:E,2,FALSE) -> upi | P34: captured | Q34: 5/18/2021 3:39 PM | S34: https://community.likeminds.community/ahoj-lets-blog
A35: =VLOOKUP(L35,payment_ids!C:D,2,FALSE) -> pay_HDJzaI79rF6AC3 | C35: Ahoj: Let's Blog | D35: 49997 | F35: 1 | G35: 99 | I35: 99 | J35: muskannagdev342@gmail.com | K35: =+919011926939 -> 919011926939 | L35: =CONCAT(J35,K35) -> muskannagdev342@gmail.com919011926939 | M35: INR | N35: FALSE | O35: =VLOOKUP(A35,payment_ids!D:E,2,FALSE) -> upi | P35: captured | Q35: 5/21/2021 10:39 AM | S35: https://community.likeminds.community/ahoj-lets-blog
A36: =VLOOKUP(L36,payment_ids!C:D,2,FALSE) -> pay_HDLaDN509Luscl | C36: Ahoj: Let's Blog | D36: 49997 | F36: 1 | G36: 99 | I36: 99 | J36: outdoorrebellions@gmail.com | K36: =+919810957676 -> 919810957676 | L36: =CONCAT(J36,K36) -> outdoorrebellions@gmail.com919810957676 | M36: INR | N36: FALSE | O36: =VLOOKUP(A36,payment_ids!D:E,2,FALSE) -> upi | P36: captured | Q36: 5/21/2021 12:12 PM | S36: https://community.likeminds.community/ahoj-lets-blog
A37: =VLOOKUP(L37,payment_ids!C:D,2,FALSE) -> pay_HDLthg6Y2SeBHZ | C37: Ahoj: Let's Blog | D37: 49997 | F37: 3 | G37: 199 | I37: 199 | J37: kanchangusain007@gmail.com | K37: =+919997428605 -> 919997428605 | L37: =CONCAT(J37,K37) -> kanchangusain007@gmail.com919997428605 | M37: INR | N37: FALSE | O37: =VLOOKUP(A37,payment_ids!D:E,2,FALSE) -> upi | P37: captured | Q37: 5/21/2021 6:37 PM | S37: https://community.likeminds.community/ahoj-lets-blog
A38: =VLOOKUP(L38,payment_ids!C:D,2,FALSE) -> pay_HDnBkPwtPD6cWs | C38: Ahoj: Let's Blog | D38: 49997 | F38: 1 | G38: 99 | I38: 99 | J38: ishaan17maxx@gmail.com | K38: =+916393992744 -> 916393992744 | L38: =CONCAT(J38,K38) -> ishaan17maxx@gmail.com916393992744 | M38: INR | N38: FALSE | O38: =VLOOKUP(A38,payment_ids!D:E,2,FALSE) -> upi | P38: captured | Q38: 5/22/2021 3:12 PM | S38: https://community.likeminds.community/ahoj-lets-blog
A39: =VLOOKUP(L39,payment_ids!C:D,2,FALSE) -> pay_HDqS1nWCVitsJy | C39: Ahoj: Let's Blog | D39: 49997 | F39: 1 | G39: 99 | I39: 99 | J39: dua.ankit@gmail.com | K39: =+919810766029 -> 919810766029 | L39: =CONCAT(J39,K39) -> dua.ankit@gmail.com919810766029 | M39: INR | N39: FALSE | O39: =VLOOKUP(A39,payment_ids!D:E,2,FALSE) -> upi | P39: captured | Q39: 5/22/2021 6:24 PM | S39: https://community.likeminds.community/ahoj-lets-blog
A40: =VLOOKUP(L40,payment_ids!C:D,2,FALSE) -> pay_HEXBPcJ144OLNK | C40: Ahoj: Let's Blog | D40: 49997 | F40: 1 | G40: 99 | I40: 99 | J40: raveenakaur544@gmail.com | K40: =+917769846304 -> 917769846304 | L40: =CONCAT(J40,K40) -> raveenakaur544@gmail.com917769846304 | M40: INR | N40: FALSE | O40: =VLOOKUP(A40,payment_ids!D:E,2,FALSE) -> upi | P40: captured | Q40: 5/24/2021 12:12 PM | S40: https://community.likeminds.community/ahoj-lets-blog
A41: =VLOOKUP(L41,payment_ids!C:D,2,FALSE) -> pay_HEfLz6CpDEh1Gg | C41: Ahoj: Let's Blog | D41: 49997 | F41: 1 | G41: 99 | I41: 99 | J41: priya19pop@gmail.com | K41: =+918200598533 -> 918200598533 | L41: =CONCAT(J41,K41) -> priya19pop@gmail.com918200598533 | M41: INR | N41: FALSE | O41: =VLOOKUP(A41,payment_ids!D:E,2,FALSE) -> card | P41: captured | Q41: 5/24/2021 8:13 PM | S41: https://community.likeminds.community/ahoj-lets-blog
A42: =VLOOKUP(L42,payment_ids!C:D,2,FALSE) -> pay_HEfovtM87qXqwO | C42: Ahoj: Let's Blog | D42: 49997 | F42: 1 | G42: 99 | I42: 99 | J42: annubhati540@gmail.com | K42: =+919354102070 -> 919354102070 | L42: =CONCAT(J42,K42) -> annubhati540@gmail.com919354102070 | M42: INR | N42: FALSE | O42: =VLOOKUP(A42,payment_ids!D:E,2,FALSE) -> upi | P42: captured | Q42: 5/24/2021 8:39 PM | S42: https://community.likeminds.community/ahoj-lets-blog
A43: =VLOOKUP(L43,payment_ids!C:D,2,FALSE) -> pay_HEpKt3n4g7QWRu | C43: Ahoj: Let's Blog | D43: 49997 | F43: 3 | G43: 199 | I43: 199 | J43: simranjitsinghsimar89@gmail.com | K43: =+919906190121 -> 919906190121 | L43: =CONCAT(J43,K43) -> simranjitsinghsimar89@gmail.com919906190121 | M43: INR | N43: FALSE | O43: =VLOOKUP(A43,payment_ids!D:E,2,FALSE) -> card | P43: captured | Q43: 5/25/2021 5:57 AM | S43: https://community.likeminds.community/ahoj-lets-blog
A44: =VLOOKUP(L44,payment_ids!C:D,2,FALSE) -> pay_HExLl0IbSHPZ9B | C44: Ahoj: Let's Blog | D44: 49997 | F44: 1 | G44: 99 | I44: 99 | J44: pradeepvatturi@gmail.com | K44: =+919951600801 -> 919951600801 | L44: =CONCAT(J44,K44) -> pradeepvatturi@gmail.com919951600801 | M44: INR | N44: FALSE | O44: =VLOOKUP(A44,payment_ids!D:E,2,FALSE) -> wallet | P44: captured | Q44: 5/25/2021 1:53 PM | S44: https://community.likeminds.community/ahoj-lets-blog
A45: =VLOOKUP(L45,payment_ids!C:D,2,FALSE) -> pay_HF04M7tr6mqtYI | C45: Ahoj: Let's Blog | D45: 49997 | F45: 1 | G45: 99 | I45: 99 | J45: smritipragya@gmail.com | K45: =+917063112159 -> 917063112159 | L45: =CONCAT(J45,K45) -> smritipragya@gmail.com917063112159 | M45: INR | N45: FALSE | O45: =VLOOKUP(A45,payment_ids!D:E,2,FALSE) -> upi | P45: captured | Q45: 5/25/2021 4:27 PM | S45: https://community.likeminds.community/ahoj-lets-blog
A46: =VLOOKUP(L46,payment_ids!C:D,2,FALSE) -> pay_HFKc1pG7zigNrx | C46: Ahoj: Let's Blog | D46: 49997 | F46: 1 | G46: 99 | I46: 99 | J46: uditraj79@gmail.com | K46: =+917982620256 -> 917982620256 | L46: =CONCAT(J46,K46) -> uditraj79@gmail.com917982620256 | M46: INR | N46: FALSE | O46: =VLOOKUP(A46,payment_ids!D:E,2,FALSE) -> upi | P46: captured | Q46: 5/26/2021 12:33 PM | S46: https://community.likeminds.community/ahoj-lets-blog
A47: =VLOOKUP(L47,payment_ids!C:D,2,FALSE) -> pay_HFMsxVkhgaRoJX | C47: Ahoj: Let's Blog | D47: 49997 | F47: 3 | G47: 199 | I47: 199 | J47: dranoopvet07@gmail.com | K47: =+919400431220 -> 919400431220 | L47: =CONCAT(J47,K47) -> dranoopvet07@gmail.com919400431220 | M47: INR | N47: FALSE | O47: =VLOOKUP(A47,payment_ids!D:E,2,FALSE) -> upi | P47: captured | Q47: 5/26/2021 2:46 PM | S47: https://community.likeminds.community/ahoj-lets-blog
A48: =VLOOKUP(L48,payment_ids!C:D,2,FALSE) -> pay_HFPXSa05pMkXjg | C48: Ahoj: Let's Blog | D48: 49997 | F48: 1 | G48: 99 | I48: 99 | J48: pratham76761@gmail.com | K48: =+919030076761 -> 919030076761 | L48: =CONCAT(J48,K48) -> pratham76761@gmail.com919030076761 | M48: INR | N48: FALSE | O48: =VLOOKUP(A48,payment_ids!D:E,2,FALSE) -> upi | P48: captured | Q48: 5/26/2021 5:22 PM | S48: https://community.likeminds.community/ahoj-lets-blog
A49: =VLOOKUP(L49,payment_ids!C:D,2,FALSE) -> pay_HFQunuJspib5Jz | C49: Ahoj: Let's Blog | D49: 49997 | F49: 1 | G49: 99 | I49: 99 | J49: rohit.marchande@outlook.com | K49: =+919579795121 -> 919579795121 | L49: =CONCAT(J49,K49) -> rohit.marchande@outlook.com919579795121 | M49: INR | N49: FALSE | O49: =VLOOKUP(A49,payment_ids!D:E,2,FALSE) -> upi | P49: captured | Q49: 5/26/2021 6:43 PM | S49: https://community.likeminds.community/ahoj-lets-blog
A50: =VLOOKUP(L50,payment_ids!C:D,2,FALSE) -> pay_HFX1l7WbKPh5DB | C50: Ahoj: Let's Blog | D50: 49997 | F50: 6 | G50: 349 | I50: 349 | J50: shoghi07@gmail.com | K50: =+919601052801 -> 919601052801 | L50: =CONCAT(J50,K50) -> shoghi07@gmail.com919601052801 | M50: INR | N50: FALSE | O50: =VLOOKUP(A50,payment_ids!D:E,2,FALSE) -> upi | P50: captured | Q50: 5/27/2021 12:41 AM | S50: https://community.likeminds.community/ahoj-lets-blog
A51: =VLOOKUP(L51,payment_ids!C:D,2,FALSE) -> pay_HG6lKY2uLkBism | C51: Ahoj: Let's Blog | D51: 49997 | F51: 3 | G51: 199 | I51: 199 | J51: sharad1093@gmail.com | K51: =+919713718090 -> 919713718090 | L51: =CONCAT(J51,K51) -> sharad1093@gmail.com919713718090 | M51: INR | N51: FALSE | O51: =VLOOKUP(A51,payment_ids!D:E,2,FALSE) -> card | P51: captured | Q51: 5/28/2021 11:39 AM | S51: https://community.likeminds.community/ahoj-lets-blog
A52: =VLOOKUP(L52,payment_ids!C:D,2,FALSE) -> pay_HG8ixTNDo1NNjx | C52: Ahoj: Let's Blog | D52: 49997 | F52: 1 | G52: 99 | I52: 99 | J52: janet9963@gmail.com | K52: =+919483512561 -> 919483512561 | L52: =CONCAT(J52,K52) -> janet9963@gmail.com919483512561 | M52: INR | N52: FALSE | O52: =VLOOKUP(A52,payment_ids!D:E,2,FALSE) -> card | P52: captured | Q52: 5/28/2021 1:34 PM | S52: https://community.likeminds.community/ahoj-lets-blog
A53: =VLOOKUP(L53,payment_ids!C:D,2,FALSE) -> pay_HG9wRSVtI7orpc | C53: Ahoj: Let's Blog | D53: 49997 | F53: 1 | G53: 99 | I53: 99 | J53: shadab3247@gmail.com | K53: =+917979787986 -> 917979787986 | L53: =CONCAT(J53,K53) -> shadab3247@gmail.com917979787986 | M53: INR | N53: FALSE | O53: =VLOOKUP(A53,payment_ids!D:E,2,FALSE) -> upi | P53: captured | Q53: 5/28/2021 2:46 PM | S53: https://community.likeminds.community/ahoj-lets-blog
A54: =VLOOKUP(L54,payment_ids!C:D,2,FALSE) -> pay_HGCbBxDpVhv614 | C54: Ahoj: Let's Blog | D54: 49997 | F54: 1 | G54: 99 | I54: 99 | J54: soham.mungikar2019@ssca.edu.in | K54: =+918669061696 -> 918669061696 | L54: =CONCAT(J54,K54) -> soham.mungikar2019@ssca.edu.in918669061696 | M54: INR | N54: FALSE | O54: =VLOOKUP(A54,payment_ids!D:E,2,FALSE) -> netbanking | P54: captured | Q54: 5/28/2021 5:23 PM | S54: https://community.likeminds.community/ahoj-lets-blog
A55: =VLOOKUP(L55,payment_ids!C:D,2,FALSE) -> pay_HGU0VrMkL3u1Uc | C55: Ahoj: Let's Blog | D55: 49997 | F55: 1 | G55: 99 | I55: 99 | J55: theedajahnavee@gmail.com | K55: =+916281153863 -> 916281153863 | L55: =CONCAT(J55,K55) -> theedajahnavee@gmail.com916281153863 | M55: INR | N55: FALSE | O55: =VLOOKUP(A55,payment_ids!D:E,2,FALSE) -> upi | P55: captured | Q55: 5/29/2021 10:24 AM | S55: https://community.likeminds.community/ahoj-lets-blog
A56: =VLOOKUP(L56,payment_ids!C:D,2,FALSE) -> pay_HGvJOjNO1Lszqd | C56: Ahoj: Let's Blog | D56: 49997 | F56: 1 | G56: 99 | I56: 99 | J56: akkcrusier@gmail.com | K56: =+919733311678 -> 919733311678 | L56: =CONCAT(J56,K56) -> akkcrusier@gmail.com919733311678 | M56: INR | N56: FALSE | O56: =VLOOKUP(A56,payment_ids!D:E,2,FALSE) -> upi | P56: captured | Q56: 5/30/2021 1:06 PM | S56: https://community.likeminds.community/ahoj-lets-blog
A57: =VLOOKUP(L57,payment_ids!C:D,2,FALSE) -> pay_HH53cIZRPAyFP0 | C57: Ahoj: Let's Blog | D57: 49997 | F57: 1 | G57: 99 | I57: 99 | J57: ankitkumar8941@gmail.com | K57: =+917983530659 -> 917983530659 | L57: =CONCAT(J57,K57) -> ankitkumar8941@gmail.com917983530659 | M57: INR | N57: FALSE | O57: =VLOOKUP(A57,payment_ids!D:E,2,FALSE) -> card | P57: captured | Q57: 5/30/2021 10:38 PM | S57: https://community.likeminds.community/ahoj-lets-blog
A58: =VLOOKUP(L58,payment_ids!C:D,2,FALSE) -> pay_HHF5zX18LZ9IO4 | C58: Ahoj: Let's Blog | D58: 49997 | F58: 6 | G58: 349 | I58: 349 | J58: ddas2172@gmail.com | K58: =+917002359932 -> 917002359932 | L58: =CONCAT(J58,K58) -> ddas2172@gmail.com917002359932 | M58: INR | N58: FALSE | O58: =VLOOKUP(A58,payment_ids!D:E,2,FALSE) -> upi | P58: captured | Q58: 5/31/2021 8:29 AM | S58: https://community.likeminds.community/ahoj-lets-blog
A59: =VLOOKUP(L59,payment_ids!C:D,2,FALSE) -> pay_HHMQNZbqwIxKxI | C59: Ahoj: Let's Blog | D59: 49997 | F59: 1 | G59: 99 | I59: 99 | J59: nehaaricag7@gmail.com | K59: =+917337069679 -> 917337069679 | L59: =CONCAT(J59,K59) -> nehaaricag7@gmail.com917337069679 | M59: INR | N59: FALSE | O59: =VLOOKUP(A59,payment_ids!D:E,2,FALSE) -> upi | P59: captured | Q59: 5/31/2021 3:38 PM | S59: https://community.likeminds.community/ahoj-lets-blog
A60: =VLOOKUP(L60,payment_ids!C:D,2,FALSE) -> pay_HHQ9CdZRbyMtcE | C60: Ahoj: Let's Blog | D60: 49997 | F60: 1 | G60: 99 | I60: 99 | J60: anjali.patra2110@gmail.com | K60: =+918968324069 -> 918968324069 | L60: =CONCAT(J60,K60) -> anjali.patra2110@gmail.com918968324069 | M60: INR | N60: FALSE | O60: =VLOOKUP(A60,payment_ids!D:E,2,FALSE) -> upi | P60: captured | Q60: 5/31/2021 7:15 PM | S60: https://community.likeminds.community/ahoj-lets-blog
A61: =VLOOKUP(L61,payment_ids!C:D,2,FALSE) -> pay_HHR9PiSutUHSLM | C61: Ahoj: Let's Blog | D61: 49997 | F61: 1 | G61: 99 | I61: 99 | J61: sbh981214@gmail.com | K61: =+918762383152 -> 918762383152 | L61: =CONCAT(J61,K61) -> sbh981214@gmail.com918762383152 | M61: INR | N61: FALSE | O61: =VLOOKUP(A61,payment_ids!D:E,2,FALSE) -> card | P61: captured | Q61: 5/31/2021 8:20 PM | S61: https://community.likeminds.community/ahoj-lets-blog
A62: =VLOOKUP(L62,payment_ids!C:D,2,FALSE) -> pay_HHk6TSR87ryjbz | C62: Ahoj: Let's Blog | D62: 49997 | F62: 1 | G62: 99 | I62: 99 | J62: phiranandani@gmail.com | K62: =+919930012925 -> 919930012925 | L62: =CONCAT(J62,K62) -> phiranandani@gmail.com919930012925 | M62: INR | N62: FALSE | O62: =VLOOKUP(A62,payment_ids!D:E,2,FALSE) -> upi | P62: captured | Q62: 44202.616 | S62: https://community.likeminds.community/ahoj-lets-blog
A63: =VLOOKUP(L63,payment_ids!C:D,2,FALSE) -> pay_HHmm7cGzCu0PRv | C63: Ahoj: Let's Blog | D63: 49997 | F63: 3 | G63: 199 | I63: 199 | J63: sunnylalwani07@gmail.com | K63: =+917276167675 -> 917276167675 | L63: =CONCAT(J63,K63) -> sunnylalwani07@gmail.com917276167675 | M63: INR | N63: FALSE | O63: =VLOOKUP(A63,payment_ids!D:E,2,FALSE) -> upi | P63: captured | Q63: 44202.725 | S63: https://community.likeminds.community/ahoj-lets-blog
A64: =VLOOKUP(L64,payment_ids!C:D,2,FALSE) -> pay_HHoytVk365rVNs | C64: Ahoj: Let's Blog | D64: 49997 | F64: 1 | G64: 99 | I64: 99 | J64: rupalimahla@gmail.com | K64: =+919589937446 -> 919589937446 | L64: =CONCAT(J64,K64) -> rupalimahla@gmail.com919589937446 | M64: INR | N64: FALSE | O64: =VLOOKUP(A64,payment_ids!D:E,2,FALSE) -> upi | P64: captured | Q64: 44202.815 | S64: https://community.likeminds.community/ahoj-lets-blog
A65: =VLOOKUP(L65,payment_ids!C:D,2,FALSE) -> pay_HI9Uxdov3huVwC | C65: Ahoj: Let's Blog | D65: 49997 | F65: 3 | G65: 199 | I65: 199 | J65: deepanshi.ashri@gmail.com | K65: =+919996537899 -> 919996537899 | L65: =CONCAT(J65,K65) -> deepanshi.ashri@gmail.com919996537899 | M65: INR | N65: FALSE | O65: =VLOOKUP(A65,payment_ids!D:E,2,FALSE) -> upi | P65: captured | Q65: 44233.651 | S65: https://community.likeminds.community/ahoj-lets-blog
A66: =VLOOKUP(L66,payment_ids!C:D,2,FALSE) -> pay_HIGKaDWtw8GspZ | C66: Ahoj: Let's Blog | D66: 49997 | F66: 1 | G66: 99 | I66: 99 | J66: amareshsingh1995@gmail.com | K66: =+918010405899 -> 918010405899 | L66: =CONCAT(J66,K66) -> amareshsingh1995@gmail.com918010405899 | M66: INR | N66: FALSE | O66: =VLOOKUP(A66,payment_ids!D:E,2,FALSE) -> upi | P66: captured | Q66: 44233.93 | S66: https://community.likeminds.community/ahoj-lets-blog
A67: =VLOOKUP(L67,payment_ids!C:D,2,FALSE) -> pay_HIRKZ26mJmjFb5 | C67: Ahoj: Let's Blog | D67: 49997 | F67: 1 | G67: 99 | I67: 99 | J67: harshan0498@gmail.com | K67: =+917904785764 -> 917904785764 | L67: =CONCAT(J67,K67) -> harshan0498@gmail.com917904785764 | M67: INR | N67: FALSE | O67: =VLOOKUP(A67,payment_ids!D:E,2,FALSE) -> upi | P67: captured | Q67: 44261.378 | S67: https://community.likeminds.community/ahoj-lets-blog
A68: =VLOOKUP(L68,payment_ids!C:D,2,FALSE) -> pay_HIYR4iMLiYUq43 | C68: Ahoj: Let's Blog | D68: 49997 | F68: 1 | G68: 99 | I68: 99 | J68: hiya2199@gmail.com | K68: =+919625464710 -> 919625464710 | L68: =CONCAT(J68,K68) -> hiya2199@gmail.com919625464710 | M68: INR | N68: FALSE | O68: =VLOOKUP(A68,payment_ids!D:E,2,FALSE) -> upi | P68: captured | Q68: 44261.667 | S68: https://community.likeminds.community/ahoj-lets-blog
A69: =VLOOKUP(L69,payment_ids!C:D,2,FALSE) -> pay_HIbsY4AZfiE0cK | C69: Ahoj: Let's Blog | D69: 49997 | F69: 1 | G69: 99 | I69: 99 | J69: abhijit.jha33@gmail.con | K69: =+919711341773 -> 919711341773 | L69: =CONCAT(J69,K69) -> abhijit.jha33@gmail.con919711341773 | M69: INR | N69: FALSE | O69: =VLOOKUP(A69,payment_ids!D:E,2,FALSE) -> upi | P69: captured | Q69: 44261.808 | S69: https://community.likeminds.community/ahoj-lets-blog
A70: =VLOOKUP(L70,payment_ids!C:D,2,FALSE) -> pay_HIjlPMEU9HPR8c | C70: Ahoj: Let's Blog | D70: 49997 | F70: 1 | G70: 99 | I70: 99 | J70: prince.varun14@gmail.com | K70: =+919681482727 -> 919681482727 | L70: =CONCAT(J70,K70) -> prince.varun14@gmail.com919681482727 | M70: INR | N70: FALSE | O70: =VLOOKUP(A70,payment_ids!D:E,2,FALSE) -> wallet | P70: captured | Q70: 44292.129 | S70: https://community.likeminds.community/ahoj-lets-blog
A71: =VLOOKUP(L71,payment_ids!C:D,2,FALSE) -> pay_HJnjRLnz1r84Kz | C71: Ahoj: Let's Blog | D71: 49997 | F71: 1 | G71: 99 | I71: 99 | J71: rakeshnature68@gnail.com | K71: =+919110437338 -> 919110437338 | L71: =CONCAT(J71,K71) -> rakeshnature68@gnail.com919110437338 | M71: INR | N71: FALSE | O71: =VLOOKUP(A71,payment_ids!D:E,2,FALSE) -> upi | P71: captured | Q71: 44353.818 | S71: https://community.likeminds.community/ahoj-lets-blog
A72: =VLOOKUP(L72,payment_ids!C:D,2,FALSE) -> pay_HK73p6YcRPktv3 | C72: Ahoj: Let's Blog | D72: 49997 | F72: 3 | G72: 199 | I72: 199 | J72: karsangnini4@gmail.com | K72: =+917642034091 -> 917642034091 | L72: =CONCAT(J72,K72) -> karsangnini4@gmail.com917642034091 | M72: INR | N72: FALSE | O72: =VLOOKUP(A72,payment_ids!D:E,2,FALSE) -> upi | P72: captured | Q72: 44383.606 | S72: https://community.likeminds.community/ahoj-lets-blog
A73: =VLOOKUP(L73,payment_ids!C:D,2,FALSE) -> pay_HKGKUD8RF03I3M | C73: Ahoj: Let's Blog | D73: 49997 | F73: 3 | G73: 199 | I73: 199 | J73: satyendrakrchauhan@gmail.com | K73: =+919614789882 -> 919614789882 | L73: =CONCAT(J73,K73) -> satyendrakrchauhan@gmail.com919614789882 | M73: INR | N73: FALSE | O73: =VLOOKUP(A73,payment_ids!D:E,2,FALSE) -> upi | P73: captured | Q73: 44383.986 | S73: https://community.likeminds.community/ahoj-lets-blog
A74: =VLOOKUP(L74,payment_ids!C:D,2,FALSE) -> pay_HKHX3seYV7mVgS | C74: Ahoj: Let's Blog | D74: 49997 | F74: 1 | G74: 99 | I74: 99 | J74: manasi.chauhan19@gmail.com | K74: =+918861355515 -> 918861355515 | L74: =CONCAT(J74,K74) -> manasi.chauhan19@gmail.com918861355515 | M74: INR | N74: FALSE | O74: =VLOOKUP(A74,payment_ids!D:E,2,FALSE) -> upi | P74: captured | Q74: 44414.033 | S74: https://community.likeminds.community/ahoj-lets-blog
A75: =VLOOKUP(L75,payment_ids!C:D,2,FALSE) -> pay_HBWG2W5fG6koig | C75: Ahoj: Let's Blog | D75: 49997 | F75: 6 | G75: 349 | I75: 349 | J75: guru_3@yahoo.com | K75: =+919916242098 -> 919916242098 | L75: =CONCAT(J75,K75) -> guru_3@yahoo.com919916242098 | M75: INR | N75: FALSE | O75: =VLOOKUP(A75,payment_ids!D:E,2,FALSE) -> upi | P75: captured | Q75: 44414.035 | S75: https://community.likeminds.community/ahoj-lets-blog
A76: =VLOOKUP(L76,payment_ids!C:D,2,FALSE) -> pay_HKtDx822EnQKjS | C76: Ahoj: Let's Blog | D76: 49997 | F76: 3 | G76: 199 | I76: 199 | J76: suniltrue@gmail.com | K76: =+919035015257 -> 919035015257 | L76: =CONCAT(J76,K76) -> suniltrue@gmail.com919035015257 | M76: INR | N76: FALSE | O76: =VLOOKUP(A76,payment_ids!D:E,2,FALSE) -> upi | P76: captured | Q76: 44445.569 | S76: https://community.likeminds.community/ahoj-lets-blog | T76: Subscription
A77: =VLOOKUP(L77,payment_ids!C:D,2,FALSE) -> pay_HLKVRMfXhoDsE3 | C77: Ahoj: Let's Blog | D77: 49997 | F77: 1 | G77: 99 | I77: 99 | J77: vanshikathakur2811@gmail.com | K77: =+918427693486 -> 918427693486 | L77: =CONCAT(J77,K77) -> vanshikathakur2811@gmail.com918427693486 | M77: INR | N77: FALSE | O77: =VLOOKUP(A77,payment_ids!D:E,2,FALSE) -> upi | P77: captured | Q77: 44475.681 | S77: https://community.likeminds.community/ahoj-lets-blog | T77: Subscription
A78: =VLOOKUP(L78,payment_ids!C:D,2,FALSE) -> pay_HLMy1uJ5lWuCtV | C78: Ahoj: Let's Blog | D78: 49997 | F78: 1 | G78: 99 | I78: 99 | J78: ayushijain0624@gmail.com | K78: =+917875897782 -> 917875897782 | L78: =CONCAT(J78,K78) -> ayushijain0624@gmail.com917875897782 | M78: INR | N78: FALSE | O78: =VLOOKUP(A78,payment_ids!D:E,2,FALSE) -> upi | P78: captured | Q78: 44475.781 | S78: https://community.likeminds.community/ahoj-lets-blog | T78: Subscription
A79: =VLOOKUP(L79,payment_ids!C:D,2,FALSE) -> pay_HLSxCVJYBkqJIg | C79: Ahoj: Let's Blog | D79: 49997 | F79: 3 | G79: 199 | I79: 199 | J79: adesarakhyati9@gmail.com | K79: =+917321988222 -> 917321988222 | L79: =CONCAT(J79,K79) -> adesarakhyati9@gmail.com917321988222 | M79: INR | N79: FALSE | O79: =VLOOKUP(A79,payment_ids!D:E,2,FALSE) -> upi | P79: captured | Q79: 44506.026 | S79: https://community.likeminds.community/ahoj-lets-blog | T79: Subscription
A80: =VLOOKUP(L80,payment_ids!C:D,2,FALSE) -> pay_HLnO3BC8QDcba6 | C80: Ahoj: Let's Blog | D80: 49997 | F80: 1 | G80: 99 | I80: 99 | J80: laxminegi2105@gmail.com | K80: =+919634081231 -> 919634081231 | L80: =CONCAT(J80,K80) -> laxminegi2105@gmail.com919634081231 | M80: INR | N80: FALSE | O80: =VLOOKUP(A80,payment_ids!D:E,2,FALSE) -> upi | P80: captured | Q80: 44506.858 | S80: https://community.likeminds.community/ahoj-lets-blog | T80: Subscription
A81: =VLOOKUP(L81,payment_ids!C:D,2,FALSE) -> pay_HMBrwPMNQJLmpx | C81: Ahoj: Let's Blog | D81: 49997 | F81: 1 | G81: 99 | I81: 99 | J81: umarr3776@gmail.com | K81: =+919677235852 -> 919677235852 | L81: =CONCAT(J81,K81) -> umarr3776@gmail.com919677235852 | M81: INR | N81: FALSE | O81: =VLOOKUP(A81,payment_ids!D:E,2,FALSE) -> wallet | P81: captured | Q81: 44536.856 | S81: https://community.likeminds.community/ahoj-lets-blog | T81: Subscription
A82: =VLOOKUP(L82,payment_ids!C:D,2,FALSE) -> pay_HMEZGjhlRaGXYm | C82: Ahoj: Let's Blog | D82: 49997 | F82: 1 | G82: 99 | I82: 99 | J82: nikhildhingaun@gmail.com | K82: =+919711350850 -> 919711350850 | L82: =CONCAT(J82,K82) -> nikhildhingaun@gmail.com919711350850 | M82: INR | N82: FALSE | O82: =VLOOKUP(A82,payment_ids!D:E,2,FALSE) -> wallet | P82: captured | Q82: 44536.967 | S82: https://community.likeminds.community/ahoj-lets-blog | T82: Subscription
A83: =VLOOKUP(L83,payment_ids!C:D,2,FALSE) -> pay_HMQxohj8HcATuA | C83: Ahoj: Let's Blog | D83: 49997 | F83: 3 | G83: 199 | I83: 199 | J83: rguditeamworks@gmail.com | K83: =+918185918851 -> 918185918851 | L83: =CONCAT(J83,K83) -> rguditeamworks@gmail.com918185918851 | M83: INR | N83: FALSE | O83: =VLOOKUP(A83,payment_ids!D:E,2,FALSE) -> upi | P83: captured | Q83: 6/13/2021 11:19 AM | S83: https://community.likeminds.community/ahoj-lets-blog | T83: Subscription
A84: =VLOOKUP(L84,payment_ids!C:D,2,FALSE) -> pay_HMeuFwm5llHvBu | C84: Ahoj: Let's Blog | D84: 49997 | F84: 1 | G84: 99 | I84: 99 | J84: kaman3724@gmail.com | K84: =+917015129688 -> 917015129688 | L84: =CONCAT(J84,K84) -> kaman3724@gmail.com917015129688 | M84: INR | N84: FALSE | O84: =VLOOKUP(A84,payment_ids!D:E,2,FALSE) -> upi | P84: captured | Q84: 6/14/2021 12:57 AM | S84: https://community.likeminds.community/ahoj-lets-blog | T84: Subscription
A85: =VLOOKUP(L85,payment_ids!C:D,2,FALSE) -> pay_HMoi6P7LqPE6tv | C85: Ahoj: Let's Blog | D85: 49997 | F85: 1 | G85: 99 | I85: 99 | J85: nikhilchauhan633@gmail.com | K85: =+917906020996 -> 917906020996 | L85: =CONCAT(J85,K85) -> nikhilchauhan633@gmail.com917906020996 | M85: INR | N85: FALSE | O85: =VLOOKUP(A85,payment_ids!D:E,2,FALSE) -> upi | P85: captured | Q85: 6/14/2021 10:33 AM | S85: https://community.likeminds.community/ahoj-lets-blog | T85: Subscription
A86: =VLOOKUP(L86,payment_ids!C:D,2,FALSE) -> pay_HMp8LaCc1oJz9k | C86: Ahoj: Let's Blog | D86: 49997 | F86: 1 | G86: 99 | I86: 99 | J86: ppsweetanny12011993@gmail.com | K86: =+917987036123 -> 917987036123 | L86: =CONCAT(J86,K86) -> ppsweetanny12011993@gmail.com917987036123 | M86: INR | N86: FALSE | O86: =VLOOKUP(A86,payment_ids!D:E,2,FALSE) -> upi | P86: captured | Q86: 6/14/2021 10:57 AM | S86: https://community.likeminds.community/ahoj-lets-blog | T86: Subscription
A87: =VLOOKUP(L87,payment_ids!C:D,2,FALSE) -> pay_HMqOPwdnSUe5Hf | C87: Ahoj: Let's Blog | D87: 49997 | F87: 1 | G87: 99 | I87: 99 | J87: pratiush.dhiman1994@gmail.com | K87: =+919897523433 -> 919897523433 | L87: =CONCAT(J87,K87) -> pratiush.dhiman1994@gmail.com919897523433 | M87: INR | N87: FALSE | O87: =VLOOKUP(A87,payment_ids!D:E,2,FALSE) -> upi | P87: captured | Q87: 6/14/2021 12:12 PM | S87: https://community.likeminds.community/ahoj-lets-blog | T87: Subscription
A88: =VLOOKUP(L88,payment_ids!C:D,2,FALSE) -> pay_HNCemmHZdCmV6X | C88: Ahoj: Let's Blog | D88: 49997 | F88: 1 | G88: 99 | I88: 99 | J88: mukund@paarthholidays.com | K88: =+918605070300 -> 918605070300 | L88: =CONCAT(J88,K88) -> mukund@paarthholidays.com918605070300 | M88: INR | N88: FALSE | O88: =VLOOKUP(A88,payment_ids!D:E,2,FALSE) -> upi | P88: captured | Q88: 6/15/2021 9:58 AM | S88: https://community.likeminds.community/ahoj-lets-blog | T88: Subscription
A89: =VLOOKUP(L89,payment_ids!C:D,2,FALSE) -> pay_HNCrqJg8lIbNWh | C89: Ahoj: Let's Blog | D89: 49997 | F89: 6 | G89: 349 | I89: 349 | J89: sujit.jena2000@gmail.com | K89: =+919420228386 -> 919420228386 | L89: =CONCAT(J89,K89) -> sujit.jena2000@gmail.com919420228386 | M89: INR | N89: FALSE | O89: =VLOOKUP(A89,payment_ids!D:E,2,FALSE) -> upi | P89: captured | Q89: 6/15/2021 10:10 AM | S89: https://community.likeminds.community/ahoj-lets-blog | T89: Subscription
A90: =VLOOKUP(L90,payment_ids!C:D,2,FALSE) -> pay_HNLkt4VKUgaMtf | C90: Ahoj: Let's Blog | D90: 49997 | F90: 1 | G90: 99 | I90: 99 | J90: saumikmanc@gmail.com | K90: =+919749331382 -> 919749331382 | L90: =CONCAT(J90,K90) -> saumikmanc@gmail.com919749331382 | M90: INR | N90: FALSE | O90: =VLOOKUP(A90,payment_ids!D:E,2,FALSE) -> upi | P90: captured | Q90: 6/15/2021 6:52 PM | S90: https://community.likeminds.community/ahoj-lets-blog | T90: Subscription
A91: =VLOOKUP(L91,payment_ids!C:D,2,FALSE) -> pay_HNhhnpWgwq1eVf | C91: Ahoj: Let's Blog | D91: 49997 | F91: 1 | G91: 99 | I91: 99 | J91: adityaphulsundar5@gmail.com | K91: =+919767053140 -> 919767053140 | L91: =CONCAT(J91,K91) -> adityaphulsundar5@gmail.com919767053140 | M91: INR | N91: FALSE | O91: =VLOOKUP(A91,payment_ids!D:E,2,FALSE) -> upi | P91: captured | Q91: 6/16/2021 4:20 PM | S91: https://community.likeminds.community/ahoj-lets-blog | T91: Subscription
A92: =VLOOKUP(L92,payment_ids!C:D,2,FALSE) -> pay_HNktUTusGwbdDd | C92: Ahoj: Let's Blog | D92: 49997 | F92: 1 | G92: 99 | I92: 99 | J92: thilakamk18@gmail.com | K92: =+919741718758 -> 919741718758 | L92: =CONCAT(J92,K92) -> thilakamk18@gmail.com919741718758 | M92: INR | N92: FALSE | O92: =VLOOKUP(A92,payment_ids!D:E,2,FALSE) -> upi | P92: captured | Q92: 6/16/2021 7:27 PM | S92: https://community.likeminds.community/ahoj-lets-blog | T92: Subscription
A93: =VLOOKUP(L93,payment_ids!C:D,2,FALSE) -> pay_HNoMr0VPC2P2e5 | C93: Ahoj: Let's Blog | D93: 49997 | F93: 6 | G93: 349 | I93: 349 | J93: amitabh.madhuri94@gmail.com | K93: =+919619204241 -> 919619204241 | L93: =CONCAT(J93,K93) -> amitabh.madhuri94@gmail.com919619204241 | M93: INR | N93: FALSE | O93: =VLOOKUP(A93,payment_ids!D:E,2,FALSE) -> card | P93: captured | Q93: 6/16/2021 11:00 PM | S93: https://community.likeminds.community/ahoj-lets-blog | T93: Subscription
A94: =VLOOKUP(L94,payment_ids!C:D,2,FALSE) -> pay_HO0K2n5jZMkRGi | C94: Ahoj: Let's Blog | D94: 49997 | F94: 1 | G94: 99 | I94: 99 | J94: katariamanish899@gmail.com | K94: =+919024031982 -> 919024031982 | L94: =CONCAT(J94,K94) -> katariamanish899@gmail.com919024031982 | M94: INR | N94: FALSE | O94: =VLOOKUP(A94,payment_ids!D:E,2,FALSE) -> upi | P94: captured | Q94: 6/17/2021 10:33 AM | S94: https://community.likeminds.community/ahoj-lets-blog#Pricing | T94: Subscription
A95: =VLOOKUP(L95,payment_ids!C:D,2,FALSE) -> pay_HO58Ewgc2hAYjD | C95: Ahoj: Let's Blog | D95: 49997 | F95: 1 | G95: 99 | I95: 99 | J95: mailme.utkarsh@gmail.com | K95: =+919412906471 -> 919412906471 | L95: =CONCAT(J95,K95) -> mailme.utkarsh@gmail.com919412906471 | M95: INR | N95: FALSE | O95: =VLOOKUP(A95,payment_ids!D:E,2,FALSE) -> upi | P95: captured | Q95: 6/17/2021 3:15 PM | S95: https://community.likeminds.community/ahoj-lets-blog#Pricing | T95: Subscription
A96: =VLOOKUP(L96,payment_ids!C:D,2,FALSE) -> pay_HO67CL8PTuU49D | C96: Ahoj: Let's Blog | D96: 49997 | F96: 1 | G96: 99 | I96: 99 | J96: swati.pushkar11@gmail.com | K96: =+919451358094 -> 919451358094 | L96: =CONCAT(J96,K96) -> swati.pushkar11@gmail.com919451358094 | M96: INR | N96: FALSE | O96: =VLOOKUP(A96,payment_ids!D:E,2,FALSE) -> upi | P96: captured | Q96: 6/17/2021 4:14 PM | S96: https://community.likeminds.community/ahoj-lets-blog | T96: Subscription
A97: =VLOOKUP(L97,payment_ids!C:D,2,FALSE) -> pay_HOD7rtEo3akVU7 | C97: Ahoj: Let's Blog | D97: 49997 | F97: 1 | G97: 99 | I97: 99 | J97: kirti23kalonia@gmail.com | K97: =+917075075300 -> 917075075300 | L97: =CONCAT(J97,K97) -> kirti23kalonia@gmail.com917075075300 | M97: INR | N97: FALSE | O97: =VLOOKUP(A97,payment_ids!D:E,2,FALSE) -> upi | P97: captured | Q97: 6/17/2021 11:05 PM | S97: https://community.likeminds.community/ahoj-lets-blog | T97: Subscription
A98: =VLOOKUP(L98,payment_ids!C:D,2,FALSE) -> pay_HONRd1pQhUm7jO | C98: Ahoj: Let's Blog | D98: 49997 | F98: 1 | G98: 99 | I98: 99 | J98: vyaspratibha7@gmail.com | K98: =+919565090119 -> 919565090119 | L98: =CONCAT(J98,K98) -> vyaspratibha7@gmail.com919565090119 | M98: INR | N98: FALSE | O98: =VLOOKUP(A98,payment_ids!D:E,2,FALSE) -> upi | P98: captured | Q98: 6/18/2021 9:10 AM | S98: https://community.likeminds.community/ahoj-lets-blog | T98: Subscription
A99: =VLOOKUP(L99,payment_ids!C:D,2,FALSE) -> pay_HOVKkdWtxlbuho | C99: Ahoj: Let's Blog | D99: 49997 | F99: 1 | G99: 99 | I99: 99 | J99: manavjhaveri2000@gmail.com | K99: =+919820917454 -> 919820917454 | L99: =CONCAT(J99,K99) -> manavjhaveri2000@gmail.com919820917454 | M99: INR | N99: FALSE | O99: =VLOOKUP(A99,payment_ids!D:E,2,FALSE) -> wallet | P99: captured | Q99: 6/18/2021 4:54 PM | S99: https://community.likeminds.community/ahoj-lets-blog | T99: Subscription
A100: =VLOOKUP(L100,payment_ids!C:D,2,FALSE) -> pay_HM9APFIoVuypDz | C100: Ahoj: Let's Blog | D100: 49997 | F100: 1 | G100: 99 | I100: 99 | J100: praroop.trivedi149@gmail.com | K100: =+919582646447 -> 919582646447 | L100: =CONCAT(J100,K100) -> praroop.trivedi149@gmail.com919582646447 | M100: INR | N100: FALSE | O100: =VLOOKUP(A100,payment_ids!D:E,2,FALSE) -> upi | P100: captured | Q100: 6/19/2021 9:51 AM | S100: https://community.likeminds.community/ahoj-lets-blog | T100: Subscription
...

Sheet payment_ids
A1: email | B1: contact | C1: =CONCAT(A1,B1) -> emailcontact | D1: id
A2: kesavanp_77@yahoo.co.in | B2: =+919841696000 -> 919841696000 | C2: =CONCAT(A2,B2) -> kesavanp_77@yahoo.co.in919841696000 | D2: pay_H5EkwiultUPr2L | E2: card
A3: srishtituteja08@gmail.com | B3: =+919136513535 -> 919136513535 | C3: =CONCAT(A3,B3) -> srishtituteja08@gmail.com919136513535 | D3: pay_H5W1QjuPk82Zxu | E3: upi
A4: yesha.aftab@gmail.com | B4: =+919718917696 -> 919718917696 | C4: =CONCAT(A4,B4) -> yesha.aftab@gmail.com919718917696 | D4: pay_H5aZdWmrCOPv8w | E4: upi
A5: saikishore809@gmail.com | B5: =+919949979809 -> 919949979809 | C5: =CONCAT(A5,B5) -> saikishore809@gmail.com919949979809 | D5: pay_H5ki0PSCLekk4E | E5: upi
A6: kamaliganapathy1998@gmail.com | B6: =+917538888132 -> 917538888132 | C6: =CONCAT(A6,B6) -> kamaliganapathy1998@gmail.com917538888132 | D6: pay_H5qCYp90bYY3IR | E6: upi
A7: himanshusaleria@gmail.com | B7: =+919888470272 -> 919888470272 | C7: =CONCAT(A7,B7) -> himanshusaleria@gmail.com919888470272 | D7: pay_H5seU4HAc7T7Uo | E7: upi
A8: himanshusaleria@gmail.com | B8: =+919888470272 -> 919888470272 | C8: =CONCAT(A8,B8) -> himanshusaleria@gmail.com919888470272 | D8: pay_H5sj9XXNAE8A94 | E8: upi
A9: himanshusaleria@gmail.com | B9: =+919888470272 -> 919888470272 | C9: =CONCAT(A9,B9) -> himanshusaleria@gmail.com919888470272 | D9: pay_H5slgkMTFrOKTg | E9: upi
A10: msnidhi.sharma09@gmail.com | B10: =+919205219728 -> 919205219728 | C10: =CONCAT(A10,B10) -> msnidhi.sharma09@gmail.com919205219728 | D10: pay_H5uhDTPxn4p5GB | E10: upi
A11: 9322296996@tempuser.com | B11: =+919322296996 -> 919322296996 | C11: =CONCAT(A11,B11) -> 9322296996@tempuser.com919322296996 | D11: pay_H5voWwvhqvku3U | E11: card
A12: biswas.manjushree@gmail.com | B12: =+919893352854 -> 919893352854 | C12: =CONCAT(A12,B12) -> biswas.manjushree@gmail.com919893352854 | D12: pay_H6B6gsl5IQqr4D | E12: netbanking
A13: mihirjoshi42@gmail.com | B13: =+917208157797 -> 917208157797 | C13: =CONCAT(A13,B13) -> mihirjoshi42@gmail.com917208157797 | D13: pay_H6BJNaiXBC9lbH | E13: upi
A14: jyotsnab@mdi.ac.in | B14: =+919910448040 -> 919910448040 | C14: =CONCAT(A14,B14) -> jyotsnab@mdi.ac.in919910448040 | D14: pay_H6FI5hqEmx0rQr | E14: upi
A15: saurabhprwl0@gmail.com | B15: =+918860206844 -> 918860206844 | C15: =CONCAT(A15,B15) -> saurabhprwl0@gmail.com918860206844 | D15: pay_H6HCHMdNg2EBjq | E15: wallet
A16: akshita.bpsmv@gmail.com | B16: =+917838168936 -> 917838168936 | C16: =CONCAT(A16,B16) -> akshita.bpsmv@gmail.com917838168936 | D16: pay_H6IQ6rjURebAEN | E16: upi
A17: tara.lanba1999@gmail.com | B17: =+919582439852 -> 919582439852 | C17: =CONCAT(A17,B17) -> tara.lanba1999@gmail.com919582439852 | D17: pay_H6IvfhXVSJtsVU | E17: upi
A18: kushagra249@gmail.com | B18: =+919650225768 -> 919650225768 | C18: =CONCAT(A18,B18) -> kushagra249@gmail.com919650225768 | D18: pay_H6IwUiKNdHcqOa | E18: upi
A19: jai.lanba@likeminds.community | B19: =+919958112731 -> 919958112731 | C19: =CONCAT(A19,B19) -> jai.lanba@likeminds.community919958112731 | D19: pay_H6IynnXpQD3vtu | E19: upi
A20: mukta@mfinserve.co.in | B20: =+919840609903 -> 919840609903 | C20: =CONCAT(A20,B20) -> mukta@mfinserve.co.in919840609903 | D20: pay_H6JewJjwlUQeor | E20: upi
A21: manasgarg28@gmail.com | B21: =+917566220220 -> 917566220220 | C21: =CONCAT(A21,B21) -> manasgarg28@gmail.com917566220220 | D21: pay_H6LyhFlnZPet4L | E21: upi
A22: mahirgupta98@gmail.com | B22: =+919416173796 -> 919416173796 | C22: =CONCAT(A22,B22) -> mahirgupta98@gmail.com919416173796 | D22: pay_H6M18PniZZxhuH | E22: upi
A23: mahirgupta98@gmail.com | B23: =+919416173796 -> 919416173796 | C23: =CONCAT(A23,B23) -> mahirgupta98@gmail.com919416173796 | D23: pay_H6MFOmyP0yzmaG | E23: upi
A24: jaimaran20@gmail.com | B24: =+919344873993 -> 919344873993 | C24: =CONCAT(A24,B24) -> jaimaran20@gmail.com919344873993 | D24: pay_H6MUxD3uiq0qMm | E24: netbanking
A25: nrjmshr14@gmail.com | B25: =+917209943488 -> 917209943488 | C25: =CONCAT(A25,B25) -> nrjmshr14@gmail.com917209943488 | D25: pay_H6OM6mtc3X24p4 | E25: card
A26: tanvimhatre001@gmail.com | B26: =+919969893269 -> 919969893269 | C26: =CONCAT(A26,B26) -> tanvimhatre001@gmail.com919969893269 | D26: pay_H6OZHMGGwhtkMg | E26: card
A27: nandanvangardensolutions@gmail.com | B27: =+917721012926 -> 917721012926 | C27: =CONCAT(A27,B27) -> nandanvangardensolutions@gmail.com917721012926 | D27: pay_H6PH7qQXUHgxfu | E27: upi
A28: nandanvangardensolutions@gmail.com | B28: =+917721012926 -> 917721012926 | C28: =CONCAT(A28,B28) -> nandanvangardensolutions@gmail.com917721012926 | D28: pay_H6PNvHEvhIfTvE | E28: upi
A29: krishnakis@gmail.com | B29: =+919538601160 -> 919538601160 | C29: =CONCAT(A29,B29) -> krishnakis@gmail.com919538601160 | D29: pay_H6Y4xoE46plyib | E29: wallet
A30: abhijit.jha33@gmail.com | B30: =+919711341773 -> 919711341773 | C30: =CONCAT(A30,B30) -> abhijit.jha33@gmail.com919711341773 | D30: pay_H6cZodbxWfXymQ | E30: upi
A31: spoojac@outlook.com | B31: =+919999861974 -> 919999861974 | C31: =CONCAT(A31,B31) -> spoojac@outlook.com919999861974 | D31: pay_H6dDZuXUs5wJYw | E31: upi
A32: dcbs13simranbajaj@gmail.com | B32: =+917389999990 -> 917389999990 | C32: =CONCAT(A32,B32) -> dcbs13simranbajaj@gmail.com917389999990 | D32: pay_H6e19mJSkBnPZl | E32: upi
A33: nawatheygaurav@gmail.com | B33: =+919819252511 -> 919819252511 | C33: =CONCAT(A33,B33) -> nawatheygaurav@gmail.com919819252511 | D33: pay_H6ejsTenhxPtgT | E33: upi
A34: leshanimehra1998@gmail.com | B34: =+918600964699 -> 918600964699 | C34: =CONCAT(A34,B34) -> leshanimehra1998@gmail.com918600964699 | D34: pay_H6gODrRvIOBR2G | E34: upi
A35: jainprachi1385@gmail.com | B35: =+919643061385 -> 919643061385 | C35: =CONCAT(A35,B35) -> jainprachi1385@gmail.com919643061385 | D35: pay_H6gUPHb3HdZe6C | E35: upi
A36: jainprachi1385@gmail.com | B36: =+919643061385 -> 919643061385 | C36: =CONCAT(A36,B36) -> jainprachi1385@gmail.com919643061385 | D36: pay_H6gVGUdkPWXtHP | E36: upi
A37: jainprachi1385@gmail.com | B37: =+919643061385 -> 919643061385 | C37: =CONCAT(A37,B37) -> jainprachi1385@gmail.com919643061385 | D37: pay_H6gWqyN5SdktFR | E37: upi
A38: dezikakol@gmail.com | B38: =+919561542950 -> 919561542950 | C38: =CONCAT(A38,B38) -> dezikakol@gmail.com919561542950 | D38: pay_H6gmIveChQnJtL | E38: netbanking
A39: iamagsusfreak@gmail.com | B39: =+918129282453 -> 918129282453 | C39: =CONCAT(A39,B39) -> iamagsusfreak@gmail.com918129282453 | D39: pay_H6hFPdEWIAM1A2 | E39: upi
A40: kalyanee.bhake@gmail.com | B40: =+919380605339 -> 919380605339 | C40: =CONCAT(A40,B40) -> kalyanee.bhake@gmail.com919380605339 | D40: pay_H6hG9WBnSD7eC3 | E40: upi
A41: adeshtdesigner@gmail.com | B41: =+919962281591 -> 919962281591 | C41: =CONCAT(A41,B41) -> adeshtdesigner@gmail.com919962281591 | D41: pay_H6hn705iFrnOvn | E41: upi
A42: kartiktrogon@gmail.com | B42: =+917348940343 -> 917348940343 | C42: =CONCAT(A42,B42) -> kartiktrogon@gmail.com917348940343 | D42: pay_H6hrVWjE4K9SPx | E42: upi
A43: abhinav.ux@gmail.com | B43: =+919481150184 -> 919481150184 | C43: =CONCAT(A43,B43) -> abhinav.ux@gmail.com919481150184 | D43: pay_H6i9yA5bbdm02Z | E43: wallet
A44: abhinav.ux@gmail.com | B44: =+919481150184 -> 919481150184 | C44: =CONCAT(A44,B44) -> abhinav.ux@gmail.com919481150184 | D44: pay_H6iAjvZbp5Odhu | E44: wallet
A45: abhinav.ux@gmail.com | B45: =+919481150184 -> 919481150184 | C45: =CONCAT(A45,B45) -> abhinav.ux@gmail.com919481150184 | D45: pay_H6iDXjIQFqmR3f | E45: wallet
A46: abhinav.ux@gmail.com | B46: =+919481150184 -> 919481150184 | C46: =CONCAT(A46,B46) -> abhinav.ux@gmail.com919481150184 | D46: pay_H6iGK8h57Yj6fp | E46: wallet
A47: abhinav.ux@gmail.com | B47: =+919481150184 -> 919481150184 | C47: =CONCAT(A47,B47) -> abhinav.ux@gmail.com919481150184 | D47: pay_H6iHDVrt5x4Jh1 | E47: upi
A48: lilitm@live.com | B48: =+919920113130 -> 919920113130 | C48: =CONCAT(A48,B48) -> lilitm@live.com919920113130 | D48: pay_H6iXqvSTHDj1v7 | E48: netbanking
A49: mammai.sravanthi@gmail.com | B49: =+919866992056 -> 919866992056 | C49: =CONCAT(A49,B49) -> mammai.sravanthi@gmail.com919866992056 | D49: pay_H6k7fH2VlH0QbR | E49: upi
A50: pakhi.chakraborty@outlook.com | B50: =+918240806728 -> 918240806728 | C50: =CONCAT(A50,B50) -> pakhi.chakraborty@outlook.com918240806728 | D50: pay_H6kWh8vVU3NDv2 | E50: upi
A51: dhirjaspreet8@gmail.com | B51: =+919210883828 -> 919210883828 | C51: =CONCAT(A51,B51) -> dhirjaspreet8@gmail.com919210883828 | D51: pay_H6kkD9JYywKQ69 | E51: upi
A52: dhirjaspreet8@gmail.com | B52: =+919210883828 -> 919210883828 | C52: =CONCAT(A52,B52) -> dhirjaspreet8@gmail.com919210883828 | D52: pay_H6km5h7FQFEuL1 | E52: upi
A53: sharvarinilesh83@gmail.com | B53: =+916304264925 -> 916304264925 | C53: =CONCAT(A53,B53) -> sharvarinilesh83@gmail.com916304264925 | D53: pay_H6ksnACdqVzbvW | E53: upi
A54: saurabhbudhaulia@gmail.com | B54: =+919594874054 -> 919594874054 | C54: =CONCAT(A54,B54) -> saurabhbudhaulia@gmail.com919594874054 | D54: pay_H6kyKMaSiF7l82 | E54: upi
A55: karthiyes1974@gmail.com | B55: =+919840045101 -> 919840045101 | C55: =CONCAT(A55,B55) -> karthiyes1974@gmail.com919840045101 | D55: pay_H6lDt5RWyqa3U4 | E55: card
A56: saumyaswarup1997@gmail.com | B56: =+919008118984 -> 919008118984 | C56: =CONCAT(A56,B56) -> saumyaswarup1997@gmail.com919008118984 | D56: pay_H6lHCzii2GCyWz | E56: upi
A57: ganeshreddy032@gmail.com | B57: =+919030643339 -> 919030643339 | C57: =CONCAT(A57,B57) -> ganeshreddy032@gmail.com919030643339 | D57: pay_H6lVQFIqAnVJnH | E57: card
A58: karthiyes1974@gmail.com | B58: =+919840045101 -> 919840045101 | C58: =CONCAT(A58,B58) -> karthiyes1974@gmail.com919840045101 | D58: pay_H6lahEhG8taZ1E | E58: upi
A59: ganeshreddy032@gmail.com | B59: =+919030643339 -> 919030643339 | C59: =CONCAT(A59,B59) -> ganeshreddy032@gmail.com919030643339 | D59: pay_H6lakmhD6MSWBF | E59: card
A60: ganeshreddy032@gmail.com | B60: =+919030643339 -> 919030643339 | C60: =CONCAT(A60,B60) -> ganeshreddy032@gmail.com919030643339 | D60: pay_H6lbTHOU4ltPL6 | E60: wallet
A61: ganeshreddy032@gmail.com | B61: =+919030643339 -> 919030643339 | C61: =CONCAT(A61,B61) -> ganeshreddy032@gmail.com919030643339 | D61: pay_H6lcsM03oXkFYZ | E61: wallet
A62: asudi1003@gmail.com | B62: =+918850267427 -> 918850267427 | C62: =CONCAT(A62,B62) -> asudi1003@gmail.com918850267427 | D62: pay_H6lgl4WJbJMGuf | E62: upi
A63: tobindiya@gmail.com | B63: =+919886180731 -> 919886180731 | C63: =CONCAT(A63,B63) -> tobindiya@gmail.com919886180731 | D63: pay_H6m2NLQGW20qHZ | E63: wallet
A64: tobindiya@gmail.com | B64: =+919886180731 -> 919886180731 | C64: =CONCAT(A64,B64) -> tobindiya@gmail.com919886180731 | D64: pay_H6mDmvSzYTAZ1G | E64: upi
A65: drpallawibishnoi@gmail.com | B65: =+918755661125 -> 918755661125 | C65: =CONCAT(A65,B65) -> drpallawibishnoi@gmail.com918755661125 | D65: pay_H6mXfd9acT25Mr | E65: upi
A66: jasleen2892@gmail.com | B66: =+918109272227 -> 918109272227 | C66: =CONCAT(A66,B66) -> jasleen2892@gmail.com918109272227 | D66: pay_H6mdTBWAVKlggZ | E66: upi
A67: singh.renu2310@gmail.com | B67: =+919711351917 -> 919711351917 | C67: =CONCAT(A67,B67) -> singh.renu2310@gmail.com919711351917 | D67: pay_H6mlWO8MHbWT18 | E67: card
A68: drashtiartistry@gmail.com | B68: =+917888699913 -> 917888699913 | C68: =CONCAT(A68,B68) -> drashtiartistry@gmail.com917888699913 | D68: pay_H6mzGpdFagGjob | E68: card
A69: ravurimadhavi@ymail.com | B69: =+919820157581 -> 919820157581 | C69: =CONCAT(A69,B69) -> ravurimadhavi@ymail.com919820157581 | D69: pay_H6nDjePTeW4yl6 | E69: wallet
A70: ashajohns@gmail.com | B70: =+919845345383 -> 919845345383 | C70: =CONCAT(A70,B70) -> ashajohns@gmail.com919845345383 | D70: pay_H6nJl9n5Yk8MrB | E70: upi
A71: m.dharan85@gmail.com | B71: =+918792100662 -> 918792100662 | C71: =CONCAT(A71,B71) -> m.dharan85@gmail.com918792100662 | D71: pay_H6o32hjh32pGfa | E71: upi
A72: freelanceryunesh@gmail.com | B72: =+917584018683 -> 917584018683 | C72: =CONCAT(A72,B72) -> freelanceryunesh@gmail.com917584018683 | D72: pay_H6oOcVynxOWYMI | E72: card
A73: deepikasha101@gmail.com | B73: =+917307203410 -> 917307203410 | C73: =CONCAT(A73,B73) -> deepikasha101@gmail.com917307203410 | D73: pay_H6oerOQel7Ikfd | E73: upi
A74: deepikasha101@gmail.com | B74: =+917307203410 -> 917307203410 | C74: =CONCAT(A74,B74) -> deepikasha101@gmail.com917307203410 | D74: pay_H6ohpxiOC10MAn | E74: upi
A75: deepikasha101@gmail.com | B75: =+917307203410 -> 917307203410 | C75: =CONCAT(A75,B75) -> deepikasha101@gmail.com917307203410 | D75: pay_H6oiVghWgQXPng | E75: upi
A76: deepikasha101@gmail.com | B76: =+917307203410 -> 917307203410 | C76: =CONCAT(A76,B76) -> deepikasha101@gmail.com917307203410 | D76: pay_H6ojDrU6gIcqqs | E76: upi
A77: pawsomelove10@gmail.com | B77: =+919619523948 -> 919619523948 | C77: =CONCAT(A77,B77) -> pawsomelove10@gmail.com919619523948 | D77: pay_H6okWm1rcL46xM | E77: card
A78: crupam714@gmail.com | B78: =+919330771104 -> 919330771104 | C78: =CONCAT(A78,B78) -> crupam714@gmail.com919330771104 | D78: pay_H6qjW9ICOOLM7A | E78: upi
A79: rohan.reginald@gmail.com | B79: =+917337511411 -> 917337511411 | C79: =CONCAT(A79,B79) -> rohan.reginald@gmail.com917337511411 | D79: pay_H6qzgrdHqxixwf | E79: upi
A80: kasagani.swetha@gmail.com | B80: =+919849871751 -> 919849871751 | C80: =CONCAT(A80,B80) -> kasagani.swetha@gmail.com919849871751 | D80: pay_H6uaMh49riAXxg | E80: card
A81: ganeshreddy032@gmail.com | B81: =+919030643339 -> 919030643339 | C81: =CONCAT(A81,B81) -> ganeshreddy032@gmail.com919030643339 | D81: pay_H6v2EnTR878sUW | E81: wallet
A82: yoshitha.k11@gmail.com | B82: =+918328361154 -> 918328361154 | C82: =CONCAT(A82,B82) -> yoshitha.k11@gmail.com918328361154 | D82: pay_H6vqOrOdRHnijW | E82: upi
A83: pallavi.dua008@gmail.com | B83: =+919873965908 -> 919873965908 | C83: =CONCAT(A83,B83) -> pallavi.dua008@gmail.com919873965908 | D83: pay_H6wiS8dEIzuvTo | E83: upi
A84: pallavi.dua008@gmail.com | B84: =+919873965908 -> 919873965908 | C84: =CONCAT(A84,B84) -> pallavi.dua008@gmail.com919873965908 | D84: pay_H6wm9CYj4pmu3R | E84: upi
A85: saravanaraaj@rediffmail.com | B85: =+919738738229 -> 919738738229 | C85: =CONCAT(A85,B85) -> saravanaraaj@rediffmail.com919738738229 | D85: pay_H6wnNOFzH0zzcL | E85: netbanking
A86: saravanaraaj@rediffmail.com | B86: =+919738738229 -> 919738738229 | C86: =CONCAT(A86,B86) -> saravanaraaj@rediffmail.com919738738229 | D86: pay_H6x0UVzk0Huagq | E86: netbanking
A87: benadikam@gmail.com | B87: =+919860729292 -> 919860729292 | C87: =CONCAT(A87,B87) -> benadikam@gmail.com919860729292 | D87: pay_H6xvuIL5Vvmaww | E87: upi
A88: charakmandalrahul@gmail.com | B88: =+919717661421 -> 919717661421 | C88: =CONCAT(A88,B88) -> charakmandalrahul@gmail.com919717661421 | D88: pay_H6y92uQ4R8K0fX | E88: upi
A89: meenamundada@gmail.com | B89: =+919890414205 -> 919890414205 | C89: =CONCAT(A89,B89) -> meenamundada@gmail.com919890414205 | D89: pay_H6yZStlMPWcVYF | E89: card
A90: shreymaheshwari007@gmail.com | B90: =+918439332423 -> 918439332423 | C90: =CONCAT(A90,B90) -> shreymaheshwari007@gmail.com918439332423 | D90: pay_H6ycnDJxYToOqt | E90: card
A91: dikshajhamtani01@gmail.com | B91: =+918377880192 -> 918377880192 | C91: =CONCAT(A91,B91) -> dikshajhamtani01@gmail.com918377880192 | D91: pay_H6ykqhq4Ec9r3X | E91: upi
A92: kavita.rudagi@gmail.com | B92: =+919673390777 -> 919673390777 | C92: =CONCAT(A92,B92) -> kavita.rudagi@gmail.com919673390777 | D92: pay_H6yxNC4t4oGEnj | E92: upi
A93: bahulika26@gmail.com | B93: =+917780528356 -> 917780528356 | C93: =CONCAT(A93,B93) -> bahulika26@gmail.com917780528356 | D93: pay_H6zxAwi7kO6fTS | E93: upi
A94: bahulika26@gmail.com | B94: =+917780528356 -> 917780528356 | C94: =CONCAT(A94,B94) -> bahulika26@gmail.com917780528356 | D94: pay_H6zyEsrCZfMcov | E94: upi
A95: niveditachaudhary7@gmail.com | B95: =+918826765482 -> 918826765482 | C95: =CONCAT(A95,B95) -> niveditachaudhary7@gmail.com918826765482 | D95: pay_H70JBrjNLqWyAI | E95: wallet
A96: rathinandhu8378@gmail.com | B96: =+917760876077 -> 917760876077 | C96: =CONCAT(A96,B96) -> rathinandhu8378@gmail.com917760876077 | D96: pay_H70Q0yvycc14eV | E96: netbanking
A97: rajpreettomar@gmail.com | B97: =+919599577212 -> 919599577212 | C97: =CONCAT(A97,B97) -> rajpreettomar@gmail.com919599577212 | D97: pay_H70eSyfVcAh8Oh | E97: card
A98: travelwithfreddie@gmail.com | B98: =+919998728170 -> 919998728170 | C98: =CONCAT(A98,B98) -> travelwithfreddie@gmail.com919998728170 | D98: pay_H70f2pvlDc6itm | E98: upi
A99: supriyaladdu97@gmail.com | B99: =+919182060469 -> 919182060469 | C99: =CONCAT(A99,B99) -> supriyaladdu97@gmail.com919182060469 | D99: pay_H710pMmlAtLRID | E99: upi
A100: sparvathi28@gmail.com | B100: =+919840374939 -> 919840374939 | C100: =CONCAT(A100,B100) -> sparvathi28@gmail.com919840374939 | D100: pay_H71EUCRPLkLTko | E100: upi
...

Sheet Transaction data
A1: payment_id | B1: created_at | C1: Community_id | D1: email | E1: contact | F1: Users | G1: plan_id | H1: Community Name | I1: plan_name | J1: plan_duration | K1: plan_cost | L1: renew | M1: amount | N1: currency | O1: is_international | P1: method | Q1: status | R1: payment_page_url
A2: pay_HMGCDlUtbqpVRR | B2: 6/13/2021 12:46 AM | C2: 49833 | D2: rashmijagtap63@gmail.com | E2: 918983081469 | F2: 17571 | H2: Han Hangul | J2: 1 | K2: 149 | M2: 149 | N2: INR | O2: FALSE | P2: upi | Q2: captured | R2: https://community.likeminds.community/hanhangul
A3: pay_H78Oq2bTVvVg4d | B3: 44321.808 | C3: 49844 | D3: rashmijagtap63@gmail.com | E3: 918983081469 | F3: 17571 | H3: Pharmacology Insiders | J3: 1 | K3: 99 | M3: 99 | N3: INR | O3: FALSE | P3: upi | Q3: captured | R3: https://community.likeminds.community/pharmacology-insiders#Pricing
A4: pay_H79ecxRYLhYp69 | B4: 44321.867 | C4: 50073 | D4: parulmehra84@gmail.com | E4: 919811316353 | F4: 17854 | H4: well being | J4: 1 | K4: 599 | M4: 599 | N4: INR | O4: FALSE | P4: wallet | Q4: captured
A5: pay_HKpsmVMmxwn8wn | B5: 44445.433 | C5: 50073 | D5: parulmehra84@gmail.com | E5: 919811316353 | F5: 17854 | H5: Well Being | J5: 1 | K5: 599 | M5: 599 | N5: INR | O5: FALSE | P5: wallet | Q5: captured | R5: https://hi.likeminds.community/well-being-renewal
A6: pay_H7AoWjPWQKyOjD | B6: 44321.907 | C6: 50073 | D6: sunderr20@gmail.com | E6: 919036755270 | F6: 17904 | H6: well being | J6: 1 | K6: 599 | M6: 599 | N6: INR | O6: FALSE | P6: netbanking | Q6: captured
A7: pay_HIYism5n7QdO6s | B7: 44261.68 | C7: 50073 | D7: sunderr20@gmail.com | E7: 919036755270 | F7: 17904 | H7: Well Being | J7: 1 | K7: 599 | M7: 599 | N7: INR | O7: FALSE | P7: netbanking | Q7: captured | R7: https://hi.likeminds.community/well-being-renewal
A8: pay_H7PltBUerzfnEK | B8: 44352.516 | C8: 50073 | D8: ma.arora@yahoo.in | E8: 919899837660 | F8: 17746 | H8: well being | J8: 1 | K8: 599 | M8: 599 | N8: INR | O8: FALSE | P8: upi | Q8: captured
A9: pay_HKTjWBOEXedT85 | B9: 44414.531 | C9: 50073 | D9: ma.arora@yahoo.in | E9: 919899837660 | F9: 17746 | H9: Well Being | J9: 3 | K9: 1499 | M9: 1499 | N9: INR | O9: FALSE | P9: upi | Q9: captured | R9: https://hi.likeminds.community/well-being-renewal
A10: pay_H7s90KcgRbvZUb | B10: 44382.674 | C10: 49834 | D10: harinsrini@gmail.com | E10: 917708066310 | F10: 17657 | H10: Deutsch In Tandem | J10: 3 | K10: 199 | M10: 199 | N10: INR | O10: FALSE | P10: upi | Q10: captured | R10: https://community.likeminds.community/deutsch-in-tandem
A11: pay_HIURXYtKsQCagS | B11: 44261.505 | C11: 50113 | D11: harinsrini@gmail.com | E11: 917708066310 | F11: 17657 | H11: Learn German with Heer | I11: PLATINUM | J11: 1 | K11: 499 | M11: 499 | N11: INR | O11: FALSE | P11: upi | Q11: captured | R11: https://hi.likeminds.community/d/heer-haria
A12: pay_H7tfEV5loA8BGL | B12: 44382.738 | C12: 50029 | D12: anjalityagi2014@gmail.com | E12: 919868133035 | F12: 17662 | H12: Bonjour Amis French | J12: 1 | K12: 99 | M12: 99 | N12: INR | O12: FALSE | P12: upi | Q12: captured | R12: https://hi.likeminds.community/d/bonjour-amis-french
A13: pay_HOTUXwXvKWQvPi | B13: 6/18/2021 3:05 PM | C13: 50029 | D13: anjalityagi2014@gmail.com | E13: 919868133035 | F13: 17662 | H13: Bonjour Amis French | J13: 3 | K13: 199 | M13: 199 | N13: INR | O13: FALSE | P13: upi | Q13: captured | R13: https://hi.likeminds.community/d/bonjour-amis-french
A14: pay_H7WOZFoeRgG2zC | B14: 44352.786 | C14: 49991 | D14: ajitrai.ajit@gmail.com | E14: 918953547813 | F14: Not Found - Join Record | H14: DeBattlers | J14: 1 | K14: 99 | M14: 99 | N14: INR | O14: FALSE | P14: upi | Q14: captured | R14: https://community.likeminds.community/debattlers
A15: pay_HIqsOugF7OJZZj | B15: 44292.419 | C15: 49991 | D15: ajitrai.ajit@gmail.com | E15: 918953547813 | F15: Not Found - Join Record | H15: DeBattlers | J15: 1 | K15: 99 | M15: 99 | N15: INR | O15: FALSE | P15: upi | Q15: captured | R15: https://community.likeminds.community/debattlers
A16: pay_H7WQcnVXRTRmkm | B16: 44352.787 | C16: 50073 | D16: inv.anshu@gmail.com | E16: 919448847519 | F16: 17738 | H16: well being | J16: 1 | K16: 599 | M16: 599 | N16: INR | O16: FALSE | P16: upi | Q16: captured
A17: pay_HKSQEkxMojypN6 | B17: 44414.477 | C17: 50073 | D17: inv.anshu@gmail.com | E17: 919448847519 | F17: 17738 | H17: Well Being | J17: 1 | K17: 599 | M17: 599 | N17: INR | O17: FALSE | P17: upi | Q17: captured | R17: https://hi.likeminds.community/well-being-renewal
A18: pay_H7WwbyTsx1i8nZ | B18: 44352.81 | C18: 50073 | D18: annusmail@gmail.com | E18: 918447208914 | F18: 17607 | H18: well being | J18: 1 | K18: 599 | M18: 599 | N18: INR | O18: FALSE | P18: netbanking | Q18: captured
A19: pay_HLN4QrIoQo1UVS | B19: 44475.785 | C19: 50073 | D19: annusmail@gmail.com | E19: 918447208914 | F19: 17607 | H19: Well Being | J19: 1 | K19: 599 | M19: 599 | N19: INR | O19: FALSE | P19: netbanking | Q19: captured | R19: https://hi.likeminds.community/well-being-renewal
A20: pay_H8ArZr4fzcp28O | B20: 44413.437 | C20: 49859 | D20: kumar.avinab@yahoo.com | E20: 919632670331 | F20: 17702 | H20: Ladies & Gentlemen | J20: 1 | K20: 99 | M20: 99 | N20: INR | O20: FALSE | P20: wallet | Q20: captured | R20: https://community.likeminds.community/ladies-and-gentlemen
A21: pay_H8Ajs6TmcwP2uq | B21: 44413.438 | C21: 49859 | D21: kumar.avinab@yahoo.com | E21: 919632670331 | F21: 17702 | H21: Ladies & Gentlemen | J21: 1 | K21: 99 | M21: 99 | N21: INR | O21: FALSE | P21: wallet | Q21: captured | R21: https://community.likeminds.community/ladies-and-gentlemen
A22: pay_H8An4U5m9l9dyL | B22: 44413.433 | C22: 50039 | D22: s.swethadri@gmail.com | E22: 919742197987 | F22: 17703 | H22: Happy Ashram | J22: 1 | K22: 99 | M22: 99 | N22: INR | O22: FALSE | P22: upi | Q22: captured | R22: https://hi.likeminds.community/d/happy-ashram
A23: pay_H8hw205XNKRrqg | B23: 44444.784 | C23: 50054 | D23: s.swethadri@gmail.com | E23: 919742197987 | F23: 17703 | H23: Rapto Bhara Jeevan | J23: 1 | K23: 99 | M23: 99 | N23: INR | O23: FALSE | P23: upi | Q23: captured | R23: https://hi.likeminds.community/d/rapto-bhara-jeevan
A24: pay_H8CNawhCwRnUle | B24: 44413.499 | C24: 50073 | D24: rishiti.rao_11@rediffmail.com | E24: 919898956482 | F24: 17761 | H24: well being | J24: 1 | K24: 599 | M24: 599 | N24: INR | O24: FALSE | P24: wallet | Q24: captured
A25: pay_HKpwBUN0Z2PINn | B25: 44445.435 | C25: 50073 | D25: rishiti.rao_11@rediffmail.com | E25: 919898956482 | F25: 17761 | H25: Well Being | J25: 1 | K25: 599 | M25: 599 | N25: INR | O25: FALSE | P25: wallet | Q25: captured | R25: https://hi.likeminds.community/well-being-renewal
A26: pay_H8DtE8iMVlbKl1 | B26: 44413.559 | C26: 50044 | D26: gladiators.eternity@gmail.com | E26: 918886237899 | F26: 17710 | H26: Through Thick and Thin | J26: 1 | K26: 349 | M26: 349 | N26: INR | O26: FALSE | P26: upi | Q26: captured | R26: https://hi.likeminds.community/d/through-thick-and-thin
A27: pay_HJKVdqR9dkfIo6 | B27: 44322.627 | C27: 50044 | D27: gladiators.eternity@gmail.com | E27: 918886237899 | F27: 17710 | H27: Through Thick and Thin | J27: 3 | K27: 599 | M27: 599 | N27: INR | O27: FALSE | P27: upi | Q27: captured | R27: https://hi.likeminds.community/d/through-thick-and-thin
A28: pay_H8FRhmUKx85pZI | B28: 44413.623 | C28: 50031 | D28: guptamona911@gmail.com | E28: 919322798720 | F28: 0 | H28: Khushi Se Yoga | J28: 1 | K28: 99 | M28: 99 | N28: INR | O28: FALSE | P28: card | Q28: captured | R28: https://hi.likeminds.community/khushi-se-yoga
A29: pay_H8kKtxYR8s3iPY | B29: 44444.882 | C29: 49994 | D29: guptamona911@gmail.com | E29: 919322798720 | F29: 0 | H29: Yo Geek | J29: 3 | K29: 199 | M29: 199 | N29: INR | O29: FALSE | P29: card | Q29: captured | R29: https://community.likeminds.community/yo-geek-the-modern-yogi
A30: pay_H8gpu2z42QNfro | B30: 44444.739 | C30: 50043 | D30: sanket.kondekar4@gmail.com | E30: 917972793242 | F30: 17824 | H30: Transformed Finance Professionals | J30: 1 | K30: 99 | M30: 99 | N30: INR | O30: FALSE | P30: upi | Q30: captured | R30: https://hi.likeminds.community/d/transformed-finance-professionals
A31: pay_HLdrCmweG25Sp0 | B31: 44506.47 | C31: 50043 | D31: sanket.kondekar4@gmail.com | E31: 917972793242 | F31: 17824 | H31: Transformed Finance Professionals | J31: 3 | K31: 199 | M31: 199 | N31: INR | O31: FALSE | P31: upi | Q31: captured | R31: https://hi.likeminds.community/d/transformed-finance-professionals
A32: pay_H8h7Z0hESE86Nv | B32: 44444.751 | C32: 49998 | D32: kratirajak971@gmail.com | E32: 919713435860 | F32: 17825 | H32: The Smart Work for NEET- UG | J32: 1 | K32: 99 | M32: 99 | N32: INR | O32: FALSE | P32: upi | Q32: captured | R32: https://community.likeminds.community/the-smart-work-for-neet-ug
A33: pay_HIsbIwZrdQlRES | B33: 44292.49 | C33: 49998 | D33: kratirajak971@gmail.com | E33: 919713435860 | F33: 17825 | H33: The Smart Work for NEET- UG | J33: 3 | K33: 199 | M33: 199 | N33: INR | O33: FALSE | P33: upi | Q33: captured | R33: https://community.likeminds.community/the-smart-work-for-neet-ug
A34: pay_H8iUznqpQgG5Ys | B34: 44444.807 | C34: 50054 | D34: gaurav.sindhiya@gmail.com | E34: 919993209318 | F34: 17834 | H34: Rapto Bhara Jeevan | J34: 1 | K34: 99 | M34: 99 | N34: INR | O34: FALSE | P34: wallet | Q34: captured | R34: https://hi.likeminds.community/d/rapto-bhara-jeevan
A35: pay_HIpQuvSIW1JbZi | B35: 44292.36 | C35: 50054 | D35: gaurav.sindhiya@gmail.com | E35: 919993209318 | F35: 17834 | H35: Rapto Bhara Jeevan | J35: 1 | K35: 99 | M35: 99 | N35: INR | O35: FALSE | P35: wallet | Q35: captured | R35: https://hi.likeminds.community/d/rapto-bhara-jeevan
A36: pay_H8jici6xtW4qW9 | B36: 44444.857 | C36: 50009 | D36: lakshmimadeti23@gmail.com | E36: 919912636113 | F36: Not Found - Join Record | H36: Blooming Rush | J36: 1 | K36: 99 | M36: 99 | N36: INR | O36: FALSE | P36: upi | Q36: captured | R36: https://hi.likeminds.community/blooming-rush
A37: pay_HHBqVsd4JPCpJn | B37: 5/31/2021 5:16 AM | C37: 50076 | D37: lakshmimadeti23@gmail.com | E37: 919912636113 | F37: 17838 | H37: Spokken | J37: 1 | K37: 199 | M37: 199 | N37: INR | O37: FALSE | P37: upi | Q37: captured | R37: https://hi.likeminds.community/d/spokken-2
A38: pay_H8JuvMG5c9y8og | B38: 44413.806 | C38: 50073 | D38: bharathipaddy@gmail.com | E38: 919844939825 | F38: 17751 | H38: well being | J38: 1 | K38: 599 | M38: 599 | N38: INR | O38: FALSE | P38: wallet | Q38: captured
A39: pay_HKU93mJD7JoOEL | B39: 44414.547 | C39: 50073 | D39: bharathipaddy@gmail.com | E39: 919844939825 | F39: 17751 | H39: Well Being | J39: 1 | K39: 599 | M39: 599 | N39: INR | O39: FALSE | P39: wallet | Q39: captured | R39: https://hi.likeminds.community/well-being-renewal
A40: pay_HDqTwJrJrBqUj1 | B40: 5/22/2021 6:25 PM | C40: 50079 | D40: sanya.sabharwal@gmail.com | E40: 919953295925 | F40: 17839 | H40: Happiness Fountain | J40: 1 | K40: 199 | M40: 199 | N40: INR | O40: FALSE | P40: upi | Q40: captured | R40: https://hi.likeminds.community/d/happiness-fountain
A41: pay_H8k2qERpMIkRZa | B41: 44444.87 | C41: 50046 | D41: sanya.sabharwal@gmail.com | E41: 919953295925 | F41: 17839 | H41: The Man Makeover | J41: 6 | K41: 349 | M41: 349 | N41: INR | O41: FALSE | P41: upi | Q41: captured | R41: https://hi.likeminds.community/d/the-man-makeover
A42: pay_HIdyrkKljLDoI2 | B42: 44261.894 | C42: 49859 | D42: singhsangeet120@gmail.com | E42: 919756031125 | F42: 17840 | H42: Ladies & Gentlemen | J42: 1 | K42: 99 | M42: 99 | N42: INR | O42: FALSE | P42: upi | Q42: captured | R42: https://hi.likeminds.community/ladies-and-gentlemen
A43: pay_H8kBQLFhTmVAB4 | B43: 44444.876 | C43: 50046 | D43: singhsangeet120@gmail.com | E43: 919756031125 | F43: Not Found - Join Record | H43: The Man Makeover | J43: 1 | K43: 99 | M43: 99 | N43: INR | O43: FALSE | P43: upi | Q43: captured | R43: https://hi.likeminds.community/d/the-man-makeover
A44: pay_HFgoaTyKkqoafQ | B44: 5/27/2021 10:16 AM | C44: 50065 | D44: padmaja.sreerangam@gmail.com | E44: 918454949008 | F44: 17847 | H44: Being Earthable | J44: 3 | K44: 199 | M44: 199 | N44: INR | O44: FALSE | P44: card | Q44: captured | R44: https://hi.likeminds.community/d/being-earthable
A45: pay_H8llyW3jP3FPJq | B45: 44444.94 | C45: 50054 | D45: padmaja.sreerangam@gmail.com | E45: 918454949008 | F45: 17847 | H45: Rapto Bhara Jeevan | J45: 6 | K45: 349 | M45: 349 | N45: INR | O45: FALSE | P45: card | Q45: captured | R45: https://hi.likeminds.community/d/rapto-bhara-jeevan
A46: pay_HJHYkFLIbiXR0a | B46: 44444.954 | C46: 50054 | D46: manjotkaurrathore@gmail.com | E46: 918375983569 | F46: 17850 | H46: Rapto Bhara Jeevan | J46: 1 | K46: 99 | M46: 99 | N46: INR | O46: FALSE | P46: card | Q46: captured | R46: https://hi.likeminds.community/d/rapto-bhara-jeevan
A47: pay_H8m6rgwsbIIrPi | B47: 44322.507 | C47: 50054 | D47: manjotkaurrathore@gmail.com | E47: 918375983569 | F47: 17850 | H47: Rapto Bhara Jeevan | J47: 1 | K47: 99 | M47: 99 | N47: INR | O47: FALSE | P47: card | Q47: captured | R47: https://hi.likeminds.community/d/rapto-bhara-jeevan
A48: pay_H8OncwGBOIh52J | B48: 44444.004 | C48: 50031 | D48: umasnairassocham@gmail.com | E48: 919036333975 | F48: 17768 | H48: Khushi Se Yoga | J48: 1 | K48: 99 | M48: 99 | N48: INR | O48: FALSE | P48: upi | Q48: captured | R48: https://hi.likeminds.community/khushi-se-yoga
A49: pay_HIoefYIAohqzHm | B49: 44292.328 | C49: 50031 | D49: umasnairassocham@gmail.com | E49: 919036333975 | F49: 17768 | H49: Khushi Se Yoga | J49: 1 | K49: 599 | M49: 599 | N49: INR | O49: FALSE | P49: upi | Q49: captured | R49: https://hi.likeminds.community/khushi-se-yoga
A50: pay_H8SPqH2isEFhRv | B50: 44444.151 | C50: 50044 | D50: jesal3ster@gmail.com | E50: 919820395010 | F50: 17773 | H50: Through Thick and Thin | J50: 1 | K50: 349 | M50: 349 | N50: INR | O50: FALSE | P50: upi | Q50: captured | R50: https://hi.likeminds.community/d/through-thick-and-thin
A51: pay_HJ1pVVteJXFbCi | B51: 44292.865 | C51: 50044 | D51: jesal3ster@gmail.com | E51: 919820395010 | F51: 17773 | H51: Through Thick and Thin | J51: 6 | K51: 999 | M51: 999 | N51: INR | O51: FALSE | P51: upi | Q51: captured | R51: https://hi.likeminds.community/d/through-thick-and-thin
A52: pay_H8WgZbfhTb655n | B52: 44444.325 | C52: 49998 | D52: naman0035@gmail.com | E52: 918669123501 | F52: 17780 | H52: The Smart Work for NEET- UG | J52: 1 | K52: 99 | M52: 99 | N52: INR | O52: FALSE | P52: upi | Q52: captured | R52: https://community.likeminds.community/the-smart-work-for-neet-ug
A53: pay_HJK59lVnbQ5pKV | B53: 44322.61 | C53: 49998 | D53: naman0035@gmail.com | E53: 918669123501 | F53: 17780 | H53: The Smart Work for NEET- UG | J53: 3 | K53: 199 | M53: 199 | N53: INR | O53: FALSE | P53: upi | Q53: captured | R53: https://community.likeminds.community/the-smart-work-for-neet-ug
A54: pay_HF3f6J31iNZ8eZ | B54: 5/25/2021 7:58 PM | C54: 50039 | D54: divya.batraconnect@gmail.com | E54: 919899824290 | F54: Not Found - Join Record | H54: Happy Ashram | J54: 1 | K54: 99 | M54: 99 | N54: INR | O54: FALSE | P54: upi | Q54: captured | R54: https://hi.likeminds.community/d/happy-ashram
A55: pay_H8zW2N7UwsDguG | B55: 44474.501 | C55: 50054 | D55: divya.batraconnect@gmail.com | E55: 919899824290 | F55: Not Found - Join Record | H55: Rapto Bhara Jeevan | J55: 1 | K55: 99 | M55: 99 | N55: INR | O55: FALSE | P55: upi | Q55: captured | R55: https://hi.likeminds.community/d/rapto-bhara-jeevan
A56: pay_H938684ZVXI648 | B56: 44474.647 | C56: 50046 | D56: santhosh8975@gmail.com | E56: 919449692235 | F56: 16820 | H56: The Man Makeover | J56: 1 | K56: 99 | M56: 99 | N56: INR | O56: FALSE | P56: upi | Q56: captured | R56: https://hi.likeminds.community/d/the-man-makeover
A57: pay_HKTn56BpGn38Ug | B57: 44414.532 | C57: 50046 | D57: santhosh8975@gmail.com | E57: 919449692235 | F57: 16820 | H57: The Man Makeover | J57: 3 | K57: 199 | M57: 199 | N57: INR | O57: FALSE | P57: upi | Q57: captured | R57: https://hi.likeminds.community/d/the-man-makeover
A58: pay_H94GAeo2tdbs0V | B58: 44474.701 | C58: 49813 | D58: shefalipoojary@gmail.com | E58: 919619857736 | F58: 17903 | H58: Mom Shares Club | J58: 1 | K58: 299 | M58: 299 | N58: INR | O58: FALSE | P58: card | Q58: captured | R58: https://community.likeminds.community/mom-shares-club
A59: pay_HKs3FpXJ0GJsZx | B59: 44445.522 | C59: 49813 | D59: shefalipoojary@gmail.com | E59: 919619857736 | F59: 17903 | H59: Mom Shares Club | J59: 3 | K59: 499 | M59: 499 | N59: INR | O59: FALSE | P59: card | Q59: captured | R59: https://community.likeminds.community/mom-shares-club
A60: pay_H94nyrYxAqIm1e | B60: 44474.716 | C60: 50073 | D60: drtulikasen@gmail.com | E60: 919560575373 | F60: 19615 | H60: well being | J60: 1 | K60: 599 | M60: 599 | N60: INR | O60: FALSE | P60: card | Q60: captured
A61: pay_HOv9f0rjj0os55 | B61: 6/19/2021 6:08 PM | C61: 50073 | D61: drtulikasen@gmail.com | E61: 919560575373 | F61: 19615 | H61: Well Being | J61: 3 | K61: 2199 | M61: 2199 | N61: INR | O61: FALSE | P61: card | Q61: captured | R61: https://community.likeminds.community/well-being
A62: pay_H96AgOMza0aMjd | B62: 44474.814 | C62: 50066 | D62: ujjwalakasbekar70@gmail.com | E62: 919592142724 | F62: 17922 | H62: BSB Life Academy | J62: 1 | K62: 199 | M62: 199 | N62: INR | O62: FALSE | P62: upi | Q62: captured | R62: https://hi.likeminds.community/d/bsb-life-academy
A63: pay_HHQgCavpQVIFq1 | B63: 5/31/2021 7:49 PM | C63: 50066 | D63: ujjwalakasbekar70@gmail.com | E63: 919592142724 | F63: 17922 | H63: BSB Life Academy | J63: 6 | K63: 2359 | M63: 2359 | N63: INR | O63: FALSE | P63: upi | Q63: captured | R63: https://hi.likeminds.community/d/bsb-life-academy
A64: pay_H97t467qVM8339 | B64: 44474.842 | C64: 49998 | D64: pawansikarwar1999@gmail.com | E64: 917489431071 | F64: 17981 | H64: The Smart Work for NEET- UG | J64: 3 | K64: 199 | M64: 199 | N64: INR | O64: FALSE | P64: upi | Q64: captured | R64: https://community.likeminds.community/the-smart-work-for-neet-ug
A65: pay_H9ChAVcoEmfD62 | B65: 44505.037 | C65: 50031 | D65: amahante@gmail.com | E65: 918892009696 | F65: 17941 | H65: Khushi Se Yoga | J65: 1 | K65: 99 | M65: 99 | N65: INR | O65: FALSE | P65: upi | Q65: captured | R65: https://hi.likeminds.community/khushi-se-yoga
A66: pay_HLjdg3OTYlNCiz | B66: 44506.706 | C66: 50031 | D66: amahante@gmail.com | E66: 918892009696 | F66: 17941 | H66: Khushi Se Yoga | J66: 1 | K66: 599 | M66: 599 | N66: INR | O66: FALSE | P66: upi | Q66: captured | R66: https://hi.likeminds.community/khushi-se-yoga
A67: pay_H9lFGxQpdLktX0 | B67: 44535.447 | C67: 50073 | D67: rpreet8@gmail.com | E67: 919915425644 | F67: 18008 | H67: well being | J67: 1 | K67: 599 | M67: 599 | N67: INR | O67: FALSE | P67: upi | Q67: captured
A68: pay_HO9PI0vExranEC | B68: 6/17/2021 7:27 PM | C68: 50073 | D68: rpreet8@gmail.com | E68: 919915425644 | F68: 18008 | H68: Well Being | J68: 1 | K68: 799 | M68: 799 | N68: INR | O68: FALSE | P68: upi | Q68: captured | R68: https://community.likeminds.community/well-being#Pricing
A69: pay_H9M5oJD8als9Bk | B69: 44505.421 | C69: 49834 | D69: vinay.vinay.v@gmail.com | E69: 919886346066 | F69: 17948 | H69: Deutsch In Tandem | J69: 6 | K69: 349 | M69: 349 | N69: INR | O69: FALSE | P69: card | Q69: captured | R69: https://community.likeminds.community/deutsch-in-tandem
A70: pay_HGV07CdZscdRzd | B70: 5/29/2021 11:22 AM | C70: 50113 | D70: vinay.vinay.v@gmail.com | E70: 919886346066 | F70: 17948 | H70: Learn German with Heer | I70: SILVER | J70: 1 | K70: 199 | M70: 199 | N70: INR | O70: FALSE | P70: card | Q70: captured | R70: https://hi.likeminds.community/d/heer-haria#Pricing
A71: pay_H9O2dvMT4E86QX | B71: 44505.5 | C71: 49834 | D71: subhakalak@gmail.com | E71: 919985198322 | F71: 17949 | H71: Deutsch In Tandem | J71: 6 | K71: 349 | M71: 349 | N71: INR | O71: FALSE | P71: upi | Q71: captured | R71: https://community.likeminds.community/deutsch-in-tandem
A72: pay_HI5BFuTClQCFGB | B72: 44233.475 | C72: 50113 | D72: subhakalak@gmail.com | E72: 919985198322 | F72: 17949 | H72: Learn German with Heer | I72: GOLD | J72: 1 | K72: 349 | M72: 349 | N72: INR | O72: FALSE | P72: upi | Q72: captured | R72: https://hi.likeminds.community/d/heer-haria#Pricing
A73: pay_H9Q3C7tKgBZQ5o | B73: 44505.582 | C73: 50029 | D73: hariprasad3785@gmail.com | E73: 918610147050 | F73: 17956 | H73: Bonjour Amis French | J73: 1 | K73: 99 | M73: 99 | N73: INR | O73: FALSE | P73: upi | Q73: captured | R73: https://hi.likeminds.community/d/bonjour-amis-french
A74: pay_HAkfIvBAUBySPN | B74: 5/14/2021 10:47 PM | C74: 50052 | D74: hariprasad3785@gmail.com | E74: 918610147050 | F74: 17956 | H74: Ishavasya Yoga & Relaxation | J74: 1 | K74: 99 | M74: 99 | N74: INR | O74: FALSE | P74: upi | Q74: captured | R74: https://hi.likeminds.community/d/ishavasya-yoga-relaxation
A75: pay_H9tt17iZr281dm | B75: 44535.798 | C75: 50073 | D75: vksndhle@gmail.com | E75: 917715861705 | F75: 17998 | H75: well being | J75: 1 | K75: 599 | M75: 599 | N75: INR | O75: FALSE | P75: upi | Q75: captured | R75: https://community.likeminds.community/well-being#Pricing
A76: pay_H9uru1DyUL2aLk | B76: 44535.84 | C76: 50073 | D76: divyablu7@gmail.com | E76: 918790446089 | F76: 18000 | H76: well being | J76: 1 | K76: 599 | M76: 599 | N76: INR | O76: FALSE | P76: upi | Q76: captured | R76: https://community.likeminds.community/well-being#Pricing
A77: pay_HKBXJfLnxtUUQg | B77: 44383.788 | C77: 50073 | D77: divyablu7@gmail.com | E77: 918790446089 | F77: 18000 | H77: Well Being | J77: 3 | K77: 1499 | M77: 1499 | N77: INR | O77: FALSE | P77: upi | Q77: captured | R77: https://hi.likeminds.community/well-being-renewal
A78: pay_H9vDxUbyoXY22n | B78: 44535.853 | C78: 50073 | D78: novonilghosh84@gmail.com | E78: 919884976841 | F78: 18495 | H78: well being | J78: 1 | K78: 599 | M78: 599 | N78: INR | O78: FALSE | P78: card | Q78: captured | R78: https://community.likeminds.community/well-being#Pricing
A79: pay_HHfNf43R4Qo1qZ | B79: 44202.424 | C79: 50073 | D79: novonilghosh84@gmail.com | E79: 919884976841 | F79: 18495 | H79: Well Being | J79: 3 | K79: 1499 | M79: 1499 | N79: INR | O79: FALSE | P79: card | Q79: captured | R79: https://community.likeminds.community/well-being#Pricing
A80: pay_H9vWhyCNGYWcZs | B80: 44535.865 | C80: 50073 | D80: sreeparnadasnath2015@gmail.com | E80: 919593380027 | F80: 18928 | H80: well being | J80: 1 | K80: 599 | M80: 599 | N80: INR | O80: FALSE | P80: card | Q80: captured | R80: https://community.likeminds.community/well-being#Pricing
A81: pay_HHeh4Rlkai5po3 | B81: 44202.396 | C81: 50073 | D81: sreeparnadasnath2015@gmail.com | E81: 919593380027 | F81: 18928 | H81: Well Being | J81: 3 | K81: 1499 | M81: 1499 | N81: INR | O81: FALSE | P81: card | Q81: captured | R81: https://community.likeminds.community/well-being#Pricing
A82: pay_H9vxMscJMKn9T0 | B82: 44535.889 | C82: 50073 | D82: nidhisharma1921@gmail.com | E82: 917042110059 | F82: 18025 | H82: well being | J82: 1 | K82: 599 | M82: 599 | N82: INR | O82: FALSE | P82: wallet | Q82: captured | R82: https://community.likeminds.community/well-being#Pricing
A83: pay_HNF0Glh5RnFwDg | B83: 6/15/2021 12:15 PM | C83: 50073 | D83: nidhisharma1921@gmail.com | E83: 917042110059 | F83: 18025 | H83: Well Being | J83: 1 | K83: 799 | M83: 799 | N83: INR | O83: FALSE | P83: wallet | Q83: captured | R83: https://community.likeminds.community/well-being
A84: pay_HAx9J6Mna3002q | B84: 5/15/2021 11:00 AM | C84: 50030 | D84: duraickkd@gmail.com | E84: 919443100747 | F84: 19270 | H84: Digital Writopreneur Hub | J84: 1 | K84: 99 | M84: 99 | N84: INR | O84: FALSE | P84: card | Q84: captured | R84: https://hi.likeminds.community/d/digital-writopreneurs-hub
A85: pay_HNyZNvgrRqJhVZ | B85: 6/17/2021 8:51 AM | C85: 50030 | D85: duraickkd@gmail.com | E85: 919443100747 | F85: 19270 | H85: Digital Writopreneur Hub | J85: 6 | K85: 349 | M85: 349 | N85: INR | O85: FALSE | P85: card | Q85: captured | R85: https://hi.likeminds.community/d/digital-writopreneurs-hub
A86: pay_HBC5xO2pTwDLjt | B86: 5/16/2021 1:42 AM | C86: 50039 | D86: alagates@gmail.com | E86: 919003024509 | F86: 18099 | H86: Happy Ashram | J86: 6 | K86: 349 | M86: 349 | N86: INR | O86: FALSE | P86: card | Q86: captured | R86: https://hi.likeminds.community/d/happy-ashram
A87: pay_HBCR6mjenxJD4B | B87: 5/16/2021 1:57 AM | C87: 50039 | D87: alagates@gmail.com | E87: 919003024509 | F87: 18099 | H87: Happy Ashram | J87: 6 | K87: 349 | M87: 349 | N87: INR | O87: FALSE | P87: card | Q87: captured | R87: https://hi.likeminds.community/d/happy-ashram
A88: pay_HBkfj5oUxjybyb | B88: 5/17/2021 11:27 AM | C88: 50046 | D88: avinash24490@gmail.com | E88: 919916965352 | F88: 18207 | H88: The Man Makeover | J88: 1 | K88: 99 | M88: 99 | N88: INR | O88: FALSE | P88: card | Q88: captured | R88: https://hi.likeminds.community/d/the-man-makeover
A89: pay_HOztAWDjQ9PWxF | B89: 6/19/2021 10:47 PM | C89: 50046 | D89: avinash24490@gmail.com | E89: 919916965352 | F89: 18207 | H89: The Man Makeover | J89: 1 | K89: 99 | M89: 99 | N89: INR | O89: FALSE | P89: card | Q89: captured | R89: https://hi.likeminds.community/d/the-man-makeover
A90: pay_HDFZOW2cuSTYZS | B90: 5/21/2021 6:22 AM | C90: 50030 | D90: anubhat268@gmail.com | E90: 919110266512 | F90: 18220 | H90: Digital Writopreneur Hub | J90: 1 | K90: 99 | M90: 99 | N90: INR | O90: FALSE | P90: upi | Q90: captured | R90: https://hi.likeminds.community/d/digital-writopreneurs-hub
A91: pay_HBnHaIMIUU8jKc | B91: 5/17/2021 1:59 PM | C91: 49859 | D91: anubhat268@gmail.com | E91: 919110266512 | F91: 18220 | H91: Ladies & Gentlemen | J91: 1 | K91: 99 | M91: 99 | N91: INR | O91: FALSE | P91: upi | Q91: captured | R91: https://community.likeminds.community/ladies-and-gentlemen
A92: pay_HBQ7q0iFaFOc0z | B92: 5/16/2021 3:20 PM | C92: 50073 | D92: rk.neurekar@gmail.com | E92: 919819599898 | F92: 18230 | H92: well being | J92: 1 | K92: 599 | M92: 599 | N92: INR | O92: FALSE | P92: upi | Q92: captured | R92: https://community.likeminds.community/well-being#Pricing
A93: pay_HHi61olsDnoUl0 | B93: 44202.534 | C93: 50073 | D93: rk.neurekar@gmail.com | E93: 919819599898 | F93: 18230 | H93: Well Being | J93: 3 | K93: 1499 | M93: 1499 | N93: INR | O93: FALSE | P93: upi | Q93: captured | R93: https://community.likeminds.community/well-being#Pricing
A94: pay_HBw679QrOF4YjL | B94: 5/17/2021 10:37 PM | C94: 50029 | D94: gaikwadabhishek5@gmail.com | E94: 917020209901 | F94: 18275 | H94: Bonjour Amis French | J94: 1 | K94: 99 | M94: 99 | N94: INR | O94: FALSE | P94: upi | Q94: captured | R94: https://hi.likeminds.community/d/bonjour-amis-french
A95: pay_HO7whQcPjj256f | B95: 6/17/2021 6:00 PM | C95: 50029 | D95: gaikwadabhishek5@gmail.com | E95: 917020209901 | F95: 18275 | H95: Bonjour Amis French | J95: 3 | K95: 199 | M95: 199 | N95: INR | O95: FALSE | P95: upi | Q95: captured | R95: https://hi.likeminds.community/d/bonjour-amis-french
A96: pay_HBWG2W5fG6koig | B96: 5/16/2021 9:20 PM | C96: 49997 | D96: guru_3@yahoo.com | E96: 919916242098 | F96: 18264 | H96: Ahoj: Let's Blog | J96: 3 | K96: 199 | M96: 199 | N96: INR | O96: FALSE | P96: upi | Q96: captured | R96: https://community.likeminds.community/ahoj-lets-blog
A97: pay_HCckOYAODDei7b | B97: 5/19/2021 4:20 PM | C97: 49991 | D97: skagarwal76@gmail.com | E97: 919765037370 | F97: 18336 | H97: DeBattlers | J97: 6 | K97: 349 | M97: 349 | N97: INR | O97: FALSE | P97: card | Q97: captured | R97: https://community.likeminds.community/debattlers
A98: pay_HCd0vbw1p0H5Uz | B98: 5/19/2021 4:36 PM | C98: 49991 | D98: skagarwal76@gmail.com | E98: 919765037370 | F98: 18336 | H98: DeBattlers | J98: 6 | K98: 349 | M98: 349 | N98: INR | O98: FALSE | P98: card | Q98: captured | R98: https://community.likeminds.community/debattlers
A99: pay_HCDtwy0wVALCu5 | B99: 5/18/2021 4:02 PM | C99: 50054 | D99: kumar.sushil.sushil625@gmail.com | E99: 917905958635 | F99: 18304 | H99: Rapto Bhara Jeevan | J99: 1 | K99: 99 | M99: 99 | N99: INR | O99: FALSE | P99: upi | Q99: captured | R99: https://hi.likeminds.community/d/rapto-bhara-jeevan
A100: pay_HMMsnoOmYL9buY | B100: 6/13/2021 7:19 AM | C100: 50054 | D100: kumar.sushil.sushil625@gmail.com | E100: 917905958635 | F100: 18304 | H100: Rapto Bhara Jeevan | J100: 3 | K100: 199 | M100: 199 | N100: INR | O100: FALSE | P100: upi | Q100: captured | R100: https://hi.likeminds.community/d/rapto-bhara-jeevan
...

Sheet Live Plan Data
A1: Community Name | B1: Community_id | C1: Plan_exists | D1: Amount - strike | E1: Amount | F1: Description | G1: Link | H1: Dump | I1: Plan_id | J1: Status
A2: A Blue Lotus Life | B2: 50143 | C2: TRUE | D2: 499 | E2: 199 | F2: <ul><li>Learn the art of long and short conversations at work</li><li>How do values shape behavior</li><li>Free participation with team in 1 OMGrr! event</li><li>1 Free ticket to attend 1 Cuddles &amp; Curveballs</li><li>Be Blue Bud: Practise Session for interviews &amp; presentation</li></ul><p><a href="https://rzp.io/l/DeutschInTandem" target="_blank"><br></a></p> | G2: https://payment.likeminds.community/?plan_id=13c0b553-5d91-4d31-b4bc-88d880628869 | H2: =IFERROR(__xludf.DUMMYFUNCTION("SPLIT(G2,""="")"),"https://payment.likeminds.community/?plan_id") -> https://payment.likeminds.community/?plan_id | I2: =IFERROR(__xludf.DUMMYFUNCTION("""COMPUTED_VALUE"""),"13c0b553-5d91-4d31-b4bc-88d880628869") -> 13c0b553-5d91-4d31-b4bc-88d880628869 | J2: Active
A3: A Blue Lotus Life | B3: 50143 | C3: TRUE | D3: 799 | E3: 399 | F3: <ul><li>Learn the art of long and short conversations at work</li><li>How do values shape behavior</li><li>Be Blue Blossom: Practise Session for interviews, public speaking, speech writing, presentation</li><li>Reasons for writing at work </li><li>'2F's that makes your writing thoughtful</li><li>Free participation with team in 2 OMGrr! events</li><li>2 Free ticket to attend 2 Cuddles &amp; Curveballs</li><li>Attend Workshops with an external speaker</li></ul><p><a href="https://rzp.io/l/DeutschInTandem" target="_blank"><br></a></p> | G3: https://payment.likeminds.community/?plan_id=f769f468-4a1f-47bd-a73b-f158d7cd9797 | H3: =IFERROR(__xludf.DUMMYFUNCTION("SPLIT(G3,""="")"),"https://payment.likeminds.community/?plan_id") -> https://payment.likeminds.community/?plan_id | I3: =IFERROR(__xludf.DUMMYFUNCTION("""COMPUTED_VALUE"""),"f769f468-4a1f-47bd-a73b-f158d7cd9797") -> f769f468-4a1f-47bd-a73b-f158d7cd9797 | J3: Active
A4: A Blue Lotus Life | B4: 50143 | C4: TRUE | D4: 1499 | E4: 999 | F4: <ul><li>Learn the art of long and short conversations at work.</li><li>Understand the importance of body language and being receptive</li><li>Reasons for writing at work. </li><li>'2F's that makes your writing thoughtful.</li><li>Master the art of being a good listener and speaker</li><li>Learn to paraphrase &amp; how to use it impactfully</li><li>Attend Workshops with an external speaker</li><li>Get access to one on one practice sessions for interviews, public speaking, speech writing, presentation.</li><li>Free participation with team in 3 OMGrr! events + 1 Family exclusive OMGrr!</li><li>3 Free ticket to attend 3 Cuddles &amp; Curveballs</li><li>1 session of Live A Blue Lotus Life which includes a one on one consultation.</li></ul><p><a href="https://rzp.io/l/DeutschInTandem" target="_blank"><br></a></p> | G4: https://payment.likeminds.community/?plan_id=5f18b70b-7596-4800-968b-3425c2266e5e | H4: =IFERROR(__xludf.DUMMYFUNCTION("SPLIT(G4,""="")"),"https://payment.likeminds.community/?plan_id") -> https://payment.likeminds.community/?plan_id | I4: =IFERROR(__xludf.DUMMYFUNCTION("""COMPUTED_VALUE"""),"5f18b70b-7596-4800-968b-3425c2266e5e") -> 5f18b70b-7596-4800-968b-3425c2266e5e | J4: Active
A5: A Meeting with Self | B5: 50146 | C5: TRUE | D5: 299 | E5: 99 | F5: <ul><li>Learn simple mindfulness techniques to breakthrough your mind &amp; its patterns</li><li>Identify your authentic self</li><li>Improve the quality of your life through regular mediation practice</li><li>Get access to Full moon Meditation session<a href="https://rzp.io/l/DeutschInTandem" target="_blank"><br></a></li></ul> | G5: https://payment.likeminds.community/?plan_id=c569cb32-9e1e-4231-a60f-b7dd838e051c | H5: =IFERROR(__xludf.DUMMYFUNCTION("SPLIT(G5,""="")"),"https://payment.likeminds.community/?plan_id") -> https://payment.likeminds.community/?plan_id | I5: =IFERROR(__xludf.DUMMYFUNCTION("""COMPUTED_VALUE"""),"c569cb32-9e1e-4231-a60f-b7dd838e051c") -> c569cb32-9e1e-4231-a60f-b7dd838e051c | J5: Active
A6: A Meeting with Self | B6: 50146 | C6: TRUE | D6: 499 | E6: 199 | F6: <ul><li>Learn simple mindfulness techniques to breakthrough your min &amp; its patterns</li><li>Identify your authentic self</li><li>Improve the quality of your life through regular mediation practice</li><li>Get access to Full moon Meditation session<a href="https://rzp.io/l/DeutschInTandem" target="_blank"><br></a></li></ul> | G6: https://payment.likeminds.community/?plan_id=507beaf4-02a0-4413-abe9-bfe08e9cd3f2 | H6: =IFERROR(__xludf.DUMMYFUNCTION("SPLIT(G6,""="")"),"https://payment.likeminds.community/?plan_id") -> https://payment.likeminds.community/?plan_id | I6: =IFERROR(__xludf.DUMMYFUNCTION("""COMPUTED_VALUE"""),"507beaf4-02a0-4413-abe9-bfe08e9cd3f2") -> 507beaf4-02a0-4413-abe9-bfe08e9cd3f2 | J6: Active
A7: A Meeting with Self | B7: 50146 | C7: TRUE | D7: 799 | E7: 349 | F7: <ul><li>Learn simple mindfulness techniques to breakthrough your mind &amp; its patterns</li><li>Identify your authentic self</li><li>Improve the quality of your life through regular mediation practice</li><li>Get access to Full moon Meditation session<a href="https://rzp.io/l/DeutschInTandem" target="_blank"><br></a></li></ul> | G7: https://payment.likeminds.community/?plan_id=aee90a54-bbfd-4a14-bca2-5f8528e05d07 | H7: =IFERROR(__xludf.DUMMYFUNCTION("SPLIT(G7,""="")"),"https://payment.likeminds.community/?plan_id") -> https://payment.likeminds.community/?plan_id | I7: =IFERROR(__xludf.DUMMYFUNCTION("""COMPUTED_VALUE"""),"aee90a54-bbfd-4a14-bca2-5f8528e05d07") -> aee90a54-bbfd-4a14-bca2-5f8528e05d07 | J7: Active
A8: Azhar's Speaking Club | B8: 50123 | C8: TRUE | D8: 499 | E8: 299 | F8: <p>(Focus – Communication, Basic to Upper-Intermediate Level)</p><ul><li>Attend 4 Live Webinars from any of the topics on English grammar, vocabulary, writing skills, Interview skills, Pronunciation, and Interpersonal skills</li><li>Participate in every week’s Community’s Challenges and improve your communication skills</li><li>Get 30 Minutes recorded on-demand videos on Effective Communication Skills – 2 Videos per week</li><li>Receive PDF English grammar, vocabulary and, writing drills to upskill your English proficiency skills (2 Worksheets per week)</li><li>Receive Bite-size video tips on Vocabulary, Grammar, and Pronunciation</li><li>Participate in Community Roleplays activities and develop persuasive speaking skills</li><li>Participate in Live / Chat Discussions and get tips from the experts<br></li></ul> | G8: https://payment.likeminds.community/?plan_id=f6c6a3a4-b29d-429e-96b6-e3c01572dfd7 | H8: =IFERROR(__xludf.DUMMYFUNCTION("SPLIT(G8,""="")"),"https://payment.likeminds.community/?plan_id") -> https://payment.likeminds.community/?plan_id | I8: =IFERROR(__xludf.DUMMYFUNCTION("""COMPUTED_VALUE"""),"f6c6a3a4-b29d-429e-96b6-e3c01572dfd7") -> f6c6a3a4-b29d-429e-96b6-e3c01572dfd7 | J8: Active
A9: Azhar's Speaking Club | B9: 50123 | C9: TRUE | D9: 1199 | E9: 499 | F9: <p>(Focus – Business Communication, Pre-Intermediate to Advanced Level)</p><ul><li>Attend 4 Live Webinars from any of the topics on Business grammar and vocabulary, Business writing, Meeting skills, Presentation, and Corporate Culture skills</li><li>Participate in Every week’s Community’s Challenges and improve your workplace communication skills</li><li>Get 30 Minutes recorded on-demand videos on Effective Communication Skills – 2 Videos per week</li><li>Receive PDF Business English grammar and vocabulary worksheets and improve your Business English Communication skills – 2 Worksheets per week</li><li>Receive Bite-size video tips on Vocabulary, Grammar, and Pronunciation</li><li>Participate in Community Roleplays activities and develop persuasive speaking skills</li><li>Participate in Live / Chat Discussions and get tips from the experts<br></li></ul> | G9: https://payment.likeminds.community/?plan_id=51e33f1a-4b78-4ca5-b009-6e460fbde9fa | H9: =IFERROR(__xludf.DUMMYFUNCTION("SPLIT(G9,""="")"),"https://payment.likeminds.community/?plan_id") -> https://payment.likeminds.community/?plan_id | I9: =IFERROR(__xludf.DUMMYFUNCTION("""COMPUTED_VALUE"""),"51e33f1a-4b78-4ca5-b009-6e460fbde9fa") -> 51e33f1a-4b78-4ca5-b009-6e460fbde9fa | J9: Active
A10: Azhar's Speaking Club | B10: 50123 | C10: TRUE | D10: 3999 | E10: 1999 | F10: <p>(Focus – Personalized Communication Goals)</p><ul><li>‘Speak Up’ Subscription FREE</li><li>‘Professional’ Subscription FREE</li><li>Get 4 Personalized One to One Private Lessons with Expert Trainer Dr. Azhar Ahmed. 30 Mins each session on General / Business Communication topics as per your choice. (Each session - 400, total worth ₹.1600)</li><li>Collaborate with Dr. Azhar and become a co-host/host for conducting his live webinars on Effective Communication Skills</li><li>Involve in Personalized speaking/writing challenges and receive individualized audio/written feedback and remedial. (4 Challenges/week)</li><li>Receive Personalized worksheet drills and overcome your communication flaws. <br></li></ul><p>‍</p><p>‍</p> | G10: https://payment.likeminds.community/?plan_id=035f8c9a-0438-4476-91eb-314a8b92181f | H10: =IFERROR(__xludf.DUMMYFUNCTION("SPLIT(G10,""="")"),"https://payment.likeminds.community/?plan_id") -> https://payment.likeminds.community/?plan_id | I10: =IFERROR(__xludf.DUMMYFUNCTION("""COMPUTED_VALUE"""),"035f8c9a-0438-4476-91eb-314a8b92181f") -> 035f8c9a-0438-4476-91eb-314a8b92181f | J10: Active
A11: BAKERPRENEURSHIP | B11: 50137 | C11: TRUE | D11: 299 | E11: 99 | F11: <ul><li>Interactive Sessions</li><li>Workshops to help you up your baking game</li><li>Enhance your Baking skills with our live training sessions</li><li>one-on-one consultations with community expert</li><li>Access to premium community of bakers<a href="https://rzp.io/l/DeutschInTandem" target="_blank">‍</a></li></ul><p><a href="https://rzp.io/l/DeutschInTandem" target="_blank">‍<br></a></p> | G11: https://payment.likeminds.community/?plan_id=56a4c42d-5825-40a2-822c-085d0bf62600 | H11: =IFERROR(__xludf.DUMMYFUNCTION("SPLIT(G11,""="")"),"https://payment.likeminds.community/?plan_id") -> https://payment.likeminds.community/?plan_id | I11: =IFERROR(__xludf.DUMMYFUNCTION("""COMPUTED_VALUE"""),"56a4c42d-5825-40a2-822c-085d0bf62600") -> 56a4c42d-5825-40a2-822c-085d0bf62600 | J11: Active
A12: BAKERPRENEURSHIP | B12: 50137 | C12: TRUE | D12: 499 | E12: 199 | F12: <ul><li>Interactive Sessions</li><li>Workshops to help you up your baking game</li><li>Enhance your Baking skills with our live training sessions</li><li>one-on-one consultations with community expert</li><li>Access to premium community of bakers</li><li>Monetization and collaborations<a href="https://rzp.io/l/DeutschInTandem" target="_blank"><br></a></li></ul> | G12: https://payment.likeminds.community/?plan_id=b3357429-e535-4d80-a3b8-248cd2cd4f9f | H12: =IFERROR(__xludf.DUMMYFUNCTION("SPLIT(G12,""="")"),"https://payment.likeminds.community/?plan_id") -> https://payment.likeminds.community/?plan_id | I12: =IFERROR(__xludf.DUMMYFUNCTION("""COMPUTED_VALUE"""),"b3357429-e535-4d80-a3b8-248cd2cd4f9f") -> b3357429-e535-4d80-a3b8-248cd2cd4f9f | J12: Active
A13: BAKERPRENEURSHIP | B13: 50137 | C13: TRUE | D13: 799 | E13: 349 | F13: <ul><li>Interactive Sessions</li><li>Workshops to help you up your baking game</li><li>Enhance your Baking skills with our live training sessions</li><li>one-on-one consultations with community expert</li><li>Access to premium community of bakers</li><li>Monetization and collaborations<a href="https://rzp.io/l/DeutschInTandem" target="_blank"><br></a></li></ul> | G13: https://payment.likeminds.community/?plan_id=7d5492e5-4806-4570-9fb4-d67785bb73f3 | H13: =IFERROR(__xludf.DUMMYFUNCTION("SPLIT(G13,""="")"),"https://payment.likeminds.community/?plan_id") -> https://payment.likeminds.community/?plan_id | I13: =IFERROR(__xludf.DUMMYFUNCTION("""COMPUTED_VALUE"""),"7d5492e5-4806-4570-9fb4-d67785bb73f3") -> 7d5492e5-4806-4570-9fb4-d67785bb73f3 | J13: Active
A14: Being Earthable | B14: 50065 | C14: TRUE | D14: 799 | E14: 349 | F14: <ul><li>Be a part of workshops/webinars from experts in low-waste living</li><li>Interactive sessions</li><li>Product Recommendations</li><li>Attend Community webinars to learn the DIY products that are sustainable.</li><li>One-One Consultation once a month</li></ul> | G14: https://payment.likeminds.community/?plan_id=913ed34f-a4bf-4efd-83eb-d64f7c21201c | H14: =IFERROR(__xludf.DUMMYFUNCTION("SPLIT(G14,""="")"),"https://payment.likeminds.community/?plan_id") -> https://payment.likeminds.community/?plan_id | I14: =IFERROR(__xludf.DUMMYFUNCTION("""COMPUTED_VALUE"""),"913ed34f-a4bf-4efd-83eb-d64f7c21201c") -> 913ed34f-a4bf-4efd-83eb-d64f7c21201c | J14: Active
A15: Being Earthable | B15: 50065 | C15: TRUE | D15: 1299 | E15: 599 | F15: <ul><li>Be a part of workshops/webinars from experts in low-waste living</li><li>Interactive sessions</li><li>Product Recommendations</li><li>Attend Community webinars to learn the DIY products that are sustainable.</li><li>3 One-One Consultation</li><li>25% off on the upcoming paid workshops</li></ul><p><a href="https://rzp.io/l/DeutschInTandem" target="_blank"><br></a></p> | G15: https://payment.likeminds.community/?plan_id=8e951c7b-6512-413a-acbd-8e5a4e455982 | H15: =IFERROR(__xludf.DUMMYFUNCTION("SPLIT(G15,""="")"),"https://payment.likeminds.community/?plan_id") -> https://payment.likeminds.community/?plan_id | I15: =IFERROR(__xludf.DUMMYFUNCTION("""COMPUTED_VALUE"""),"8e951c7b-6512-413a-acbd-8e5a4e455982") -> 8e951c7b-6512-413a-acbd-8e5a4e455982 | J15: Active
A16: Being Earthable | B16: 50065 | C16: TRUE | D16: 1699 | E16: 899 | F16: <ul><li>Be a part of workshops/webinars from experts in low-waste living</li><li>Interactive sessions</li><li>Product Recommendations</li><li>Attend Community webinars to learn the DIY products that are sustainable.</li><li>6 One-One Consultation</li><li>50% off on the upcoming paid workshops</li></ul><p><a href="https://rzp.io/l/DeutschInTandem" target="_blank"><br></a></p> | G16: https://payment.likeminds.community/?plan_id=48bc08a0-d834-4c70-aaa9-5a73eb900e8a | H16: =IFERROR(__xludf.DUMMYFUNCTION("SPLIT(G16,""="")"),"https://payment.likeminds.community/?plan_id") -> https://payment.likeminds.community/?plan_id | I16: =IFERROR(__xludf.DUMMYFUNCTION("""COMPUTED_VALUE"""),"48bc08a0-d834-4c70-aaa9-5a73eb900e8a") -> 48bc08a0-d834-4c70-aaa9-5a73eb900e8a | J16: Active
A17: Blogging Life | B17: 50015 | C17: TRUE | D17: 299 | E17: 149 | F17: <ul><li>SEO Techniques</li><li>Image Optimization</li><li>Interactive sessions</li><li>Know the Digital Marketing world</li></ul> | G17: https://payment.likeminds.community/?plan_id=44a32d15-1826-48af-9451-9cf9d50683c6 | H17: =IFERROR(__xludf.DUMMYFUNCTION("SPLIT(G17,""="")"),"https://payment.likeminds.community/?plan_id") -> https://payment.likeminds.community/?plan_id | I17: =IFERROR(__xludf.DUMMYFUNCTION("""COMPUTED_VALUE"""),"44a32d15-1826-48af-9451-9cf9d50683c6") -> 44a32d15-1826-48af-9451-9cf9d50683c6 | J17: Active
A18: Blogging Life | B18: 50015 | C18: TRUE | D18: 699 | E18: 349 | F18: <ul><li>SEO Techniques</li><li>Image Optimization</li><li>Interactive sessions</li><li>Know the Digital Marketing world</li><li>Extra Classes</li><li>Access to templates worth $30</li></ul> | G18: https://payment.likeminds.community/?plan_id=f4e45163-a32d-4772-ad0f-d4886e3e3e61 | H18: =IFERROR(__xludf.DUMMYFUNCTION("SPLIT(G18,""="")"),"https://payment.likeminds.community/?plan_id") -> https://payment.likeminds.community/?plan_id | I18: =IFERROR(__xludf.DUMMYFUNCTION("""COMPUTED_VALUE"""),"f4e45163-a32d-4772-ad0f-d4886e3e3e61") -> f4e45163-a32d-4772-ad0f-d4886e3e3e61 | J18: Active
A19: Blogging Life | B19: 50015 | C19: TRUE | D19: 999 | E19: 699 | F19: <ul><li>SEO Techniques</li><li>Image Optimization</li><li>Interactive sessions</li><li>Know the Digital Marketing world</li><li>Personal assistance in creating websites</li><li>Access to premium templates worth $59</li></ul> | G19: https://payment.likeminds.community/?plan_id=928c42ca-379d-4f02-8429-4aed5151bd31 | H19: =IFERROR(__xludf.DUMMYFUNCTION("SPLIT(G19,""="")"),"https://payment.likeminds.community/?plan_id") -> https://payment.likeminds.community/?plan_id | I19: =IFERROR(__xludf.DUMMYFUNCTION("""COMPUTED_VALUE"""),"928c42ca-379d-4f02-8429-4aed5151bd31") -> 928c42ca-379d-4f02-8429-4aed5151bd31 | J19: Active
A20: Blogging Life | B20: 50015 | C20: TRUE | G20: https://payment.likeminds.community/?plan_id=72f81c22-ab2b-4015-99d8-e4594a0b185f | H20: =IFERROR(__xludf.DUMMYFUNCTION("SPLIT(G20,""="")"),"https://payment.likeminds.community/?plan_id") -> https://payment.likeminds.community/?plan_id | I20: =IFERROR(__xludf.DUMMYFUNCTION("""COMPUTED_VALUE"""),"72f81c22-ab2b-4015-99d8-e4594a0b185f") -> 72f81c22-ab2b-4015-99d8-e4594a0b185f | J20: Active
A21: Bonjour Amis French | B21: 50029 | C21: TRUE | D21: 299 | E21: 99 | F21: <ul><li>Events</li><li>Exam prep</li><li>Interactive sessions</li><li>Know French Culture<a href="https://rzp.io/l/DeutschInTandem" target="_blank"><br></a></li></ul> | G21: https://payment.likeminds.community/?plan_id=plan_H4kF9Rb1Rappwf | H21: =IFERROR(__xludf.DUMMYFUNCTION("SPLIT(G21,""="")"),"https://payment.likeminds.community/?plan_id") -> https://payment.likeminds.community/?plan_id | I21: =IFERROR(__xludf.DUMMYFUNCTION("""COMPUTED_VALUE"""),"plan_H4kF9Rb1Rappwf") -> plan_H4kF9Rb1Rappwf | J21: Active
A22: Bonjour Amis French | B22: 50029 | C22: TRUE | D22: 499 | E22: 199 | F22: <ul><li>Events</li><li>Exam prep</li><li>Interactive sessions</li><li>Know French Culture<a href="https://rzp.io/l/DeutschInTandem" target="_blank"><br></a></li></ul> | G22: https://payment.likeminds.community/?plan_id=plan_H4kFA3Nlir02TM | H22: =IFERROR(__xludf.DUMMYFUNCTION("SPLIT(G22,""="")"),"https://payment.likeminds.community/?plan_id") -> https://payment.likeminds.community/?plan_id | I22: =IFERROR(__xludf.DUMMYFUNCTION("""COMPUTED_VALUE"""),"plan_H4kFA3Nlir02TM") -> plan_H4kFA3Nlir02TM | J22: Active
A23: Bonjour Amis French | B23: 50029 | C23: TRUE | D23: 799 | E23: 349 | F23: <ul><li>Events</li><li>Exam prep</li><li>Interactive sessions</li><li>Know French Culture<a href="https://rzp.io/l/DeutschInTandem" target="_blank"><br></a></li></ul> | G23: https://payment.likeminds.community/?plan_id=plan_H4kFAiqRh0KWfC | H23: =IFERROR(__xludf.DUMMYFUNCTION("SPLIT(G23,""="")"),"https://payment.likeminds.community/?plan_id") -> https://payment.likeminds.community/?plan_id | I23: =IFERROR(__xludf.DUMMYFUNCTION("""COMPUTED_VALUE"""),"plan_H4kFAiqRh0KWfC") -> plan_H4kFAiqRh0KWfC | J23: Active
A24: BRIDL360.CLUB | B24: 50114 | C24: TRUE | D24: 499 | E24: 249 | F24: <p><strong>•Get the Connection that could get you the contract</strong></p><p><strong>•Get the Lead that you were looking for</strong></p><p><strong>•Know what's happening, right now, in Real Estate</strong></p><p><strong>•Create beautiful Automations and funnels that are pre-designed to walk your buyer through each step of the sales process, and convert them from “Leads” into actual property buyer</strong></p><p><strong>•Get to know more from industry experts.</strong></p><p><strong>‍</strong></p><p><strong>‍</strong><br></p> | G24: https://payment.likeminds.community/?plan_id=6288ed1f-0ebf-4cf4-a9ad-be8645390b91 | H24: =IFERROR(__xludf.DUMMYFUNCTION("SPLIT(G24,""="")"),"https://payment.likeminds.community/?plan_id") -> https://payment.likeminds.community/?plan_id | I24: =IFERROR(__xludf.DUMMYFUNCTION("""COMPUTED_VALUE"""),"6288ed1f-0ebf-4cf4-a9ad-be8645390b91") -> 6288ed1f-0ebf-4cf4-a9ad-be8645390b91 | J24: Active
A25: BRIDL360.CLUB | B25: 50114 | C25: TRUE | D25: 1999 | E25: 719 | F25: <p><strong>•Get the Connection that could get you the contract</strong></p><p><strong>•Get the Lead that you were looking for</strong></p><p><strong>•Know what's happening, right now, in Real Estate</strong></p><p><strong>•Create beautiful Automations and funnels that are pre-designed to walk your buyer through each step of the sales process, and convert them from “Leads” into actual property buyer</strong></p><p><strong>•Get to know more from industry experts.</strong></p><p>‍</p><p><br></p> | G25: https://payment.likeminds.community/?plan_id=ef06f095-0bfb-46b5-a818-eb6dd3baf71d | H25: =IFERROR(__xludf.DUMMYFUNCTION("SPLIT(G25,""="")"),"https://payment.likeminds.community/?plan_id") -> https://payment.likeminds.community/?plan_id | I25: =IFERROR(__xludf.DUMMYFUNCTION("""COMPUTED_VALUE"""),"ef06f095-0bfb-46b5-a818-eb6dd3baf71d") -> ef06f095-0bfb-46b5-a818-eb6dd3baf71d | J25: Active
A26: BRIDL360.CLUB | B26: 50114 | C26: TRUE | D26: 2999 | E26: 1199 | F26: <p><strong>•Get the Connection that could get you the contract</strong></p><p><strong>•Get the Lead that you were looking for</strong></p><p><strong>•Know what's happening, right now, in Real Estate</strong></p><p><strong>•Create beautiful Automations and funnels that are pre-designed to walk your buyer through each step of the sales process, and convert them from “Leads” into actual property buyer</strong></p><p><strong>•Get to know more from industry experts</strong></p><p>‍</p><p>‍</p> | G26: https://payment.likeminds.community/?plan_id=4d78fcbc-c31f-478a-923e-aefec3f77d67 | H26: =IFERROR(__xludf.DUMMYFUNCTION("SPLIT(G26,""="")"),"https://payment.likeminds.community/?plan_id") -> https://payment.likeminds.community/?plan_id | I26: =IFERROR(__xludf.DUMMYFUNCTION("""COMPUTED_VALUE"""),"4d78fcbc-c31f-478a-923e-aefec3f77d67") -> 4d78fcbc-c31f-478a-923e-aefec3f77d67 | J26: Active
A27: BRIDL360.CLUB | B27: 50114 | C27: TRUE | D27: 5999 | E27: 2399 | F27: <p><strong>•Get the Connection that could get you the contract</strong></p><p><strong>•Get the Lead that you were looking for</strong></p><p><strong>•Know what's happening, right now, in Real Estate</strong></p><p><strong>•Create beautiful Automations and funnels that are pre-designed to walk your buyer through each step of the sales process, and convert them from “Leads” into actual property buyer</strong></p><p><strong>•Get to know more from industry experts</strong></p><p>‍</p><p>‍</p> | G27: https://payment.likeminds.community/?plan_id=b6444d56-895a-47c2-b77a-d9ce753a5aa5 | H27: =IFERROR(__xludf.DUMMYFUNCTION("SPLIT(G27,""="")"),"https://payment.likeminds.community/?plan_id") -> https://payment.likeminds.community/?plan_id | I27: =IFERROR(__xludf.DUMMYFUNCTION("""COMPUTED_VALUE"""),"b6444d56-895a-47c2-b77a-d9ce753a5aa5") -> b6444d56-895a-47c2-b77a-d9ce753a5aa5 | J27: Active
A28: BSB Life Academy | B28: 50066 | C28: TRUE | E28: 499 | F28: <ul><li>Fortnightly session by BSB on topics covering from his books.</li><li>Fortnightly session by BSB on topics on Goal setting, time management and career guidance</li><li>Discussions on topics from his podcast (Zindagi unplugged) decided by the community members</li><li>Answers to problems pertaining to personal and professional life</li><li>Innovative new events to be done every month, 20% discount for all the community members.</li><li>One 1-on-1, 20 mins session free</li><li>Get complimentary 'COVID-19' (ebook) - 19 articles to help you succeed during difficult times</li></ul><h5>*The above price is not inclusive of GST</h5><p>‍</p><p>‍</p><p>‍<br></p> | G28: https://payment.likeminds.community/?plan_id=f186703a-658d-44ee-8621-a60e6680e433 | H28: =IFERROR(__xludf.DUMMYFUNCTION("SPLIT(G28,""="")"),"https://payment.likeminds.community/?plan_id") -> https://payment.likeminds.community/?plan_id | I28: =IFERROR(__xludf.DUMMYFUNCTION("""COMPUTED_VALUE"""),"f186703a-658d-44ee-8621-a60e6680e433") -> f186703a-658d-44ee-8621-a60e6680e433 | J28: Active
A29: BSB Life Academy | B29: 50066 | C29: TRUE | E29: 999 | F29: <ul><li>Fortnightly session by BSB on topics covering from his books.</li><li>Fortnightly session by BSB on topics on Goal setting, time management and career guidance</li><li>Discussions on topics from his podcast (Zindagi unplugged) decided by the community members</li><li>Answers to problems pertaining to personal and professional life</li><li>Innovative new events to be done every month, 30% discount for all the community members</li><li>Two 1-on-1, 30 mins sessions free</li><li>Get complimentary '7 Mantras of Organic Success' (ebook) worth INR 99</li></ul><p>‍</p><p>‍</p><p><a href="https://rzp.io/l/DeutschInTandem" target="_blank"><br></a></p><h5>*The above price is not inclusive of GST</h5><p>‍</p> | G29: https://payment.likeminds.community/?plan_id=58951811-af90-4b0d-9a5d-c074b5dd060a | H29: =IFERROR(__xludf.DUMMYFUNCTION("SPLIT(G29,""="")"),"https://payment.likeminds.community/?plan_id") -> https://payment.likeminds.community/?plan_id | I29: =IFERROR(__xludf.DUMMYFUNCTION("""COMPUTED_VALUE"""),"58951811-af90-4b0d-9a5d-c074b5dd060a") -> 58951811-af90-4b0d-9a5d-c074b5dd060a | J29: Active
A30: BSB Life Academy | B30: 50066 | C30: TRUE | E30: 1999 | F30: <ul><li>Fortnightly session by BSB on topics covering from his books.</li><li>Fortnightly session by BSB on topics on Goal setting, time management and career guidance</li><li>Discussions on topics from his podcast (Zindagi unplugged) decided by the community members</li><li>Answers to problems pertaining to personal and professional life</li><li>Innovative new events to be done every month, 50% discount for all the community members</li><li>Four 1-on-1, 45 mins sessions free</li><li>Get complimentary signed copy of the book 'Design Your Life' worth INR 299</li><li>Get complimentary 'COVID-19' (ebook) - 19 articles to help you succeed during difficult times</li></ul><p><a href="https://rzp.io/l/DeutschInTandem" target="_blank"><br></a></p><h5>*The above price is not inclusive of GST</h5><p>‍</p> | G30: https://payment.likeminds.community/?plan_id=407b5ace-ff40-4be7-9e1c-71ed0332cb3a | H30: =IFERROR(__xludf.DUMMYFUNCTION("SPLIT(G30,""="")"),"https://payment.likeminds.community/?plan_id") -> https://payment.likeminds.community/?plan_id | I30: =IFERROR(__xludf.DUMMYFUNCTION("""COMPUTED_VALUE"""),"407b5ace-ff40-4be7-9e1c-71ed0332cb3a") -> 407b5ace-ff40-4be7-9e1c-71ed0332cb3a | J30: Active
A31: CCSB | B31: 50093 | C31: TRUE | E31: 299 | F31: <ul><li>‍<strong>Fortnightly Masterclasses on various topics like Interview Skills, Resume Building etc.</strong></li><li><strong>Group Discussions Preparations</strong></li><li><strong>Access to closed group, community access to stay in touch with like minded and also job seekers</strong></li><li><strong>Part of the learning group with access to Author of the group for learning and also get their questions answered live</strong></li><li><strong>Author's other products like video course and books with 40% discount</strong></li></ul><p>‍</p> | G31: https://payment.likeminds.community/?plan_id=9cbc76c9-da60-4fd1-b9f1-41e3b0dcb630 | H31: =IFERROR(__xludf.DUMMYFUNCTION("SPLIT(G31,""="")"),"https://payment.likeminds.community/?plan_id") -> https://payment.likeminds.community/?plan_id | I31: =IFERROR(__xludf.DUMMYFUNCTION("""COMPUTED_VALUE"""),"9cbc76c9-da60-4fd1-b9f1-41e3b0dcb630") -> 9cbc76c9-da60-4fd1-b9f1-41e3b0dcb630 | J31: Active
A32: CCSB | B32: 50093 | C32: TRUE | E32: 499 | F32: <ul><li><strong>Fortnightly Masterclasses on various topics like Interview Skills, Resume Building etc.</strong></li><li><strong>Exclusive Ask Me Anything Sessions</strong></li><li><strong>Group Discussions Preparations</strong></li><li><strong>Access to closed group, community access to stay in touch with like minded and also job seekers</strong></li><li><strong>Part of the learning group with access to Author of the group for learning and also get their questions answered live</strong></li><li><strong>Author's other products like video course and books with 50% discount</strong></li></ul><p><strong>‍</strong><a href="https://rzp.io/l/DeutschInTandem" target="_blank"><br></a></p> | G32: https://payment.likeminds.community/?plan_id=2003371e-6514-4404-9b97-73dbffff40f1 | H32: =IFERROR(__xludf.DUMMYFUNCTION("SPLIT(G32,""="")"),"https://payment.likeminds.community/?plan_id") -> https://payment.likeminds.community/?plan_id | I32: =IFERROR(__xludf.DUMMYFUNCTION("""COMPUTED_VALUE"""),"2003371e-6514-4404-9b97-73dbffff40f1") -> 2003371e-6514-4404-9b97-73dbffff40f1 | J32: Active
A33: CCSB | B33: 50093 | C33: TRUE | E33: 999 | F33: <ul><li><strong>Fortnightly Masterclasses on various topics like Interview Skills, Resume Building etc.</strong></li><li><strong>Exclusive Ask Me Anything Sessions</strong></li><li><strong>Group Discussions Preparations</strong></li><li><strong>Access to closed group, community access to stay in touch with like minded and also job seekers</strong></li><li><strong>Part of the learning group with access to Author of the group for learning and also get their questions answered live</strong></li><li><strong>Author's other products like video course and books with 60% discount</strong></li><li><strong>1:1 &nbsp;coaching / counselling session with the author</strong><a href="https://rzp.io/l/DeutschInTandem" target="_blank"><br></a></li></ul> | G33: https://payment.likeminds.community/?plan_id=f1b4fdcb-b227-4fe6-942b-cee2af33e993 | H33: =IFERROR(__xludf.DUMMYFUNCTION("SPLIT(G33,""="")"),"https://payment.likeminds.community/?plan_id") -> https://payment.likeminds.community/?plan_id | I33: =IFERROR(__xludf.DUMMYFUNCTION("""COMPUTED_VALUE"""),"f1b4fdcb-b227-4fe6-942b-cee2af33e993") -> f1b4fdcb-b227-4fe6-942b-cee2af33e993 | J33: Active
A34: CONFIDENCE BOOSTING CLUB | B34: 50150 | C34: TRUE | D34: 299 | E34: 99 | F34: <ul><li>You get to attend Live Classes</li><li>You will get access to Interactive sessions</li><li>Get real time feedback</li><li>You get a Lifetime Support (and a Friendly Mentor!)</li><li>Attend monthly community meet-ups and impromptu discussions</li></ul><p><a href="https://rzp.io/l/DeutschInTandem" target="_blank"><br></a></p> | G34: https://payment.likeminds.community/?plan_id=8097ae9e-393d-4c46-8330-5c8218f170ea | H34: =IFERROR(__xludf.DUMMYFUNCTION("SPLIT(G34,""="")"),"https://payment.likeminds.community/?plan_id") -> https://payment.likeminds.community/?plan_id | I34: =IFERROR(__xludf.DUMMYFUNCTION("""COMPUTED_VALUE"""),"8097ae9e-393d-4c46-8330-5c8218f170ea") -> 8097ae9e-393d-4c46-8330-5c8218f170ea | J34: Active
A35: CONFIDENCE BOOSTING CLUB | B35: 50150 | C35: TRUE | D35: 499 | E35: 199 | F35: <ul><li>You get to attend Live Classes</li><li>You will get access to Interactive sessions</li><li>Get real time feedback</li><li>You get a Lifetime Support (and a Friendly Mentor!)</li><li>Attend monthly community meet-ups and impromptu discussions</li></ul><p><a href="https://rzp.io/l/DeutschInTandem" target="_blank"><br></a></p> | G35: https://payment.likeminds.community/?plan_id=6797ea80-f4dd-4d12-aedd-a792f74454dc | H35: =IFERROR(__xludf.DUMMYFUNCTION("SPLIT(G35,""="")"),"https://payment.likeminds.community/?plan_id") -> https://payment.likeminds.community/?plan_id | I35: =IFERROR(__xludf.DUMMYFUNCTION("""COMPUTED_VALUE"""),"6797ea80-f4dd-4d12-aedd-a792f74454dc") -> 6797ea80-f4dd-4d12-aedd-a792f74454dc | J35: Active
A36: CONFIDENCE BOOSTING CLUB | B36: 50150 | C36: TRUE | D36: 799 | E36: 349 | F36: <ul><li>You get to attend Live Classes</li><li>You will get access to Interactive sessions</li><li>Get real time feedback</li><li>You get a Lifetime Support (and a Friendly Mentor!)</li><li>Attend monthly community meet-ups and impromptu discussion.</li></ul><p><a href="https://rzp.io/l/DeutschInTandem" target="_blank"><br></a></p> | G36: https://payment.likeminds.community/?plan_id=a3f34baa-f418-4590-8fb1-3128706ab202 | H36: =IFERROR(__xludf.DUMMYFUNCTION("SPLIT(G36,""="")"),"https://payment.likeminds.community/?plan_id") -> https://payment.likeminds.community/?plan_id | I36: =IFERROR(__xludf.DUMMYFUNCTION("""COMPUTED_VALUE"""),"a3f34baa-f418-4590-8fb1-3128706ab202") -> a3f34baa-f418-4590-8fb1-3128706ab202 | J36: Active
A37: Daily Skills Community | B37: 50129 | C37: TRUE | D37: 2999 | E37: 599 | F37: <p>‍</p><ul><li><strong>Daily Yoga &amp; Meditation sessions</strong></li><li><strong>Daily live training on one subject</strong></li><li><strong>Curated content to read, watch and learn</strong></li><li><strong>Daily growth hack tips</strong></li><li><strong>Free access to paid recorded courses</strong></li><li><strong>Promote courses, products and services through online and earn</strong></li><li><strong>Dedicated Social Media &amp; Instant Messaging platforms</strong>‍</li></ul><p>‍</p> | G37: https://payment.likeminds.community/?plan_id=37a030d7-0b74-4b28-abfc-95806ec318c9 | H37: =IFERROR(__xludf.DUMMYFUNCTION("SPLIT(G37,""="")"),"https://payment.likeminds.community/?plan_id") -> https://payment.likeminds.community/?plan_id | I37: =IFERROR(__xludf.DUMMYFUNCTION("""COMPUTED_VALUE"""),"37a030d7-0b74-4b28-abfc-95806ec318c9") -> 37a030d7-0b74-4b28-abfc-95806ec318c9 | J37: Active
A38: Design Forward | B38: 50047 | C38: TRUE | D38: 799 | E38: 349 | F38: <ul><li>Get access to "3 Days Short Course"</li><li>Get Mentorship Support</li><li>Get exclusive session through one to one call</li></ul><p><a href="https://rzp.io/l/DeutschInTandem" target="_blank"><br></a></p> | G38: https://payment.likeminds.community/?plan_id=6f23ca13-a6ac-4084-9c4d-51662e6072cc | H38: =IFERROR(__xludf.DUMMYFUNCTION("SPLIT(G38,""="")"),"https://payment.likeminds.community/?plan_id") -> https://payment.likeminds.community/?plan_id | I38: =IFERROR(__xludf.DUMMYFUNCTION("""COMPUTED_VALUE"""),"6f23ca13-a6ac-4084-9c4d-51662e6072cc") -> 6f23ca13-a6ac-4084-9c4d-51662e6072cc | J38: Active
A39: Design Forward | B39: 50047 | C39: TRUE | D39: 999 | E39: 599 | F39: <ul><li>Get access to "3 Days Short Course"</li><li>Get Mentorship Support</li><li>Get exclusive session through one to one call</li><li>Get your UI/UX portfolio review &amp; Project work feedback from community members and Coach. </li></ul><p><a href="https://rzp.io/l/DeutschInTandem" target="_blank"><br></a></p> | G39: https://payment.likeminds.community/?plan_id=1e63c928-755f-4efd-981f-f4db1dfbb3da | H39: =IFERROR(__xludf.DUMMYFUNCTION("SPLIT(G39,""="")"),"https://payment.likeminds.community/?plan_id") -> https://payment.likeminds.community/?plan_id | I39: =IFERROR(__xludf.DUMMYFUNCTION("""COMPUTED_VALUE"""),"1e63c928-755f-4efd-981f-f4db1dfbb3da") -> 1e63c928-755f-4efd-981f-f4db1dfbb3da | J39: Active
A40: Design Forward | B40: 50047 | C40: TRUE | D40: 1499 | E40: 999 | F40: <ul><li>Get access to "3 Days Short Course"</li><li>Get Mentorship Support</li><li>Get exclusive session through one to one call</li><li>Get your UI/UX portfolio review &amp; Project work feedback from community members and Coach. </li><li>Get Support and Guidance in building your UI/UX Portfolio</li></ul><p>‍</p> | G40: https://payment.likeminds.community/?plan_id=becefe33-f7ad-4b6c-afa2-9361ecb71e2c | H40: =IFERROR(__xludf.DUMMYFUNCTION("SPLIT(G40,""="")"),"https://payment.likeminds.community/?plan_id") -> https://payment.likeminds.community/?plan_id | I40: =IFERROR(__xludf.DUMMYFUNCTION("""COMPUTED_VALUE"""),"becefe33-f7ad-4b6c-afa2-9361ecb71e2c") -> becefe33-f7ad-4b6c-afa2-9361ecb71e2c | J40: Active
A41: Digital Writopreneurs Hub | B41: 50030 | C41: TRUE | D41: 299 | E41: 99 | F41: <ul><li>Weekly Events</li><li>Interactive sessions</li><li>Know the Writopreneurs Community</li><li>Specialized Chatrooms with real-time engagement<a href="https://rzp.io/l/DeutschInTandem" target="_blank"><br></a></li></ul> | G41: https://payment.likeminds.community/?plan_id=2eeed9e1-7198-434a-9265-8a4cb054ae66 | H41: =IFERROR(__xludf.DUMMYFUNCTION("SPLIT(G41,""="")"),"https://payment.likeminds.community/?plan_id") -> https://payment.likeminds.community/?plan_id | I41: =IFERROR(__xludf.DUMMYFUNCTION("""COMPUTED_VALUE"""),"2eeed9e1-7198-434a-9265-8a4cb054ae66") -> 2eeed9e1-7198-434a-9265-8a4cb054ae66 | J41: Active
A42: Digital Writopreneurs Hub | B42: 50030 | C42: TRUE | D42: 499 | E42: 199 | F42: <ul><li>Weekly Events</li><li>Become client ready</li><li>Interactive sessions</li><li>Know the Writopreneurs Community<a href="https://rzp.io/l/DeutschInTandem" target="_blank"><br></a></li></ul> | G42: https://payment.likeminds.community/?plan_id=b26c3eb2-a2fa-4041-bd96-0e6de8c84c1c | H42: =IFERROR(__xludf.DUMMYFUNCTION("SPLIT(G42,""="")"),"https://payment.likeminds.community/?plan_id") -> https://payment.likeminds.community/?plan_id | I42: =IFERROR(__xludf.DUMMYFUNCTION("""COMPUTED_VALUE"""),"b26c3eb2-a2fa-4041-bd96-0e6de8c84c1c") -> b26c3eb2-a2fa-4041-bd96-0e6de8c84c1c | J42: Active
A43: Digital Writopreneurs Hub | B43: 50030 | C43: TRUE | D43: 699 | E43: 349 | F43: <ul><li>Alternate day live sessions</li><li>Work as a Freelancer</li><li>Interactive sessions</li><li>Know the Writopreneurs Community</li><li>Focused Community Manager</li><li>Weekly special events<a href="https://rzp.io/l/DeutschInTandem" target="_blank"><br></a></li></ul> | G43: https://payment.likeminds.community/?plan_id=52ed98cd-6114-4448-a667-35ba78cf9e05 | H43: =IFERROR(__xludf.DUMMYFUNCTION("SPLIT(G43,""="")"),"https://payment.likeminds.community/?plan_id") -> https://payment.likeminds.community/?plan_id | I43: =IFERROR(__xludf.DUMMYFUNCTION("""COMPUTED_VALUE"""),"52ed98cd-6114-4448-a667-35ba78cf9e05") -> 52ed98cd-6114-4448-a667-35ba78cf9e05 | J43: Active
A44: Emptycup | B44: 50136 | C44: TRUE | D44: 399 | E44: 99 | F44: <ul><li>Fundamental Training</li><li>Get pro on Crypto!</li><li>Multi-step Research Training</li><li>Interactive Discussions</li></ul><p><a href="https://rzp.io/l/DeutschInTandem" target="_blank"><br></a></p> | G44: https://payment.likeminds.community/?plan_id=36cc0ab1-564a-4b61-9161-01d2227495a4 | H44: =IFERROR(__xludf.DUMMYFUNCTION("SPLIT(G44,""="")"),"https://payment.likeminds.community/?plan_id") -> https://payment.likeminds.community/?plan_id | I44: =IFERROR(__xludf.DUMMYFUNCTION("""COMPUTED_VALUE"""),"36cc0ab1-564a-4b61-9161-01d2227495a4") -> 36cc0ab1-564a-4b61-9161-01d2227495a4 | J44: Active
A45: Emptycup | B45: 50136 | C45: TRUE | D45: 499 | E45: 199 | F45: <ul><li>Fundamental Training</li><li>Get pro on Crypto!</li><li>Multi-step Research Training</li><li>Interactive Discussions</li></ul><p><a href="https://rzp.io/l/DeutschInTandem" target="_blank"><br></a></p> | G45: https://payment.likeminds.community/?plan_id=ba661b8e-7085-49b2-a1bd-259671a1b9f2 | H45: =IFERROR(__xludf.DUMMYFUNCTION("SPLIT(G45,""="")"),"https://payment.likeminds.community/?plan_id") -> https://payment.likeminds.community/?plan_id | I45: =IFERROR(__xludf.DUMMYFUNCTION("""COMPUTED_VALUE"""),"ba661b8e-7085-49b2-a1bd-259671a1b9f2") -> ba661b8e-7085-49b2-a1bd-259671a1b9f2 | J45: Active
A46: Emptycup | B46: 50136 | C46: TRUE | D46: 799 | E46: 349 | F46: <ul><li>Fundamental Training</li><li>Get pro on Crypto!</li><li>Multi-step Research Training</li><li>Interactive Discussions</li></ul><p><a href="https://rzp.io/l/DeutschInTandem" target="_blank"><br></a></p> | G46: https://payment.likeminds.community/?plan_id=3154e1c0-d3a1-44a7-a41a-24ee392e0009 | H46: =IFERROR(__xludf.DUMMYFUNCTION("SPLIT(G46,""="")"),"https://payment.likeminds.community/?plan_id") -> https://payment.likeminds.community/?plan_id | I46: =IFERROR(__xludf.DUMMYFUNCTION("""COMPUTED_VALUE"""),"3154e1c0-d3a1-44a7-a41a-24ee392e0009") -> 3154e1c0-d3a1-44a7-a41a-24ee392e0009 | J46: Active
A47: Energy Healing By Dr. Bharti Dua | B47: 50104 | C47: TRUE | D47: 399 | E47: 99 | F47: <ul><li>Daily Meditation Circle</li><li>Weekly Self Mastery Class</li><li>One to One Interaction</li><li>E-book for a Rich Mindset</li></ul><p>‍</p> | G47: https://payment.likeminds.community/?plan_id=121ebc9c-f6b0-469f-a3b8-08202d930e88 | H47: =IFERROR(__xludf.DUMMYFUNCTION("SPLIT(G47,""="")"),"https://payment.likeminds.community/?plan_id") -> https://payment.likeminds.community/?plan_id | I47: =IFERROR(__xludf.DUMMYFUNCTION("""COMPUTED_VALUE"""),"121ebc9c-f6b0-469f-a3b8-08202d930e88") -> 121ebc9c-f6b0-469f-a3b8-08202d930e88 | J47: Active
A48: Energy Healing By Dr. Bharti Dua | B48: 50104 | C48: TRUE | D48: 799 | E48: 199 | F48: <ul><li>Daily Meditation Circle</li><li>Weekly Self Mastery Class</li><li>One to One Interaction</li><li>E-book for a Rich Mindset</li></ul><p>‍</p><p>‍</p> | G48: https://payment.likeminds.community/?plan_id=554e5de6-fa9d-4328-93e1-3570b3380b57 | H48: =IFERROR(__xludf.DUMMYFUNCTION("SPLIT(G48,""="")"),"https://payment.likeminds.community/?plan_id") -> https://payment.likeminds.community/?plan_id | I48: =IFERROR(__xludf.DUMMYFUNCTION("""COMPUTED_VALUE"""),"554e5de6-fa9d-4328-93e1-3570b3380b57") -> 554e5de6-fa9d-4328-93e1-3570b3380b57 | J48: Active
A49: Energy Healing By Dr. Bharti Dua | B49: 50104 | C49: TRUE | D49: 999 | E49: 349 | F49: <ul><li>Daily Meditation Circle</li><li>Weekly Self Mastery Class</li><li>One to One Interaction</li><li>E-book for a Rich Mindset</li></ul><p>‍</p><p>‍</p> | G49: https://payment.likeminds.community/?plan_id=bd5bf2f2-bb3a-4db5-8f78-f9af6ff7cef9 | H49: =IFERROR(__xludf.DUMMYFUNCTION("SPLIT(G49,""="")"),"https://payment.likeminds.community/?plan_id") -> https://payment.likeminds.community/?plan_id | I49: =IFERROR(__xludf.DUMMYFUNCTION("""COMPUTED_VALUE"""),"bd5bf2f2-bb3a-4db5-8f78-f9af6ff7cef9") -> bd5bf2f2-bb3a-4db5-8f78-f9af6ff7cef9 | J49: Active
A50: Fight Diabetes Mellitus | B50: 50110 | C50: TRUE | D50: 499 | E50: 200 | F50: <ul><li>Attend regular fitness session</li><li>Ask your query to the expert regarding Diabetes Mellitus</li><li>10% discount for attending one paid event</li><li>Attend regular health awareness sessions for Diabetes Mellitus</li><li>Get access to practical Health Tips</li><li>The day’s motto to Fight Diabetes Mellitus<a href="https://rzp.io/l/DeutschInTandem" target="_blank"><br></a></li></ul> | G50: https://payment.likeminds.community/?plan_id=aa03b87f-173a-42bd-a1d6-2bf3b353dfa6 | H50: =IFERROR(__xludf.DUMMYFUNCTION("SPLIT(G50,""="")"),"https://payment.likeminds.community/?plan_id") -> https://payment.likeminds.community/?plan_id | I50: =IFERROR(__xludf.DUMMYFUNCTION("""COMPUTED_VALUE"""),"aa03b87f-173a-42bd-a1d6-2bf3b353dfa6") -> aa03b87f-173a-42bd-a1d6-2bf3b353dfa6 | J50: Active
A51: Fight Diabetes Mellitus | B51: 50110 | C51: TRUE | D51: 899 | E51: 600 | F51: <ul><li>Attend regular fitness sessions</li><li>Ask your query to the expert regarding Diabetes Mellitus</li><li>25% discount for attending one paid event</li><li>Attend regular health awareness sessions for Diabetes Mellitus</li><li>Get access to practical Health Tips</li><li>The day’s motto to Fight Diabetes Mellitus</li><li>Diet and Food Essentials Suggestions<a href="https://rzp.io/l/DeutschInTandem" target="_blank"><br></a></li></ul> | G51: https://payment.likeminds.community/?plan_id=7fd50cc4-b3b4-4a48-97eb-23ebb8013b4c | H51: =IFERROR(__xludf.DUMMYFUNCTION("SPLIT(G51,""="")"),"https://payment.likeminds.community/?plan_id") -> https://payment.likeminds.community/?plan_id | I51: =IFERROR(__xludf.DUMMYFUNCTION("""COMPUTED_VALUE"""),"7fd50cc4-b3b4-4a48-97eb-23ebb8013b4c") -> 7fd50cc4-b3b4-4a48-97eb-23ebb8013b4c | J51: Active
A52: Fight Diabetes Mellitus | B52: 50110 | C52: TRUE | D52: 1499 | E52: 1100 | F52: <ul><li>&nbsp;Attend regular fitness sessions</li><li>Ask your query to Dr. Nigel Gonsalves (PT) regarding Diabetes Mellitus</li><li>50% discount on consultation with Dr. Nigel Gonsalves (PT)</li><li>50% discount for attending one paid event</li><li>Attend regular health awareness sessions for Diabetes Mellitus</li><li>Get access to practical Health Tips</li><li>The day’s motto to Fight Diabetes Mellitus</li><li>Diet and Food Essentials Suggestions</li><li>Ergonomics Session</li><li>Lifestyle Modification Session<a href="https://rzp.io/l/DeutschInTandem" target="_blank"><br></a></li></ul> | G52: https://payment.likeminds.community/?plan_id=6ea82515-6670-4ad1-b591-539205579647 | H52: =IFERROR(__xludf.DUMMYFUNCTION("SPLIT(G52,""="")"),"https://payment.likeminds.community/?plan_id") -> https://payment.likeminds.community/?plan_id | I52: =IFERROR(__xludf.DUMMYFUNCTION("""COMPUTED_VALUE"""),"6ea82515-6670-4ad1-b591-539205579647") -> 6ea82515-6670-4ad1-b591-539205579647 | J52: Active
A53: Finowiz - The Financial Wizard | B53: 50173 | C53: TRUE | D53: 199 | E53: 99 | F53: <ul><li>Weekly Masterclass about Cryptocurrencies</li><li>Exclusive Ask me Anything session</li><li>Chat Support for Doubt Clearing</li><li>Regular 1 Trading Analysis with explanation of the Indicators used (For Educational Purpose)</li><li>Weekly Detailed Review of 1 Crypto Token/Coin </li><li>1 Personal Consultation Call for "15 Minutes" &nbsp; &nbsp; &nbsp; </li></ul><p><strong>*&nbsp;Pre-register right now&nbsp;for this&nbsp;price, Batches&nbsp;start from&nbsp;July 1,2021&nbsp;* &nbsp; </strong>&nbsp; &nbsp; &nbsp; &nbsp; &nbsp; &nbsp; &nbsp; &nbsp; &nbsp; &nbsp; &nbsp; &nbsp; &nbsp;</p> | G53: https://payment.likeminds.community/?plan_id=eaffabf1-37e8-4aee-ba89-b6dc8ff591ad | H53: =IFERROR(__xludf.DUMMYFUNCTION("SPLIT(G53,""="")"),"https://payment.likeminds.community/?plan_id") -> https://payment.likeminds.community/?plan_id | I53: =IFERROR(__xludf.DUMMYFUNCTION("""COMPUTED_VALUE"""),"eaffabf1-37e8-4aee-ba89-b6dc8ff591ad") -> eaffabf1-37e8-4aee-ba89-b6dc8ff591ad | J53: Active
A54: Finowiz - The Financial Wizard | B54: 50173 | C54: TRUE | D54: 499 | E54: 249 | F54: <ul><li>Weekly Masterclass about Cryptocurrencies</li><li>Exclusive Ask me Anything session</li><li>Chat Support for Doubt Clearing</li><li>Regular 1 Trading Analysis with explanation of the Indicators used (For Educational Purpose)</li><li>Weekly Detailed Review of 1 Crypto Token/Coin </li><li>3 Personal Consultation Call for "20 Minutes" &nbsp; &nbsp; &nbsp; &nbsp; &nbsp; &nbsp; &nbsp; &nbsp; &nbsp; &nbsp; &nbsp; &nbsp; &nbsp; &nbsp; &nbsp; &nbsp; &nbsp; &nbsp; &nbsp; &nbsp; &nbsp; &nbsp; &nbsp;</li></ul><p><strong>*&nbsp;Pre-register right now&nbsp;for this&nbsp;price, Batches&nbsp;start from&nbsp;July 1,2021&nbsp;* &nbsp;</strong><a href="https://rzp.io/l/DeutschInTandem" target="_blank"><br></a></p> | G54: https://payment.likeminds.community/?plan_id=403ad6be-18b8-49a1-9da8-dcaea3ce844f | H54: =IFERROR(__xludf.DUMMYFUNCTION("SPLIT(G54,""="")"),"https://payment.likeminds.community/?plan_id") -> https://payment.likeminds.community/?plan_id | I54: =IFERROR(__xludf.DUMMYFUNCTION("""COMPUTED_VALUE"""),"403ad6be-18b8-49a1-9da8-dcaea3ce844f") -> 403ad6be-18b8-49a1-9da8-dcaea3ce844f | J54: Active
A55: Finowiz - The Financial Wizard | B55: 50173 | C55: TRUE | D55: 899 | E55: 449 | F55: <ul><li>Weekly Masterclass about Cryptocurrencies</li><li>Exclusive Ask me Anything session</li><li>Chat Support for Doubt Clearing</li><li>Regular 1 Trading Analysis with explanation of the Indicators used (For Educational Purpose)</li><li>Weekly Detailed Review of 1 Crypto Token/Coin </li><li>6 Personal Consultation Call for "30 Minutes" &nbsp; &nbsp; </li></ul><p><strong>*&nbsp;Pre-register right now&nbsp;for this&nbsp;price, Batches&nbsp;start from&nbsp;July 1,2021&nbsp;* &nbsp;</strong>&nbsp; &nbsp; &nbsp; &nbsp; &nbsp; &nbsp; &nbsp; &nbsp; &nbsp; &nbsp; &nbsp; &nbsp; &nbsp; &nbsp; &nbsp; &nbsp; &nbsp; &nbsp; &nbsp; &nbsp; &nbsp;</p> | G55: https://payment.likeminds.community/?plan_id=1962a26a-8787-46e5-8379-11f84eab382a | H55: =IFERROR(__xludf.DUMMYFUNCTION("SPLIT(G55,""="")"),"https://payment.likeminds.community/?plan_id") -> https://payment.likeminds.community/?plan_id | I55: =IFERROR(__xludf.DUMMYFUNCTION("""COMPUTED_VALUE"""),"1962a26a-8787-46e5-8379-11f84eab382a") -> 1962a26a-8787-46e5-8379-11f84eab382a | J55: Active
A56: Flavors N Fitness | B56: 50091 | C56: TRUE | D56: 199 | E56: 99 | F56: <ul><li>home style meal plans</li><li>personalised and flexible plans</li><li>live sessions </li><li>different type of cusinies dishes </li></ul><p><a href="https://rzp.io/l/DeutschInTandem" target="_blank"><br></a></p> | G56: https://payment.likeminds.community/?plan_id=6f568db3-3b66-44e0-b839-fc9dc525714f | H56: =IFERROR(__xludf.DUMMYFUNCTION("SPLIT(G56,""="")"),"https://payment.likeminds.community/?plan_id") -> https://payment.likeminds.community/?plan_id | I56: =IFERROR(__xludf.DUMMYFUNCTION("""COMPUTED_VALUE"""),"6f568db3-3b66-44e0-b839-fc9dc525714f") -> 6f568db3-3b66-44e0-b839-fc9dc525714f | J56: Active
A57: Flavors N Fitness | B57: 50091 | C57: TRUE | D57: 499 | E57: 199 | F57: <ul><li>home style meal plans</li><li>personalised and flexible plans</li><li>live sessions </li><li>different type of cusinies dishes <a href="https://rzp.io/l/DeutschInTandem" target="_blank"><br></a></li></ul><p><a href="https://rzp.io/l/DeutschInTandem" target="_blank"><br></a></p> | G57: https://payment.likeminds.community/?plan_id=03766c45-7344-41e9-b606-d31dbe94af35 | H57: =IFERROR(__xludf.DUMMYFUNCTION("SPLIT(G57,""="")"),"https://payment.likeminds.community/?plan_id") -> https://payment.likeminds.community/?plan_id | I57: =IFERROR(__xludf.DUMMYFUNCTION("""COMPUTED_VALUE"""),"03766c45-7344-41e9-b606-d31dbe94af35") -> 03766c45-7344-41e9-b606-d31dbe94af35 | J57: Active
A58: Flavors N Fitness | B58: 50091 | C58: TRUE | D58: 799 | E58: 349 | F58: <ul><li>home style meal plans</li><li>personalized and flexible plans</li><li>live sessions </li><li>different type of cuisines dishes <a href="https://rzp.io/l/DeutschInTandem" target="_blank"><br></a></li></ul><p>‍</p><p><a href="https://rzp.io/l/DeutschInTandem" target="_blank"><br></a></p> | G58: https://payment.likeminds.community/?plan_id=5e235de0-5054-4c7f-a9e5-e1e2827227a9 | H58: =IFERROR(__xludf.DUMMYFUNCTION("SPLIT(G58,""="")"),"https://payment.likeminds.community/?plan_id") -> https://payment.likeminds.community/?plan_id | I58: =IFERROR(__xludf.DUMMYFUNCTION("""COMPUTED_VALUE"""),"5e235de0-5054-4c7f-a9e5-e1e2827227a9") -> 5e235de0-5054-4c7f-a9e5-e1e2827227a9 | J58: Active
A59: Focus Inside | B59: 50149 | C59: TRUE | D59: 999 | E59: 799 | F59: <ul><li>Group yoga sessions 5 times a week ( Mon-Fri)</li><li>Yoga Nidra sessions for mind relaxation</li><li>Meditation &amp; Pranayama practice sessions</li><li>An hour long power yoga challenge to burn more calories<a href="https://rzp.io/l/DeutschInTandem" target="_blank"><br></a></li></ul> | G59: https://payment.likeminds.community/?plan_id=56089366-6283-4505-9e69-267f7db76659 | H59: =IFERROR(__xludf.DUMMYFUNCTION("SPLIT(G59,""="")"),"https://payment.likeminds.community/?plan_id") -> https://payment.likeminds.community/?plan_id | I59: =IFERROR(__xludf.DUMMYFUNCTION("""COMPUTED_VALUE"""),"56089366-6283-4505-9e69-267f7db76659") -> 56089366-6283-4505-9e69-267f7db76659 | J59: Active
A60: Focus Inside | B60: 50149 | C60: TRUE | D60: 2499 | E60: 1999 | F60: <ul><li>Group yoga sessions 5 times a week ( Mon-Fri)</li><li>Yoga Nidra sessions for mind relaxation</li><li>Meditation &amp; Pranayama practice sessions</li><li>An hour long power yoga challenge to burn more calories<a href="https://rzp.io/l/DeutschInTandem" target="_blank">‍</a></li><li>1 Missed session will be compensated on weekends<a href="https://rzp.io/l/DeutschInTandem" target="_blank"><br></a></li></ul> | G60: https://payment.likeminds.community/?plan_id=b45c4241-78b2-499a-88f4-fd3ed315bcb2 | H60: =IFERROR(__xludf.DUMMYFUNCTION("SPLIT(G60,""="")"),"https://payment.likeminds.community/?plan_id") -> https://payment.likeminds.community/?plan_id | I60: =IFERROR(__xludf.DUMMYFUNCTION("""COMPUTED_VALUE"""),"b45c4241-78b2-499a-88f4-fd3ed315bcb2") -> b45c4241-78b2-499a-88f4-fd3ed315bcb2 | J60: Active
A61: Focus Inside | B61: 50149 | C61: TRUE | D61: 4999 | E61: 3799 | F61: <ul><li>Group yoga sessions 5 times a week ( Mon-Fri)</li><li>Yoga Nidra sessions for mind relaxation</li><li>Meditation &amp; Pranayama practice sessions</li><li>An hour long power yoga challenge to burn more calories<a href="https://rzp.io/l/DeutschInTandem" target="_blank">‍</a></li><li>2 Missed session will be compensated on weekends<a href="https://rzp.io/l/DeutschInTandem" target="_blank"><br></a></li></ul> | G61: https://payment.likeminds.community/?plan_id=ef615171-651d-4882-8309-d411063960ee | H61: =IFERROR(__xludf.DUMMYFUNCTION("SPLIT(G61,""="")"),"https://payment.likeminds.community/?plan_id") -> https://payment.likeminds.community/?plan_id | I61: =IFERROR(__xludf.DUMMYFUNCTION("""COMPUTED_VALUE"""),"ef615171-651d-4882-8309-d411063960ee") -> ef615171-651d-4882-8309-d411063960ee | J61: Active
A62: Focus Inside | B62: 50149 | C62: TRUE | D62: 4499 | E62: 3499 | F62: <p>Be a part of personalized 1-1 sessions for one month and get access to:</p><ul><li>Live online personalized classes</li><li>Personalized diet plan</li><li>1-1 sessions</li><li>Missed class will be compensated on weekends</li><li>Achieve your desired goals by personalized classes quickly</li></ul> | G62: https://payment.likeminds.community/?plan_id=ee032174-ef8e-461d-97d2-1ff3e70c7c6d | H62: =IFERROR(__xludf.DUMMYFUNCTION("SPLIT(G62,""="")"),"https://payment.likeminds.community/?plan_id") -> https://payment.likeminds.community/?plan_id | I62: =IFERROR(__xludf.DUMMYFUNCTION("""COMPUTED_VALUE"""),"ee032174-ef8e-461d-97d2-1ff3e70c7c6d") -> ee032174-ef8e-461d-97d2-1ff3e70c7c6d | J62: Active
A63: GAPD | B63: 50122 | C63: TRUE | D63: 1999 | E63: 399 | F63: <p>‍</p><ul><li><strong>Two personal sessions</strong></li><li><strong>10% off on all exclusive G.A.P.D. courses </strong></li><li><strong>Weekly assignments and individual assessment</strong></li><li><strong>Regular personal development content</strong></li><li><strong>Introspection training</strong></li><li><strong>Daily article on members selected topic</strong></li><li><strong>Get a chance to represent your self in front of the community</strong></li></ul><p>‍</p><p>‍</p><p>‍</p><p>‍</p><p>‍</p><p>‍</p><p>‍</p><p>‍</p><p>‍</p><p>‍</p><p>‍</p> | G63: https://payment.likeminds.community/?plan_id=410e1a5c-de81-4fab-9987-657dcf149c2f | H63: =IFERROR(__xludf.DUMMYFUNCTION("SPLIT(G63,""="")"),"https://payment.likeminds.community/?plan_id") -> https://payment.likeminds.community/?plan_id | I63: =IFERROR(__xludf.DUMMYFUNCTION("""COMPUTED_VALUE"""),"410e1a5c-de81-4fab-9987-657dcf149c2f") -> 410e1a5c-de81-4fab-9987-657dcf149c2f | J63: Active
A64: GAPD | B64: 50122 | C64: TRUE | D64: 2999 | E64: 499 | F64: <p><strong><br></strong></p><ul><li><strong>Two personal sessions every week</strong></li><li><strong>30% off on all exclusive G.A.P.D. courses</strong></li><li><strong>Weekly assignments and individual assessment</strong></li><li><strong>Regular personal development content</strong></li><li><strong>Introspection training</strong></li><li><strong>Daily article on members selected topic</strong></li><li><strong>Get a chance to represent your self</strong></li><li><strong>Constant track of learning</strong></li><li><strong>Monthly reports</strong></li><li><strong>Priority session booking</strong></li><li><strong>1 counseling session </strong></li></ul><p>‍</p><p>‍</p><p>‍</p><p>‍</p><p>‍</p><p>‍</p><p>‍</p> | G64: https://payment.likeminds.community/?plan_id=81761c14-7b3f-4b2a-8cef-79ad7fea54b7 | H64: =IFERROR(__xludf.DUMMYFUNCTION("SPLIT(G64,""="")"),"https://payment.likeminds.community/?plan_id") -> https://payment.likeminds.community/?plan_id | I64: =IFERROR(__xludf.DUMMYFUNCTION("""COMPUTED_VALUE"""),"81761c14-7b3f-4b2a-8cef-79ad7fea54b7") -> 81761c14-7b3f-4b2a-8cef-79ad7fea54b7 | J64: Active
A65: GAPD | B65: 50122 | C65: TRUE | D65: 4999 | E65: 799 | F65: <p>‍<strong><br></strong></p><ul><li><strong>Unlimited &nbsp;personal sessions on demand</strong></li><li><strong>40% off on all exclusive G.A.P.D. courses</strong></li><li><strong>Choose from 11 subjects for intensive specialization</strong></li><li><strong>Recognized certification in specialization</strong></li><li><strong>Personal assessment for tailored course delivery</strong></li><li><strong>Weekly assignments and individual assessment </strong></li><li><strong>Regular personal development content</strong></li><li><strong>Introspection training</strong></li><li><strong>Daily article on members selected topic</strong></li><li><strong>Get a chance to represent your self</strong></li><li><strong>Constant track of learning</strong></li><li><strong>Monthly reports</strong></li><li><strong>First Priority session booking</strong></li><li><strong>6 counseling session </strong></li></ul><p>‍</p><p>‍</p> | G65: https://payment.likeminds.community/?plan_id=49cba17b-86ad-4b5d-ba83-1f2c218851df | H65: =IFERROR(__xludf.DUMMYFUNCTION("SPLIT(G65,""="")"),"https://payment.likeminds.community/?plan_id") -> https://payment.likeminds.community/?plan_id | I65: =IFERROR(__xludf.DUMMYFUNCTION("""COMPUTED_VALUE"""),"49cba17b-86ad-4b5d-ba83-1f2c218851df") -> 49cba17b-86ad-4b5d-ba83-1f2c218851df | J65: Active
A66: Garv Malik | B66: 50086 | C66: TRUE | E66: 249 | F66: <ul><li>Daily 10pm Show</li><li>Surprise Celebrity Acts</li><li>Interactive Sessions</li><li>Inclusive of 30 shows worth INR 6,000</li></ul><p>‍</p> | G66: https://payment.likeminds.community/?plan_id=e57b1b7e-e366-44f5-ab73-706cdf1ef23b | H66: =IFERROR(__xludf.DUMMYFUNCTION("SPLIT(G66,""="")"),"https://payment.likeminds.community/?plan_id") -> https://payment.likeminds.community/?plan_id | I66: =IFERROR(__xludf.DUMMYFUNCTION("""COMPUTED_VALUE"""),"e57b1b7e-e366-44f5-ab73-706cdf1ef23b") -> e57b1b7e-e366-44f5-ab73-706cdf1ef23b | J66: Active
A67: Garv Malik | B67: 50086 | C67: TRUE | E67: 599 | F67: <ul><li>Daily 10pm Show</li><li>Surprise Celebrity Acts</li><li>Interactive Sessions</li><li>Inclusive of 90 shows worth INR 18,000</li></ul><h4><a href="https://rzp.io/l/DeutschInTandem" target="_blank"><br></a></h4> | G67: https://payment.likeminds.community/?plan_id=d636d641-38ca-445c-929c-90dad886af32 | H67: =IFERROR(__xludf.DUMMYFUNCTION("SPLIT(G67,""="")"),"https://payment.likeminds.community/?plan_id") -> https://payment.likeminds.community/?plan_id | I67: =IFERROR(__xludf.DUMMYFUNCTION("""COMPUTED_VALUE"""),"d636d641-38ca-445c-929c-90dad886af32") -> d636d641-38ca-445c-929c-90dad886af32 | J67: Active
A68: Garv Malik | B68: 50086 | C68: TRUE | E68: 999 | F68: <ul><li>Daily 10pm Show</li><li>Surprise Celebrity Acts</li><li>Interactive Sessions</li><li>Inclusive of 180 shows worth INR 36,000</li></ul><p><a href="https://rzp.io/l/DeutschInTandem" target="_blank"><br></a></p> | G68: https://payment.likeminds.community/?plan_id=66daae8c-82c7-410c-a217-562b894e22dc | H68: =IFERROR(__xludf.DUMMYFUNCTION("SPLIT(G68,""="")"),"https://payment.likeminds.community/?plan_id") -> https://payment.likeminds.community/?plan_id | I68: =IFERROR(__xludf.DUMMYFUNCTION("""COMPUTED_VALUE"""),"66daae8c-82c7-410c-a217-562b894e22dc") -> 66daae8c-82c7-410c-a217-562b894e22dc | J68: Active
A69: Graphology | B69: 50082 | C69: TRUE | D69: 5999 | E69: 2999 | F69: <ul><li>One time handwriting and signature analysis consultation on Zoom with Pavan Badllani</li><li>Q&amp;A support for a month with Pavan Badllani</li><li>1 month LikeMinds Community membership</li><li>Free 3 Hour Graphology Masterclass Sessions </li><li>Graphology e-books worth Rs.5,000</li></ul><p>‍</p><p>‍</p><p>‍</p><p><a href="https://rzp.io/l/DeutschInTandem" target="_blank"><br></a></p> | G69: https://payment.likeminds.community/?plan_id=22fd7677-6f7e-406b-855f-ce38886aea9d | H69: =IFERROR(__xludf.DUMMYFUNCTION("SPLIT(G69,""="")"),"https://payment.likeminds.community/?plan_id") -> https://payment.likeminds.community/?plan_id | I69: =IFERROR(__xludf.DUMMYFUNCTION("""COMPUTED_VALUE"""),"22fd7677-6f7e-406b-855f-ce38886aea9d") -> 22fd7677-6f7e-406b-855f-ce38886aea9d | J69: Active
A70: Graphology | B70: 50082 | C70: TRUE | D70: 9999 | E70: 4999 | F70: <ul><li>One time handwriting and signature analysis consultation on zoom </li><li>Q&amp;A support for 3 months with Pavan Badllani</li><li>3 month LikeMinds Community membership</li><li>Free 3 Hour Graphology Masterclass Sessions </li><li>Graphology e-books worth ₹5,000 </li><li>21 days handwriting and signature analysis assignments for reducing stress, emotional stability, personal growth, boosting self confidence &amp; self esteem worth ₹8,999</li></ul><p>‍</p><p>‍</p><p>‍</p><p>‍</p><p>‍<a href="https://rzp.io/l/DeutschInTandem" target="_blank"><br></a></p> | G70: https://payment.likeminds.community/?plan_id=6c27e352-6721-4371-83fc-5e9725b9a1bd | H70: =IFERROR(__xludf.DUMMYFUNCTION("SPLIT(G70,""="")"),"https://payment.likeminds.community/?plan_id") -> https://payment.likeminds.community/?plan_id | I70: =IFERROR(__xludf.DUMMYFUNCTION("""COMPUTED_VALUE"""),"6c27e352-6721-4371-83fc-5e9725b9a1bd") -> 6c27e352-6721-4371-83fc-5e9725b9a1bd | J70: Active
A71: Graphology | B71: 50082 | C71: TRUE | D71: 24999 | E71: 11999 | F71: <ul><li>One time handwriting and signature analysis consultation on zoom </li><li>Lifetime Q&amp;A support with Pavan Badllani</li><li>12 month LikeMinds Community membership</li><li>Free 3 Hour Graphology Masterclass Sessions </li><li>Graphology e-books worth ₹5,000 </li><li>21 days handwriting and signature analysis assignments for reducing stress, emotional stability, personal growth, boosting self confidence &amp; self esteem worth ₹8,999 </li><li>52 e-books for spotting different kinds of handwriting and signatures worth ₹10,000 </li><li>3 tickets to my live training sessions worth ₹15,000 </li><li>Lifetime Access to the Graphology Online Course and Exclusive Marketing Strategies on How To Earn upto ₹30,000 every month with a 30 day money back guarantee if you aren’t happy with the online course. </li><li>You will learn how to become a handwriting and signature analyst as a full time, part time professional or freelancer.</li></ul> | G71: https://payment.likeminds.community/?plan_id=c1e16f2b-ed2f-4563-b6a3-9bfd3eec0afc | H71: =IFERROR(__xludf.DUMMYFUNCTION("SPLIT(G71,""="")"),"https://payment.likeminds.community/?plan_id") -> https://payment.likeminds.community/?plan_id | I71: =IFERROR(__xludf.DUMMYFUNCTION("""COMPUTED_VALUE"""),"c1e16f2b-ed2f-4563-b6a3-9bfd3eec0afc") -> c1e16f2b-ed2f-4563-b6a3-9bfd3eec0afc | J71: Active
A72: Growing Buddies | B72: 50162 | C72: TRUE | D72: 999 | E72: 299 | F72: <ul><li>Weekly workshops on various growth topics</li><li>Promotion on Facebook group with 15k members and Facebook live once per month</li><li>Promotion through Instagram story feature for full month</li><li>Promotion through one Admin post introducing your brand for full month</li><li>Get your inspiring journey featured and promoted on our magazines, calendars launch, events, awards shows</li><li>Exclusive Ask me Anything sessions </li><li>Access to a premium community of budding entrepreneurs for collaborative growth and learning</li></ul><p>‍</p> | G72: https://payment.likeminds.community/?plan_id=16abfe26-e51b-4328-a59b-fceb8d9e9cd4 | H72: =IFERROR(__xludf.DUMMYFUNCTION("SPLIT(G72,""="")"),"https://payment.likeminds.community/?plan_id") -> https://payment.likeminds.community/?plan_id | I72: =IFERROR(__xludf.DUMMYFUNCTION("""COMPUTED_VALUE"""),"16abfe26-e51b-4328-a59b-fceb8d9e9cd4") -> 16abfe26-e51b-4328-a59b-fceb8d9e9cd4 | J72: Active
A73: Growing Buddies | B73: 50162 | C73: TRUE | D73: 1999 | E73: 499 | F73: <ul><li>Weekly workshops on various growth topics </li><li>Promotion on Facebook group with 15k members and Facebook live once per 3 months </li><li>Promotion through Instagram story feature for full 3 months </li><li>Promotion through one Admin post introducing your brand for full 3 months </li><li>Get your inspiring journey featured and promoted on our magazines, calendars launch, events, awards shows</li><li>Exclusive Ask me Anything sessions </li><li>Access to a premium community of budding entrepreneurs for collaborative growth and learning</li></ul><p>‍</p> | G73: https://payment.likeminds.community/?plan_id=3237ded3-a2e7-450e-bf3c-f640d5570805 | H73: =IFERROR(__xludf.DUMMYFUNCTION("SPLIT(G73,""="")"),"https://payment.likeminds.community/?plan_id") -> https://payment.likeminds.community/?plan_id | I73: =IFERROR(__xludf.DUMMYFUNCTION("""COMPUTED_VALUE"""),"3237ded3-a2e7-450e-bf3c-f640d5570805") -> 3237ded3-a2e7-450e-bf3c-f640d5570805 | J73: Active
A74: Growing Buddies | B74: 50162 | C74: TRUE | D74: 2999 | E74: 999 | F74: <ul><li>Weekly workshops on various growth topics </li><li>Promotion on Facebook group with 15k members and Facebook live once for full &nbsp;6months </li><li>Promotion through Instagram story feature for full 6 months </li><li>Promotion through one Admin post introducing your brand for full 6 months </li><li>Get your inspiring journey featured and promoted on our magazines, calendars launch, events, awards shows</li><li>Exclusive Ask me Anything sessions </li><li>Access to a premium community of budding entrepreneurs for collaborative growth and learning</li></ul><p>‍</p> | G74: https://payment.likeminds.community/?plan_id=1e7ff6de-6324-4bd3-950d-c240d942fda5 | H74: =IFERROR(__xludf.DUMMYFUNCTION("SPLIT(G74,""="")"),"https://payment.likeminds.community/?plan_id") -> https://payment.likeminds.community/?plan_id | I74: =IFERROR(__xludf.DUMMYFUNCTION("""COMPUTED_VALUE"""),"1e7ff6de-6324-4bd3-950d-c240d942fda5") -> 1e7ff6de-6324-4bd3-950d-c240d942fda5 | J74: Active
A75: Happiness Fountain | B75: 50079 | C75: TRUE | D75: 299 | E75: 99 | F75: <ul><li>Life Time support for Professional &amp; Personal Growth</li><li>Live Work Shop</li><li>Community Meet-ups</li><li>Live Healing &amp; Interactive Sessions</li></ul><p><a href="https://rzp.io/l/DeutschInTandem" target="_blank"><br></a></p> | G75: https://payment.likeminds.community/?plan_id=46974ce7-59e5-41d9-8696-c54064b74ccd | H75: =IFERROR(__xludf.DUMMYFUNCTION("SPLIT(G75,""="")"),"https://payment.likeminds.community/?plan_id") -> https://payment.likeminds.community/?plan_id | I75: =IFERROR(__xludf.DUMMYFUNCTION("""COMPUTED_VALUE"""),"46974ce7-59e5-41d9-8696-c54064b74ccd") -> 46974ce7-59e5-41d9-8696-c54064b74ccd | J75: Active
A76: Happiness Fountain | B76: 50079 | C76: TRUE | D76: 499 | E76: 199 | F76: <ul><li>Life Time support for Professional &amp; Personal Growth</li><li>Live Work Shop</li><li>Community Meet-ups</li><li>Live Healing &amp; Interactive Sessions</li></ul><p><a href="https://rzp.io/l/DeutschInTandem" target="_blank"><br></a></p> | G76: https://payment.likeminds.community/?plan_id=51fcc0ab-b372-4e6e-9e6d-4ce92a0f14db | H76: =IFERROR(__xludf.DUMMYFUNCTION("SPLIT(G76,""="")"),"https://payment.likeminds.community/?plan_id") -> https://payment.likeminds.community/?plan_id | I76: =IFERROR(__xludf.DUMMYFUNCTION("""COMPUTED_VALUE"""),"51fcc0ab-b372-4e6e-9e6d-4ce92a0f14db") -> 51fcc0ab-b372-4e6e-9e6d-4ce92a0f14db | J76: Active
A77: Happiness Fountain | B77: 50079 | C77: TRUE | D77: 799 | E77: 349 | F77: <ul><li>Life Time support for Professional &amp; Personal Growth</li><li>Live Work Shop</li><li>Community Meet-ups</li><li>Live Healing &amp; Interactive Sessions</li></ul><p>‍</p><p><a href="https://rzp.io/l/DeutschInTandem" target="_blank"><br></a></p> | G77: https://payment.likeminds.community/?plan_id=1604b1d4-82ec-4ba8-b274-b6b1f32382c6 | H77: =IFERROR(__xludf.DUMMYFUNCTION("SPLIT(G77,""="")"),"https://payment.likeminds.community/?plan_id") -> https://payment.likeminds.community/?plan_id | I77: =IFERROR(__xludf.DUMMYFUNCTION("""COMPUTED_VALUE"""),"1604b1d4-82ec-4ba8-b274-b6b1f32382c6") -> 1604b1d4-82ec-4ba8-b274-b6b1f32382c6 | J77: Active
A78: Happy Ashram | B78: 50039 | C78: TRUE | D78: 299 | E78: 99 | F78: <ul><li>Be a part of our daily online meetings to share your stories and experience</li><li>Attend our weekly sessions </li><li>Learn how to be financially independent </li><li>Get help in healing yourself emotionally, physically &amp; mentally</li><li>Understand the important of spirituality </li></ul><p><a href="https://rzp.io/l/DeutschInTandem" target="_blank"><br></a></p> | G78: https://payment.likeminds.community/?plan_id=a93dd58f-7877-4f52-9c49-76f904601d67 | H78: =IFERROR(__xludf.DUMMYFUNCTION("SPLIT(G78,""="")"),"https://payment.likeminds.community/?plan_id") -> https://payment.likeminds.community/?plan_id | I78: =IFERROR(__xludf.DUMMYFUNCTION("""COMPUTED_VALUE"""),"a93dd58f-7877-4f52-9c49-76f904601d67") -> a93dd58f-7877-4f52-9c49-76f904601d67 | J78: Active
A79: Happy Ashram | B79: 50039 | C79: TRUE | D79: 499 | E79: 199 | F79: <ul><li>Be a part of our daily online meetings to share your stories and experience</li><li>Attend our weekly sessions </li><li>Learn how to be financially independent </li><li>Get help in healing yourself emotionally, physically &amp; mentally</li><li>Understand the important of spirituality </li></ul><p><a href="https://rzp.io/l/DeutschInTandem" target="_blank"><br></a></p> | G79: https://payment.likeminds.community/?plan_id=7bfdf2da-c8b3-4f0c-a2b5-92d40e5e7694 | H79: =IFERROR(__xludf.DUMMYFUNCTION("SPLIT(G79,""="")"),"https://payment.likeminds.community/?plan_id") -> https://payment.likeminds.community/?plan_id | I79: =IFERROR(__xludf.DUMMYFUNCTION("""COMPUTED_VALUE"""),"7bfdf2da-c8b3-4f0c-a2b5-92d40e5e7694") -> 7bfdf2da-c8b3-4f0c-a2b5-92d40e5e7694 | J79: Active
A80: Happy Ashram | B80: 50039 | C80: TRUE | D80: 799 | E80: 349 | F80: <ul><li>Be a part of our daily online meetings to share your stories and experience</li><li>Attend our weekly sessions </li><li>Learn how to be financially independent </li><li>Get help in healing yourself emotionally, physically &amp; mentally</li><li>Understand the important of spirituality </li></ul><p><a href="https://rzp.io/l/DeutschInTandem" target="_blank"><br></a></p> | G80: https://payment.likeminds.community/?plan_id=5262aeef-2a7c-4547-b7e8-9820437b74e4 | H80: =IFERROR(__xludf.DUMMYFUNCTION("SPLIT(G80,""="")"),"https://payment.likeminds.community/?plan_id") -> https://payment.likeminds.community/?plan_id | I80: =IFERROR(__xludf.DUMMYFUNCTION("""COMPUTED_VALUE"""),"5262aeef-2a7c-4547-b7e8-9820437b74e4") -> 5262aeef-2a7c-4547-b7e8-9820437b74e4 | J80: Active
A81: Happy Living | B81: 50110 | C81: TRUE | D81: 299 | E81: 99 | F81: <ul><li>Mind Relaxation Sessions</li><li>Desktop Yoga Sessions</li><li>Divine diet</li><li>Art Therapy</li></ul><p><a href="https://rzp.io/l/DeutschInTandem" target="_blank"><br></a></p> | G81: https://payment.likeminds.community/?plan_id=aa03b87f-173a-42bd-a1d6-2bf3b353dfa6 | H81: =IFERROR(__xludf.DUMMYFUNCTION("SPLIT(G81,""="")"),"https://payment.likeminds.community/?plan_id") -> https://payment.likeminds.community/?plan_id | I81: =IFERROR(__xludf.DUMMYFUNCTION("""COMPUTED_VALUE"""),"aa03b87f-173a-42bd-a1d6-2bf3b353dfa6") -> aa03b87f-173a-42bd-a1d6-2bf3b353dfa6 | J81: Active
A82: Happy Living | B82: 50110 | C82: TRUE | D82: 499 | E82: 199 | F82: <ul><li>Mind Relaxation Sessions</li><li>Desktop Yoga Sessions</li><li>Divine diet</li><li>Art Therapy</li></ul><p><a href="https://rzp.io/l/DeutschInTandem" target="_blank"><br></a></p> | G82: https://payment.likeminds.community/?plan_id=7fd50cc4-b3b4-4a48-97eb-23ebb8013b4c | H82: =IFERROR(__xludf.DUMMYFUNCTION("SPLIT(G82,""="")"),"https://payment.likeminds.community/?plan_id") -> https://payment.likeminds.community/?plan_id | I82: =IFERROR(__xludf.DUMMYFUNCTION("""COMPUTED_VALUE"""),"7fd50cc4-b3b4-4a48-97eb-23ebb8013b4c") -> 7fd50cc4-b3b4-4a48-97eb-23ebb8013b4c | J82: Active
A83: Happy Living | B83: 50110 | C83: TRUE | D83: 799 | E83: 349 | F83: <ul><li>Mind Relaxation Sessions</li><li>Desktop Yoga Sessions</li><li>Divine diet</li><li>Art Therapy</li></ul><p><a href="https://rzp.io/l/DeutschInTandem" target="_blank"><br></a></p> | G83: https://payment.likeminds.community/?plan_id=6ea82515-6670-4ad1-b591-539205579647 | H83: =IFERROR(__xludf.DUMMYFUNCTION("SPLIT(G83,""="")"),"https://payment.likeminds.community/?plan_id") -> https://payment.likeminds.community/?plan_id | I83: =IFERROR(__xludf.DUMMYFUNCTION("""COMPUTED_VALUE"""),"6ea82515-6670-4ad1-b591-539205579647") -> 6ea82515-6670-4ad1-b591-539205579647 | J83: Active
A84: HEAL - Journey To Happiness | B84: 50026 | C84: TRUE | D84: 499 | E84: 199 | F84: <ul><li>Get access to all the programs. Join HEAL today!</li><li>Sessions on Personal Growth</li><li>Guided Meditations &amp; Workshops</li><li>Global Community that cares</li></ul><p>‍</p> | G84: https://payment.likeminds.community/?plan_id=810d1301-ec74-4cfa-9d0c-aeca3f9dbece | H84: =IFERROR(__xludf.DUMMYFUNCTION("SPLIT(G84,""="")"),"https://payment.likeminds.community/?plan_id") -> https://payment.likeminds.community/?plan_id | I84: =IFERROR(__xludf.DUMMYFUNCTION("""COMPUTED_VALUE"""),"810d1301-ec74-4cfa-9d0c-aeca3f9dbece") -> 810d1301-ec74-4cfa-9d0c-aeca3f9dbece | J84: Active
A85: HEAL - Journey To Happiness | B85: 50026 | C85: TRUE | D85: 899 | E85: 499 | F85: <ul><li>Get access to all the programs. Join HEAL today!</li><li>GIFT One Month of HEAL Subscription Free To Your Friend</li><li>Sessions on Personal Growth</li><li>Guided Meditations &amp; Workshops</li><li>Global Community that cares</li></ul><p><a href="https://rzp.io/l/DeutschInTandem" target="_blank"><br></a></p> | G85: https://payment.likeminds.community/?plan_id=1f55df2b-4424-4c5a-b687-272369dc16bc | H85: =IFERROR(__xludf.DUMMYFUNCTION("SPLIT(G85,""="")"),"https://payment.likeminds.community/?plan_id") -> https://payment.likeminds.community/?plan_id | I85: =IFERROR(__xludf.DUMMYFUNCTION("""COMPUTED_VALUE"""),"1f55df2b-4424-4c5a-b687-272369dc16bc") -> 1f55df2b-4424-4c5a-b687-272369dc16bc | J85: Active
A86: Hiraeth | B86: 12345 | C86: TRUE | D86: 299 | E86: 99 | F86: <ul><li>Events</li><li>Exam prep</li><li>Interactive sessions</li><li>Know German Culture</li></ul> | G86: https://payment.likeminds.community/?plan_id=18790be4-04cd-4484-a2f2-538d0485ec3f | H86: =IFERROR(__xludf.DUMMYFUNCTION("SPLIT(G86,""="")"),"https://payment.likeminds.community/?plan_id") -> https://payment.likeminds.community/?plan_id | I86: =IFERROR(__xludf.DUMMYFUNCTION("""COMPUTED_VALUE"""),"18790be4-04cd-4484-a2f2-538d0485ec3f") -> 18790be4-04cd-4484-a2f2-538d0485ec3f | J86: Active
A87: iQue Career Guide | B87: 50053 | C87: TRUE | D87: 999 | E87: 299 | F87: <ul><li>Unlimited access to all workshops happening across India</li><li>Access to regular Ask Me Anything sessions with Mr. Mohit Mangal</li><li>Access to expert career guidance &amp; QnA for Parents of Children studying in Class 9th to 12th</li><li>Flat 20% discount on all published handbooks</li><li>10% discount on any career counselling package fee</li><li>Access to premium community of parents and young adults for collaborative learnings and growth</li><li>Free digital copy of CBSE recommender career guide worth INR250</li></ul> | G87: https://payment.likeminds.community/?plan_id=plan_H4kFSqbs3Jk1ge | H87: =IFERROR(__xludf.DUMMYFUNCTION("SPLIT(G87,""="")"),"https://payment.likeminds.community/?plan_id") -> https://payment.likeminds.community/?plan_id | I87: =IFERROR(__xludf.DUMMYFUNCTION("""COMPUTED_VALUE"""),"plan_H4kFSqbs3Jk1ge") -> plan_H4kFSqbs3Jk1ge | J87: Active
A88: iQue Career Guide | B88: 50053 | C88: TRUE | D88: 1999 | E88: 599 | F88: <ul><li>Unlimited access to all workshops happening across India</li><li>Access to regular Ask Me Anything sessions with Mr. Mohit Mangal</li><li>Access to expert career guidance &amp; QnA for Parents of Children studying in Class 9th to 12th</li><li>Flat 20% discount on all published handbooks</li><li>20% discount on any career counselling package fee</li><li>Access to premium community of parents and young adults for collaborative learnings and growth</li><li>Free digital copy of CBSE recommender career guide worth INR250</li></ul> | G88: https://payment.likeminds.community/?plan_id=plan_H4kFTT8X6NVHAF | H88: =IFERROR(__xludf.DUMMYFUNCTION("SPLIT(G88,""="")"),"https://payment.likeminds.community/?plan_id") -> https://payment.likeminds.community/?plan_id | I88: =IFERROR(__xludf.DUMMYFUNCTION("""COMPUTED_VALUE"""),"plan_H4kFTT8X6NVHAF") -> plan_H4kFTT8X6NVHAF | J88: Active
A89: iQue Career Guide | B89: 50053 | C89: TRUE | D89: 2999 | E89: 899 | F89: <ul><li>Unlimited access to all workshops happening across India</li><li>Access to regular Ask Me Anything sessions with Mr. Mohit Mangal</li><li>Access to expert career guidance &amp; QnA for Parents of Children studying in Class 9th to 12th</li><li>Flat 20% discount on all published handbooks</li><li>1 free 30 mins one-on-one consulting session worth INR&nbsp;3000/-</li><li>30% discount on Career Counselling and Brain-mapping Package worth INR 7500/-</li><li>Access to premium community of parents and young adults for collaborative learnings and growth</li><li>Free digital copy of CBSE recommender career guide worth INR250</li></ul><p><a href="https://rzp.io/l/DeutschInTandem" target="_blank"><br></a></p> | G89: https://payment.likeminds.community/?plan_id=plan_H4kFU1RptbibnV | H89: =IFERROR(__xludf.DUMMYFUNCTION("SPLIT(G89,""="")"),"https://payment.likeminds.community/?plan_id") -> https://payment.likeminds.community/?plan_id | I89: =IFERROR(__xludf.DUMMYFUNCTION("""COMPUTED_VALUE"""),"plan_H4kFU1RptbibnV") -> plan_H4kFU1RptbibnV | J89: Active
A90: iQue Career Guide | B90: 50053 | C90: TRUE | D90: 4999 | E90: 1499 | F90: <ul><li>Unlimited access to all workshops happening across India</li><li>Access to regular Ask Me Anything sessions wit Mr. Mohit Mangal</li><li>Access to expert career guidance &amp; QnA for Parents of Children studying in Class 9th to 12th</li><li>Flat 20% discount on all published handbooks </li><li>1 Free Career Counselling and Brain-mapping Package worth INR 7500/-</li><li>Access to premium community of parents and young adults for collaborative learnings and growth</li><li>Free digital copy of CBSE recommender career guide worth INR250 </li></ul><p>‍</p> | G90: https://payment.likeminds.community/?plan_id=plan_H4kFUbuD1qYxSn | H90: =IFERROR(__xludf.DUMMYFUNCTION("SPLIT(G90,""="")"),"https://payment.likeminds.community/?plan_id") -> https://payment.likeminds.community/?plan_id | I90: =IFERROR(__xludf.DUMMYFUNCTION("""COMPUTED_VALUE"""),"plan_H4kFUbuD1qYxSn") -> plan_H4kFUbuD1qYxSn | J90: Active
A91: Ishavasya Yoga & Relaxation | B91: 50052 | C91: TRUE | D91: 299 | E91: 99 | F91: <ul><li>Daily Fitness Routine</li><li>Enhance Immunity</li><li>Interactive sessions</li><li>Mindfulness</li></ul> | G91: https://payment.likeminds.community/?plan_id=bd536099-969b-488d-aade-e2609a81db4c | H91: =IFERROR(__xludf.DUMMYFUNCTION("SPLIT(G91,""="")"),"https://payment.likeminds.community/?plan_id") -> https://payment.likeminds.community/?plan_id | I91: =IFERROR(__xludf.DUMMYFUNCTION("""COMPUTED_VALUE"""),"bd536099-969b-488d-aade-e2609a81db4c") -> bd536099-969b-488d-aade-e2609a81db4c | J91: Active
A92: Ishavasya Yoga & Relaxation | B92: 50052 | C92: TRUE | D92: 499 | E92: 199 | F92: <ul><li>Daily Fitness Routine</li><li>Enhance Immunity</li><li>Interactive sessions</li><li>Mindfulness</li></ul><p><a href="https://rzp.io/l/DeutschInTandem" target="_blank"><br></a></p> | G92: https://payment.likeminds.community/?plan_id=fe9c730b-e9f8-45a3-b642-1f67dc84a146 | H92: =IFERROR(__xludf.DUMMYFUNCTION("SPLIT(G92,""="")"),"https://payment.likeminds.community/?plan_id") -> https://payment.likeminds.community/?plan_id | I92: =IFERROR(__xludf.DUMMYFUNCTION("""COMPUTED_VALUE"""),"fe9c730b-e9f8-45a3-b642-1f67dc84a146") -> fe9c730b-e9f8-45a3-b642-1f67dc84a146 | J92: Active
A93: Ishavasya Yoga & Relaxation | B93: 50052 | C93: TRUE | D93: 799 | E93: 349 | F93: <ul><li>Daily Fitness Routine</li><li>Enhance Immunity</li><li>Interactive sessions</li><li>Mindfulness</li></ul><p><a href="https://rzp.io/l/DeutschInTandem" target="_blank"><br></a></p> | G93: https://payment.likeminds.community/?plan_id=17a16a93-d1f3-46a0-bcb3-daabf6cf759d | H93: =IFERROR(__xludf.DUMMYFUNCTION("SPLIT(G93,""="")"),"https://payment.likeminds.community/?plan_id") -> https://payment.likeminds.community/?plan_id | I93: =IFERROR(__xludf.DUMMYFUNCTION("""COMPUTED_VALUE"""),"17a16a93-d1f3-46a0-bcb3-daabf6cf759d") -> 17a16a93-d1f3-46a0-bcb3-daabf6cf759d | J93: Active
A94: Kash Studios | B94: 50148 | C94: TRUE | D94: 399 | E94: 199 | F94: <p></p><ul><li>Learn about drawing basics, VFX, SFX, writing skills, recording voiceovers</li><li>Discuss various topics</li><li>Attend live sessions tutorials and tips</li><li>Improve skills involved in creating animation from start to end</li><li>Learn professional animation</li></ul><p>‍<a href="https://rzp.io/l/DeutschInTandem" target="_blank"><br></a></p><p><a href="https://rzp.io/l/DeutschInTandem" target="_blank"><br></a></p><p>‍</p> | G94: https://payment.likeminds.community/?plan_id=79e54610-9547-4fa6-b843-45e6fe54ca0a | H94: =IFERROR(__xludf.DUMMYFUNCTION("SPLIT(G94,""="")"),"https://payment.likeminds.community/?plan_id") -> https://payment.likeminds.community/?plan_id | I94: =IFERROR(__xludf.DUMMYFUNCTION("""COMPUTED_VALUE"""),"79e54610-9547-4fa6-b843-45e6fe54ca0a") -> 79e54610-9547-4fa6-b843-45e6fe54ca0a | J94: Active
A95: Kash Studios | B95: 50148 | C95: TRUE | D95: 499 | E95: 399 | F95: <ul><li>Learn about drawing basics, VFX, SFX, writing skills, recording voiceovers</li><li>Discuss various topics</li><li>Attend live sessions tutorials and tips</li><li>Improve skills involved in creating animation from start to end</li><li>Learn professional animation</li></ul><p>‍<a href="https://rzp.io/l/DeutschInTandem" target="_blank"><br></a></p><p><a href="https://rzp.io/l/DeutschInTandem" target="_blank"><br></a></p> | G95: https://payment.likeminds.community/?plan_id=95ac66af-ca1c-4dcd-9f5d-44a3427e5109 | H95: =IFERROR(__xludf.DUMMYFUNCTION("SPLIT(G95,""="")"),"https://payment.likeminds.community/?plan_id") -> https://payment.likeminds.community/?plan_id | I95: =IFERROR(__xludf.DUMMYFUNCTION("""COMPUTED_VALUE"""),"95ac66af-ca1c-4dcd-9f5d-44a3427e5109") -> 95ac66af-ca1c-4dcd-9f5d-44a3427e5109 | J95: Active
A96: Kash Studios | B96: 50148 | C96: TRUE | D96: 1499 | E96: 899 | F96: <p></p><ul><li>Learn about drawing basics, VFX, SFX, writing skills, recording voiceovers</li><li>Discuss various topics</li><li>Attend live sessions tutorials and tips</li><li>Improve skills involved in creating animation from start to end</li><li>Learn professional animation</li></ul><p>‍<a href="https://rzp.io/l/DeutschInTandem" target="_blank"><br></a></p><p><a href="https://rzp.io/l/DeutschInTandem" target="_blank"><br></a></p><p>‍</p> | G96: https://payment.likeminds.community/?plan_id=33dba64d-bd0d-4bcd-9282-f03dab6aedc2 | H96: =IFERROR(__xludf.DUMMYFUNCTION("SPLIT(G96,""="")"),"https://payment.likeminds.community/?plan_id") -> https://payment.likeminds.community/?plan_id | I96: =IFERROR(__xludf.DUMMYFUNCTION("""COMPUTED_VALUE"""),"33dba64d-bd0d-4bcd-9282-f03dab6aedc2") -> 33dba64d-bd0d-4bcd-9282-f03dab6aedc2 | J96: Active
A97: Learn German with Heer | B97: 50113 | C97: TRUE | E97: 499 | F97: <ul><li>Daily learning of minimum 15 vocabulary words and its usage</li><li>Daily news in German</li><li>A1, A2 and B1 level preparation which includes - Emails, Letters, Speaking Exercise, Reading and Solving Texts, and Grammar Exercise</li><li>Twice a week interactive session for speaking and grammar</li><li>Four days a week worksheet solving and doubt solving</li><li>A Special Guest Delivery Lecture from a German native to learn about culture of Germany</li><li>A Special Lecture Delivery for universities application and top universities of Germany once a month</li><li>Test to be conducted once a week</li><li>Regular updates on job opportunities in Germany</li></ul> | G97: https://payment.likeminds.community/?plan_id=c9a0eaa9-4fc6-4b8b-9583-03644deb2281 | H97: =IFERROR(__xludf.DUMMYFUNCTION("SPLIT(G97,""="")"),"https://payment.likeminds.community/?plan_id") -> https://payment.likeminds.community/?plan_id | I97: =IFERROR(__xludf.DUMMYFUNCTION("""COMPUTED_VALUE"""),"c9a0eaa9-4fc6-4b8b-9583-03644deb2281") -> c9a0eaa9-4fc6-4b8b-9583-03644deb2281 | J97: Active
A98: Learn German with Heer | B98: 50113 | C98: TRUE | E98: 1349 | F98: <ul><li>Daily learning of minimum 15 vocabulary words and its usage</li><li>Daily news in German</li><li>A1, A2 and B1 level preparation which includes - Emails, Letters, Speaking Exercise, Reading and Solving Texts, and Grammar Exercise</li><li>Twice a week interactive session for speaking and grammar</li><li>Four days a week worksheet solving and doubt solving</li><li>A Special Guest Delivery Lecture from a German native to learn about culture of Germany</li><li>A Special Lecture Delivery for universities application and top universities of Germany once a month</li><li>Test to be conducted once a week</li><li>Regular updates on job opportunities in Germany</li></ul> | G98: https://payment.likeminds.community/?plan_id=b4921819-7640-4509-b07f-84ba27b31e4f | H98: =IFERROR(__xludf.DUMMYFUNCTION("SPLIT(G98,""="")"),"https://payment.likeminds.community/?plan_id") -> https://payment.likeminds.community/?plan_id | I98: =IFERROR(__xludf.DUMMYFUNCTION("""COMPUTED_VALUE"""),"b4921819-7640-4509-b07f-84ba27b31e4f") -> b4921819-7640-4509-b07f-84ba27b31e4f | J98: Active
